Workbook

Sheet 01_INPUTS
A1: 01_INPUTS — Única interfaz de carga manual: Identificación, Condiciones de Ronda y Decisiones D1–D8
A2: Azul = celda editable (decisión CADIZ o condición de ronda publicada por CESIM). Negro = fórmula de arrastre (edítese solo si CESIM publica un valor nuevo). Gris = dato histórico real (Ronda 0/1, no editar). Para agregar una ronda nueva: completar la columna de esa ronda; el resto de las hojas ya está preparado hasta la Ronda 12. | U2: PESIMISTA
U3: OPTIMISTA
A4: Bloque | B4: Variable | C4: Dimensión | D4: Unidad | E4: Tipo | F4: Fuente | G4: Ronda 0 | H4: Ronda 1 | I4: Ronda 2 | J4: Ronda 3 | K4: Ronda 4 | L4: Ronda 5 | M4: Ronda 6 | N4: Ronda 7 | O4: Ronda 8 | P4: Ronda 9 | Q4: Ronda 10 | R4: Ronda 11 | S4: Ronda 12 | U4: BASE
A5: SECCIÓN [SUPUESTO PROPIO] · MATRIZ DE SENSIBILIDAD (planificación propia, NO es una regla CESIM — no afecta Ronda 2 con Escenario Activo=BASE)
A6: Pesimista/Optimista en C/D → (Base fija en 0%, col. E oculta a propósito) | C6: Pesimista | D6: Optimista | E6: Base (fija, oculta) | U6: Equilibrado
A7: SENS · Supuesto propio | B7: Desvío en Crecimiento de Mercado (vs. condición publicada) | C7: -0.03 | D7: 0.03 | E7: 0 | F7: CESIM R2 | U7: Precio bajo
A8: SENS · Supuesto propio | B8: Agresividad de la Competencia (recorte a la cuota efectiva de CADIZ) | C8: 0.05 | D8: 0 | E8: 0 | F8: CESIM R2 | U8: Características
A9: SENS · Supuesto propio | B9: Escenario Activo | C9: BASE | D9: texto | E9: DECISIÓN CADIZ (planificación) | F9: Ver comentario | U9: Sostenibilidad
A10: SENS · Supuesto propio | B10: Factor de Crecimiento Activo (calculado) | C10: =INDEX(C7:E7,MATCH(01_INPUTS!$C$9,$U$2:$U$4,0)) -> 0 | D10: % | E10: CÁLCULO | F10: Ver comentario | U10: Marca
A11: SENS · Supuesto propio | B11: Factor de Competencia Activo (calculado) | C11: =INDEX(C8:E8,MATCH(01_INPUTS!$C$9,$U$2:$U$4,0)) -> 0 | D11: % | E11: CÁLCULO | F11: Ver comentario
U12: 1
A13: SECCIÓN A · IDENTIFICACIÓN | U13: 2
A14: A. Identificación | B14: Número de ronda | C14: - | D14: n° | E14: CÁLCULO | G14: 0 | H14: 1 | I14: 2 | J14: 3 | K14: 4 | L14: 5 | M14: 6 | N14: 7 | O14: 8 | P14: 9 | Q14: 10 | R14: 11 | S14: 12 | U14: 3
A15: A. Identificación | B15: Escenario | C15: - | D15: texto | E15: DECISIÓN CADIZ | F15: Ver comentario | G15: n/a (histórico) | H15: n/a (histórico) | I15: A
A16: A. Identificación | B16: Estado | C16: - | D16: REAL/PLAN/SIM | E16: DECISIÓN CADIZ | F16: CESIM R2 | G16: REAL | H16: REAL | I16: PLAN | J16: PLAN
A17: A. Identificación | B17: RONDA_ACTIVA (calculado) | C17: - | D17: VERDADERO/FALSO | E17: CÁLCULO | F17: Ver comentario | G17: =TRUE() -> TRUE | H17: =TRUE() -> TRUE | I17: =AND(OR(I16="PLAN",I16="SIM",I16="REAL"),ISNUMBER(I110)) -> TRUE | J17: =AND(OR(J16="PLAN",J16="SIM",J16="REAL"),ISNUMBER(J110)) -> FALSE | K17: =AND(OR(K16="PLAN",K16="SIM",K16="REAL"),ISNUMBER(K110)) -> FALSE | L17: =AND(OR(L16="PLAN",L16="SIM",L16="REAL"),ISNUMBER(L110)) -> FALSE | M17: =AND(OR(M16="PLAN",M16="SIM",M16="REAL"),ISNUMBER(M110)) -> FALSE | N17: =AND(OR(N16="PLAN",N16="SIM",N16="REAL"),ISNUMBER(N110)) -> FALSE | O17: =AND(OR(O16="PLAN",O16="SIM",O16="REAL"),ISNUMBER(O110)) -> FALSE | P17: =AND(OR(P16="PLAN",P16="SIM",P16="REAL"),ISNUMBER(P110)) -> FALSE | ... S17: =AND(OR(S16="PLAN",S16="SIM",S16="REAL"),ISNUMBER(S110)) -> FALSE
A19: SECCIÓN B · CONDICIONES DE RONDA (valores publicados por CESIM en 'Condiciones' de cada ronda — R3-R12 arrastran el último valor conocido, EDITABLE en cuanto se publique el real)
A20: B. Condiciones | B20: Crecimiento de mercado esperado (vs. ronda anterior) | C20: EE.UU. | D20: % | E20: CONDICIÓN DE RONDA | F20: CESIM R2 | G20: n/a (Ronda 0, sin ronda anterior) | H20: n/a (no cargado retroactivamente) | I20: 0.05 | J20: =I20 -> 0.05 | K20: =J20 -> 0.05 | L20: =K20 -> 0.05 | M20: =L20 -> 0.05 | N20: =M20 -> 0.05 | O20: =N20 -> 0.05 | P20: =O20 -> 0.05 | Q20: =P20 -> 0.05 | ... S20: =R20 -> 0.05
A21: B. Condiciones | B21: Crecimiento de mercado esperado (vs. ronda anterior) | C21: China | D21: % | E21: CONDICIÓN DE RONDA | F21: CESIM R2 | G21: n/a (Ronda 0, sin ronda anterior) | H21: n/a (no cargado retroactivamente) | I21: 0.085 | J21: =I21 -> 0.085 | K21: =J21 -> 0.085 | L21: =K21 -> 0.085 | M21: =L21 -> 0.085 | N21: =M21 -> 0.085 | O21: =N21 -> 0.085 | P21: =O21 -> 0.085 | Q21: =P21 -> 0.085 | ... S21: =R21 -> 0.085
A22: B. Condiciones | B22: Crecimiento de mercado esperado (vs. ronda anterior) | C22: Europa | D22: % | E22: CONDICIÓN DE RONDA | F22: CESIM R2 | G22: n/a (Ronda 0, sin ronda anterior) | H22: n/a (no cargado retroactivamente) | I22: 0.03 | J22: =I22 -> 0.03 | K22: =J22 -> 0.03 | L22: =K22 -> 0.03 | M22: =L22 -> 0.03 | N22: =M22 -> 0.03 | O22: =N22 -> 0.03 | P22: =O22 -> 0.03 | Q22: =P22 -> 0.03 | ... S22: =R22 -> 0.03
A23: B. Condiciones | B23: Tasa de impuesto corporativo | C23: EE.UU. | D23: % | E23: CONDICIÓN DE RONDA | F23: CESIM R2 | G23: 0.22 | H23: 0.25 | I23: 0.22 | J23: =I23 -> 0.22 | K23: =J23 -> 0.22 | L23: =K23 -> 0.22 | M23: =L23 -> 0.22 | N23: =M23 -> 0.22 | O23: =N23 -> 0.22 | P23: =O23 -> 0.22 | Q23: =P23 -> 0.22 | ... S23: =R23 -> 0.22
A24: B. Condiciones | B24: Tasa de impuesto corporativo | C24: China | D24: % | E24: CONDICIÓN DE RONDA | F24: CESIM R2 | G24: 0.25 | H24: 0.28 | I24: 0.25 | J24: =I24 -> 0.25 | K24: =J24 -> 0.25 | L24: =K24 -> 0.25 | M24: =L24 -> 0.25 | N24: =M24 -> 0.25 | O24: =N24 -> 0.25 | P24: =O24 -> 0.25 | Q24: =P24 -> 0.25 | ... S24: =R24 -> 0.25
A25: B. Condiciones | B25: Tasa de impuesto corporativo | C25: Europa | D25: % | E25: CONDICIÓN DE RONDA | F25: CESIM R2 | G25: 0.21 | H25: 0.23 | I25: 0.21 | J25: =I25 -> 0.21 | K25: =J25 -> 0.21 | L25: =K25 -> 0.21 | M25: =L25 -> 0.21 | N25: =M25 -> 0.21 | O25: =N25 -> 0.21 | P25: =O25 -> 0.21 | Q25: =P25 -> 0.21 | ... S25: =R25 -> 0.21
A26: B. Condiciones | B26: Tipo de cambio (USD por 1 unidad de moneda local) | C26: China (RMB) | D26: USD/u.moneda | E26: CONDICIÓN DE RONDA | G26: n/a (Ronda 0) | H26: 0.162 | I26: 0.1507 | J26: =I26 -> 0.1507 | K26: =J26 -> 0.1507 | L26: =K26 -> 0.1507 | M26: =L26 -> 0.1507 | N26: =M26 -> 0.1507 | O26: =N26 -> 0.1507 | P26: =O26 -> 0.1507 | Q26: =P26 -> 0.1507 | ... S26: =R26 -> 0.1507
A27: B. Condiciones | B27: Tipo de cambio (USD por 1 unidad de moneda local) | C27: Europa (EUR) | D27: USD/u.moneda | E27: CONDICIÓN DE RONDA | G27: n/a (Ronda 0) | H27: 1.146 | I27: 1.1126 | J27: =I27 -> 1.1126 | K27: =J27 -> 1.1126 | L27: =K27 -> 1.1126 | M27: =L27 -> 1.1126 | N27: =M27 -> 1.1126 | O27: =N27 -> 1.1126 | P27: =O27 -> 1.1126 | Q27: =P27 -> 1.1126 | ... S27: =R27 -> 1.1126
A28: B. Condiciones | B28: Efectivo mínimo de fin de ronda | C28: Todos los países (por país) | D28: USD | E28: CONDICIÓN DE RONDA | F28: Supuesto propio | G28: n/a (Ronda 0) | H28: 2000000 | I28: 2000000 | J28: =I28 -> 2000000 | K28: =J28 -> 2000000 | L28: =K28 -> 2000000 | M28: =L28 -> 2000000 | N28: =M28 -> 2000000 | O28: =N28 -> 2000000 | P28: =O28 -> 2000000 | Q28: =P28 -> 2000000 | ... S28: =R28 -> 2000000
A29: B. Condiciones | B29: Tasa de interés — deuda a largo plazo | C29: Casa matriz EE.UU. | D29: %/ronda | E29: CONDICIÓN DE RONDA | G29: n/a (Ronda 0) | H29: 0.08 | I29: 0.05 | J29: =I29 -> 0.05 | K29: =J29 -> 0.05 | L29: =K29 -> 0.05 | M29: =L29 -> 0.05 | N29: =M29 -> 0.05 | O29: =N29 -> 0.05 | P29: =O29 -> 0.05 | Q29: =P29 -> 0.05 | ... S29: =R29 -> 0.05
A30: B. Condiciones | B30: Tasa de interés — deuda a corto plazo | C30: EE.UU. | D30: %/ronda | E30: CONDICIÓN DE RONDA | G30: n/a (Ronda 0) | H30: 0.15 | I30: 0.1 | J30: =I30 -> 0.1 | K30: =J30 -> 0.1 | L30: =K30 -> 0.1 | M30: =L30 -> 0.1 | N30: =M30 -> 0.1 | O30: =N30 -> 0.1 | P30: =O30 -> 0.1 | Q30: =P30 -> 0.1 | ... S30: =R30 -> 0.1
A31: B. Condiciones | B31: Tasa de interés — deuda a corto plazo | C31: China | D31: %/ronda | E31: CONDICIÓN DE RONDA | G31: n/a (Ronda 0) | H31: 0.1 | I31: 0.07 | J31: =I31 -> 0.07 | K31: =J31 -> 0.07 | L31: =K31 -> 0.07 | M31: =L31 -> 0.07 | N31: =M31 -> 0.07 | O31: =N31 -> 0.07 | P31: =O31 -> 0.07 | Q31: =P31 -> 0.07 | ... S31: =R31 -> 0.07
A32: B. Condiciones | B32: Tasa de interés — deuda a corto plazo | C32: Europa | D32: %/ronda | E32: CONDICIÓN DE RONDA | G32: n/a (Ronda 0) | H32: 0.085 | I32: 0.055 | J32: =I32 -> 0.055 | K32: =J32 -> 0.055 | L32: =K32 -> 0.055 | M32: =L32 -> 0.055 | N32: =M32 -> 0.055 | O32: =N32 -> 0.055 | P32: =O32 -> 0.055 | Q32: =P32 -> 0.055 | ... S32: =R32 -> 0.055
A33: B. Condiciones | B33: Tasa de interés sobre efectivo | C33: EE.UU. | D33: %/ronda | E33: CONDICIÓN DE RONDA | G33: n/a (Ronda 0) | H33: 0.06 | I33: 0.04 | J33: =I33 -> 0.04 | K33: =J33 -> 0.04 | L33: =K33 -> 0.04 | M33: =L33 -> 0.04 | N33: =M33 -> 0.04 | O33: =N33 -> 0.04 | P33: =O33 -> 0.04 | Q33: =P33 -> 0.04 | ... S33: =R33 -> 0.04
A34: B. Condiciones | B34: Tasa de interés sobre efectivo | C34: China | D34: %/ronda | E34: CONDICIÓN DE RONDA | G34: n/a (Ronda 0) | H34: 0.065 | I34: 0.055 | J34: =I34 -> 0.055 | K34: =J34 -> 0.055 | L34: =K34 -> 0.055 | M34: =L34 -> 0.055 | N34: =M34 -> 0.055 | O34: =N34 -> 0.055 | P34: =O34 -> 0.055 | Q34: =P34 -> 0.055 | ... S34: =R34 -> 0.055
A35: B. Condiciones | B35: Tasa de interés sobre efectivo | C35: Europa | D35: %/ronda | E35: CONDICIÓN DE RONDA | G35: n/a (Ronda 0) | H35: 0.055 | I35: 0.03 | J35: =I35 -> 0.03 | K35: =J35 -> 0.03 | L35: =K35 -> 0.03 | M35: =L35 -> 0.03 | N35: =M35 -> 0.03 | O35: =N35 -> 0.03 | P35: =O35 -> 0.03 | Q35: =P35 -> 0.03 | ... S35: =R35 -> 0.03
A36: B. Condiciones | B36: Costo de la característica | C36: EE.UU. | D36: USD/u. | E36: CONDICIÓN DE RONDA | F36: RDOS R1 | G36: n/a (Ronda 0) | H36: 700 | I36: 700 | J36: =I36 -> 700 | K36: =J36 -> 700 | L36: =K36 -> 700 | M36: =L36 -> 700 | N36: =M36 -> 700 | O36: =N36 -> 700 | P36: =O36 -> 700 | Q36: =P36 -> 700 | ... S36: =R36 -> 700
A37: B. Condiciones | B37: Costo de la característica | C37: China | D37: USD/u. | E37: CONDICIÓN DE RONDA | F37: RDOS R1 | G37: n/a (Ronda 0) | H37: 650 | I37: 650 | J37: =I37 -> 650 | K37: =J37 -> 650 | L37: =K37 -> 650 | M37: =L37 -> 650 | N37: =M37 -> 650 | O37: =N37 -> 650 | P37: =O37 -> 650 | Q37: =P37 -> 650 | ... S37: =R37 -> 650
A38: B. Condiciones | B38: Costo de la característica | C38: Europa | D38: USD/u. | E38: CONDICIÓN DE RONDA | F38: RDOS R1 | G38: n/a (Ronda 0) | H38: 750 | I38: 750 | J38: =I38 -> 750 | K38: =J38 -> 750 | L38: =K38 -> 750 | M38: =L38 -> 750 | N38: =M38 -> 750 | O38: =N38 -> 750 | P38: =O38 -> 750 | Q38: =P38 -> 750 | ... S38: =R38 -> 750
A39: B. Condiciones | B39: Costo de adquirir tecnología nueva | C39: Combustión | D39: USD | E39: CONDICIÓN DE RONDA | F39: CESIM R2 | G39: n/a (ya habilitada para CADIZ) | H39: n/a (ya habilitada para CADIZ) | I39: n/a (ya habilitada para CADIZ) | J39: n/a (ya habilitada para CADIZ) | K39: n/a (ya habilitada para CADIZ) | L39: n/a (ya habilitada para CADIZ) | M39: n/a (ya habilitada para CADIZ) | N39: n/a (ya habilitada para CADIZ) | O39: n/a (ya habilitada para CADIZ) | P39: n/a (ya habilitada para CADIZ) | Q39: n/a (ya habilitada para CADIZ) | R39: n/a (ya habilitada para CADIZ) | S39: n/a (ya habilitada para CADIZ)
A40: B. Condiciones | B40: Costo de adquirir tecnología nueva | C40: Híbrido | D40: USD | E40: CONDICIÓN DE RONDA | F40: CESIM R2 | G40: n/a (ya habilitada para CADIZ) | H40: n/a (ya habilitada para CADIZ) | I40: n/a (ya habilitada para CADIZ) | J40: n/a (ya habilitada para CADIZ) | K40: n/a (ya habilitada para CADIZ) | L40: n/a (ya habilitada para CADIZ) | M40: n/a (ya habilitada para CADIZ) | N40: n/a (ya habilitada para CADIZ) | O40: n/a (ya habilitada para CADIZ) | P40: n/a (ya habilitada para CADIZ) | Q40: n/a (ya habilitada para CADIZ) | R40: n/a (ya habilitada para CADIZ) | S40: n/a (ya habilitada para CADIZ)
A41: B. Condiciones | B41: Costo de adquirir tecnología nueva | C41: Eléctrico | D41: USD | E41: CONDICIÓN DE RONDA | F41: CESIM R2 | G41: n/a (no verificado) | H41: n/a (no verificado) | J41: =I41 -> 0 | K41: =J41 -> 0 | L41: =K41 -> 0 | M41: =L41 -> 0 | N41: =M41 -> 0 | O41: =N41 -> 0 | P41: =O41 -> 0 | Q41: =P41 -> 0 | ... S41: =R41 -> 0
A42: B. Condiciones | B42: Costo de adquirir tecnología nueva | C42: Hidrógeno | D42: USD | E42: CONDICIÓN DE RONDA | F42: CESIM R2 | G42: n/a (no verificado) | H42: n/a (no verificado) | J42: =I42 -> 0 | K42: =J42 -> 0 | L42: =K42 -> 0 | M42: =L42 -> 0 | N42: =M42 -> 0 | O42: =N42 -> 0 | P42: =O42 -> 0 | Q42: =P42 -> 0 | ... S42: =R42 -> 0
A43: B. Condiciones | B43: Costo de generar/adquirir característica nueva | C43: Combustión | D43: USD | E43: CONDICIÓN DE RONDA | F43: CESIM R2 | G43: n/a (no verificado) | H43: n/a (no verificado) | J43: =I43 -> 0 | K43: =J43 -> 0 | L43: =K43 -> 0 | M43: =L43 -> 0 | N43: =M43 -> 0 | O43: =N43 -> 0 | P43: =O43 -> 0 | Q43: =P43 -> 0 | ... S43: =R43 -> 0
A44: B. Condiciones | B44: Costo de generar/adquirir característica nueva | C44: Híbrido | D44: USD | E44: CONDICIÓN DE RONDA | F44: CESIM R2 | G44: n/a (no verificado) | H44: n/a (no verificado) | J44: =I44 -> 0 | K44: =J44 -> 0 | L44: =K44 -> 0 | M44: =L44 -> 0 | N44: =M44 -> 0 | O44: =N44 -> 0 | P44: =O44 -> 0 | Q44: =P44 -> 0 | ... S44: =R44 -> 0
A45: B. Condiciones | B45: Costo de generar/adquirir característica nueva | C45: Eléctrico | D45: USD | E45: CONDICIÓN DE RONDA | F45: CESIM R2 | G45: n/a (no verificado) | H45: n/a (no verificado) | J45: =I45 -> 0 | K45: =J45 -> 0 | L45: =K45 -> 0 | M45: =L45 -> 0 | N45: =M45 -> 0 | O45: =N45 -> 0 | P45: =O45 -> 0 | Q45: =P45 -> 0 | ... S45: =R45 -> 0
A46: B. Condiciones | B46: Costo de generar/adquirir característica nueva | C46: Hidrógeno | D46: USD | E46: CONDICIÓN DE RONDA | F46: CESIM R2 | G46: n/a (no verificado) | H46: n/a (no verificado) | J46: =I46 -> 0 | K46: =J46 -> 0 | L46: =K46 -> 0 | M46: =L46 -> 0 | N46: =M46 -> 0 | O46: =N46 -> 0 | P46: =O46 -> 0 | Q46: =P46 -> 0 | ... S46: =R46 -> 0
A47: B. Condiciones | B47: Administración — componente fijo | C47: EE.UU. | D47: USD | E47: CONDICIÓN DE RONDA | F47: Alerta modelo | G47: n/a (Ronda 0) | H47: 35000000 | I47: 35000000 | J47: =I47 -> 35000000 | K47: =J47 -> 35000000 | L47: =K47 -> 35000000 | M47: =L47 -> 35000000 | N47: =M47 -> 35000000 | O47: =N47 -> 35000000 | P47: =O47 -> 35000000 | Q47: =P47 -> 35000000 | ... S47: =R47 -> 35000000
A48: B. Condiciones | B48: Administración — componente fijo | C48: China | D48: USD | E48: CONDICIÓN DE RONDA | F48: Alerta modelo | G48: n/a (Ronda 0) | H48: 71000000 | I48: 74000000 | J48: =I48 -> 74000000 | K48: =J48 -> 74000000 | L48: =K48 -> 74000000 | M48: =L48 -> 74000000 | N48: =M48 -> 74000000 | O48: =N48 -> 74000000 | P48: =O48 -> 74000000 | Q48: =P48 -> 74000000 | ... S48: =R48 -> 74000000
A49: B. Condiciones | B49: Administración — componente fijo | C49: Europa | D49: USD | E49: CONDICIÓN DE RONDA | F49: Alerta modelo | G49: n/a (Ronda 0) | H49: 20000000 | I49: 20000000 | J49: =I49 -> 20000000 | K49: =J49 -> 20000000 | L49: =K49 -> 20000000 | M49: =L49 -> 20000000 | N49: =M49 -> 20000000 | O49: =N49 -> 20000000 | P49: =O49 -> 20000000 | Q49: =P49 -> 20000000 | ... S49: =R49 -> 20000000
A50: B. Condiciones | B50: Administración — componente por planta (aplicado linealmente, ver ALERTA) | C50: EE.UU. | D50: USD/fábrica | E50: CONDICIÓN DE RONDA | G50: n/a (Ronda 0) | H50: 4000000 | I50: 4000000 | J50: =I50 -> 4000000 | K50: =J50 -> 4000000 | L50: =K50 -> 4000000 | M50: =L50 -> 4000000 | N50: =M50 -> 4000000 | O50: =N50 -> 4000000 | P50: =O50 -> 4000000 | Q50: =P50 -> 4000000 | ... S50: =R50 -> 4000000
A51: B. Condiciones | B51: Administración — componente por planta (aplicado linealmente, ver ALERTA) | C51: China | D51: USD/fábrica | E51: CONDICIÓN DE RONDA | G51: n/a (Ronda 0) | H51: 12000000 | I51: 13000000 | J51: =I51 -> 13000000 | K51: =J51 -> 13000000 | L51: =K51 -> 13000000 | M51: =L51 -> 13000000 | N51: =M51 -> 13000000 | O51: =N51 -> 13000000 | P51: =O51 -> 13000000 | Q51: =P51 -> 13000000 | ... S51: =R51 -> 13000000
A52: B. Condiciones | B52: Administración — componente % sobre ingresos | C52: EE.UU. | D52: % | E52: CONDICIÓN DE RONDA | G52: n/a (Ronda 0) | H52: 0 | I52: 0 | J52: =I52 -> 0 | K52: =J52 -> 0 | L52: =K52 -> 0 | M52: =L52 -> 0 | N52: =M52 -> 0 | O52: =N52 -> 0 | P52: =O52 -> 0 | Q52: =P52 -> 0 | ... S52: =R52 -> 0
A53: B. Condiciones | B53: Administración — componente % sobre ingresos | C53: China | D53: % | E53: CONDICIÓN DE RONDA | G53: n/a (Ronda 0) | H53: 0 | I53: 0 | J53: =I53 -> 0 | K53: =J53 -> 0 | L53: =K53 -> 0 | M53: =L53 -> 0 | N53: =M53 -> 0 | O53: =N53 -> 0 | P53: =O53 -> 0 | Q53: =P53 -> 0 | ... S53: =R53 -> 0
A54: B. Condiciones | B54: Administración — componente % sobre ingresos | C54: Europa | D54: % | E54: CONDICIÓN DE RONDA | G54: n/a (Ronda 0) | H54: 0 | I54: 0 | J54: =I54 -> 0 | K54: =J54 -> 0 | L54: =K54 -> 0 | M54: =L54 -> 0 | N54: =M54 -> 0 | O54: =N54 -> 0 | P54: =O54 -> 0 | Q54: =P54 -> 0 | ... S54: =R54 -> 0
A55: B. Condiciones | B55: % Sueldo bruto sobre costo laboral total (RRHH) | C55: Global | D55: % | E55: CONDICIÓN DE RONDA | F55: RDOS R1 | G55: n/a (Ronda 0) | H55: 0.7 | I55: 0.7 | J55: =I55 -> 0.7 | K55: =J55 -> 0.7 | L55: =K55 -> 0.7 | M55: =L55 -> 0.7 | N55: =M55 -> 0.7 | O55: =N55 -> 0.7 | P55: =O55 -> 0.7 | Q55: =P55 -> 0.7 | ... S55: =R55 -> 0.7
A56: B. Condiciones | B56: Otros costos de I+D por empleado/mes | C56: Global | D56: USD/empleado/mes | E56: CONDICIÓN DE RONDA | F56: RDOS R1 | G56: n/a (Ronda 0) | H56: 680 | I56: 670 | J56: =I56 -> 670 | K56: =J56 -> 670 | L56: =K56 -> 670 | M56: =L56 -> 670 | N56: =M56 -> 670 | O56: =N56 -> 670 | P56: =O56 -> 670 | Q56: =P56 -> 670 | ... S56: =R56 -> 670
A57: B. Condiciones | B57: Costo de contratación por persona | C57: Global | D57: USD/persona | E57: CONDICIÓN DE RONDA | G57: n/a (Ronda 0) | H57: 4100 | I57: 4000 | J57: =I57 -> 4000 | K57: =J57 -> 4000 | L57: =K57 -> 4000 | M57: =L57 -> 4000 | N57: =M57 -> 4000 | O57: =N57 -> 4000 | P57: =O57 -> 4000 | Q57: =P57 -> 4000 | ... S57: =R57 -> 4000
A58: B. Condiciones | B58: Costo de despido por persona | C58: tramo 5%-20% de reducción | D58: USD/persona | E58: CONDICIÓN DE RONDA | G58: n/a (Ronda 0) | H58: 18600 | I58: 18400 | J58: =I58 -> 18400 | K58: =J58 -> 18400 | L58: =K58 -> 18400 | M58: =L58 -> 18400 | N58: =M58 -> 18400 | O58: =N58 -> 18400 | P58: =O58 -> 18400 | Q58: =P58 -> 18400 | ... S58: =R58 -> 18400
A59: B. Condiciones | B59: Costo de despido por persona | C59: tramo 20%-50% de reducción | D59: USD/persona | E59: CONDICIÓN DE RONDA | G59: n/a (Ronda 0) | H59: 23600 | I59: 23400 | J59: =I59 -> 23400 | K59: =J59 -> 23400 | L59: =K59 -> 23400 | M59: =L59 -> 23400 | N59: =M59 -> 23400 | O59: =N59 -> 23400 | P59: =O59 -> 23400 | Q59: =P59 -> 23400 | ... S59: =R59 -> 23400
A60: B. Condiciones | B60: Costo de despido por persona | C60: tramo >50% de reducción | D60: USD/persona | E60: CONDICIÓN DE RONDA | G60: n/a (Ronda 0) | H60: 30600 | I60: 30400 | J60: =I60 -> 30400 | K60: =J60 -> 30400 | L60: =K60 -> 30400 | M60: =L60 -> 30400 | N60: =M60 -> 30400 | O60: =N60 -> 30400 | P60: =O60 -> 30400 | Q60: =P60 -> 30400 | ... S60: =R60 -> 30400
A61: B. Condiciones | B61: Valor de referencia de la acción (proxy para EPS/emisión-recompra) | C61: Casa matriz EE.UU. | D61: USD/acción | E61: NO DETERMINADO | F61: No determinado | G61: 33.59236 | H61: 38.651795 | I61: 38.651795 | J61: =I61 -> 38.651795 | K61: =J61 -> 38.651795 | L61: =K61 -> 38.651795 | M61: =L61 -> 38.651795 | N61: =M61 -> 38.651795 | O61: =N61 -> 38.651795 | P61: =O61 -> 38.651795 | Q61: =P61 -> 38.651795 | ... S61: =R61 -> 38.651795
A62: B. Condiciones | B62: Costo de transporte por unidad | C62: EE.UU. → China | D62: USD/u. | E62: CONDICIÓN DE RONDA | G62: n/a (Ronda 0) | H62: 550 | I62: 350 | J62: =I62 -> 350 | K62: =J62 -> 350 | L62: =K62 -> 350 | M62: =L62 -> 350 | N62: =M62 -> 350 | O62: =N62 -> 350 | P62: =O62 -> 350 | Q62: =P62 -> 350 | ... S62: =R62 -> 350
A63: B. Condiciones | B63: Costo de transporte por unidad | C63: EE.UU. → Europa | D63: USD/u. | E63: CONDICIÓN DE RONDA | G63: n/a (Ronda 0) | H63: 300 | I63: 200 | J63: =I63 -> 200 | K63: =J63 -> 200 | L63: =K63 -> 200 | M63: =L63 -> 200 | N63: =M63 -> 200 | O63: =N63 -> 200 | P63: =O63 -> 200 | Q63: =P63 -> 200 | ... S63: =R63 -> 200
A64: B. Condiciones | B64: Costo de transporte por unidad | C64: China → EE.UU. | D64: USD/u. | E64: CONDICIÓN DE RONDA | G64: n/a (Ronda 0) | H64: 450 | I64: 300 | J64: =I64 -> 300 | K64: =J64 -> 300 | L64: =K64 -> 300 | M64: =L64 -> 300 | N64: =M64 -> 300 | O64: =N64 -> 300 | P64: =O64 -> 300 | Q64: =P64 -> 300 | ... S64: =R64 -> 300
A65: B. Condiciones | B65: Costo de transporte por unidad | C65: China → Europa | D65: USD/u. | E65: CONDICIÓN DE RONDA | G65: n/a (Ronda 0) | H65: 400 | I65: 250 | J65: =I65 -> 250 | K65: =J65 -> 250 | L65: =K65 -> 250 | M65: =L65 -> 250 | N65: =M65 -> 250 | O65: =N65 -> 250 | P65: =O65 -> 250 | Q65: =P65 -> 250 | ... S65: =R65 -> 250
A66: B. Condiciones | B66: Arancel específico por unidad | C66: EE.UU. → China | D66: USD/u. | E66: CONDICIÓN DE RONDA | G66: n/a (Ronda 0) | H66: 0 | I66: 0 | J66: =I66 -> 0 | K66: =J66 -> 0 | L66: =K66 -> 0 | M66: =L66 -> 0 | N66: =M66 -> 0 | O66: =N66 -> 0 | P66: =O66 -> 0 | Q66: =P66 -> 0 | ... S66: =R66 -> 0
A67: B. Condiciones | B67: Arancel específico por unidad | C67: EE.UU. → Europa | D67: USD/u. | E67: CONDICIÓN DE RONDA | G67: n/a (Ronda 0) | H67: 0 | I67: 0 | J67: =I67 -> 0 | K67: =J67 -> 0 | L67: =K67 -> 0 | M67: =L67 -> 0 | N67: =M67 -> 0 | O67: =N67 -> 0 | P67: =O67 -> 0 | Q67: =P67 -> 0 | ... S67: =R67 -> 0
A68: B. Condiciones | B68: Arancel específico por unidad | C68: China → EE.UU. | D68: USD/u. | E68: CONDICIÓN DE RONDA | G68: n/a (Ronda 0) | H68: 0 | I68: 0 | J68: =I68 -> 0 | K68: =J68 -> 0 | L68: =K68 -> 0 | M68: =L68 -> 0 | N68: =M68 -> 0 | O68: =N68 -> 0 | P68: =O68 -> 0 | Q68: =P68 -> 0 | ... S68: =R68 -> 0
A69: B. Condiciones | B69: Arancel específico por unidad | C69: China → Europa | D69: USD/u. | E69: CONDICIÓN DE RONDA | G69: n/a (Ronda 0) | H69: 0 | I69: 0 | J69: =I69 -> 0 | K69: =J69 -> 0 | L69: =K69 -> 0 | M69: =L69 -> 0 | N69: =M69 -> 0 | O69: =N69 -> 0 | P69: =O69 -> 0 | Q69: =P69 -> 0 | ... S69: =R69 -> 0
A70: B. Condiciones | B70: Arancel ad valorem (%) | C70: EE.UU. → China | D70: % | E70: CONDICIÓN DE RONDA | F70: Supuesto propio | G70: n/a (Ronda 0) | H70: 0.3 | I70: 0.2 | J70: =I70 -> 0.2 | K70: =J70 -> 0.2 | L70: =K70 -> 0.2 | M70: =L70 -> 0.2 | N70: =M70 -> 0.2 | O70: =N70 -> 0.2 | P70: =O70 -> 0.2 | Q70: =P70 -> 0.2 | ... S70: =R70 -> 0.2
A71: B. Condiciones | B71: Arancel ad valorem (%) | C71: EE.UU. → Europa | D71: % | E71: CONDICIÓN DE RONDA | F71: Supuesto propio | G71: n/a (Ronda 0) | H71: 0.2 | I71: 0.1 | J71: =I71 -> 0.1 | K71: =J71 -> 0.1 | L71: =K71 -> 0.1 | M71: =L71 -> 0.1 | N71: =M71 -> 0.1 | O71: =N71 -> 0.1 | P71: =O71 -> 0.1 | Q71: =P71 -> 0.1 | ... S71: =R71 -> 0.1
A72: B. Condiciones | B72: Arancel ad valorem (%) | C72: China → EE.UU. | D72: % | E72: CONDICIÓN DE RONDA | F72: Supuesto propio | G72: n/a (Ronda 0) | H72: 0.3 | I72: 0.025 | J72: =I72 -> 0.025 | K72: =J72 -> 0.025 | L72: =K72 -> 0.025 | M72: =L72 -> 0.025 | N72: =M72 -> 0.025 | O72: =N72 -> 0.025 | P72: =O72 -> 0.025 | Q72: =P72 -> 0.025 | ... S72: =R72 -> 0.025
A73: B. Condiciones | B73: Arancel ad valorem (%) | C73: China → Europa | D73: % | E73: CONDICIÓN DE RONDA | F73: Supuesto propio | G73: n/a (Ronda 0) | H73: 0.2 | I73: 0.1 | J73: =I73 -> 0.1 | K73: =J73 -> 0.1 | L73: =K73 -> 0.1 | M73: =L73 -> 0.1 | N73: =M73 -> 0.1 | O73: =N73 -> 0.1 | P73: =O73 -> 0.1 | Q73: =P73 -> 0.1 | ... S73: =R73 -> 0.1
A74: B. Condiciones | B74: Costo de inversión por fábrica | C74: EE.UU. | D74: USD | E74: CONDICIÓN DE RONDA | G74: n/a (Ronda 0) | H74: 1207500000 | I74: 1202000000 | J74: =I74 -> 1202000000 | K74: =J74 -> 1202000000 | L74: =K74 -> 1202000000 | M74: =L74 -> 1202000000 | N74: =M74 -> 1202000000 | O74: =N74 -> 1202000000 | P74: =O74 -> 1202000000 | Q74: =P74 -> 1202000000 | ... S74: =R74 -> 1202000000
A75: B. Condiciones | B75: Costo de inversión por fábrica | C75: China | D75: USD | E75: CONDICIÓN DE RONDA | G75: n/a (Ronda 0) | H75: 1057500000 | I75: 1052000000 | J75: =I75 -> 1052000000 | K75: =J75 -> 1052000000 | L75: =K75 -> 1052000000 | M75: =L75 -> 1052000000 | N75: =M75 -> 1052000000 | O75: =N75 -> 1052000000 | P75: =O75 -> 1052000000 | Q75: =P75 -> 1052000000 | ... S75: =R75 -> 1052000000
A76: B. Condiciones | B76: Precio de venta por fábrica (desinversión) | C76: EE.UU. | D76: USD | E76: CONDICIÓN DE RONDA | G76: n/a (Ronda 0) | H76: 1207500000 | I76: 1202000000 | J76: =I76 -> 1202000000 | K76: =J76 -> 1202000000 | L76: =K76 -> 1202000000 | M76: =L76 -> 1202000000 | N76: =M76 -> 1202000000 | O76: =N76 -> 1202000000 | P76: =O76 -> 1202000000 | Q76: =P76 -> 1202000000 | ... S76: =R76 -> 1202000000
A77: B. Condiciones | B77: Precio de venta por fábrica (desinversión) | C77: China | D77: USD | E77: CONDICIÓN DE RONDA | G77: n/a (Ronda 0) | H77: 1057500000 | I77: 1052000000 | J77: =I77 -> 1052000000 | K77: =J77 -> 1052000000 | L77: =K77 -> 1052000000 | M77: =L77 -> 1052000000 | N77: =M77 -> 1052000000 | O77: =N77 -> 1052000000 | P77: =O77 -> 1052000000 | Q77: =P77 -> 1052000000 | ... S77: =R77 -> 1052000000
A78: B. Condiciones | B78: Costo unitario de producción tercerizada | C78: EE.UU. / Combustión | D78: USD/u. | E78: NO DETERMINADO / PENDIENTE DE CARGA | F78: No determinado | G78: 11425.641 | H78: 11142.16
A79: B. Condiciones | B79: Costo unitario de producción tercerizada | C79: EE.UU. / Híbrido | D79: USD/u. | E79: NO DETERMINADO / PENDIENTE DE CARGA | F79: No determinado | H79: 17630.523
A80: B. Condiciones | B80: Costo unitario de producción tercerizada | C80: EE.UU. / Eléctrico | D80: USD/u. | E80: NO DETERMINADO / PENDIENTE DE CARGA | F80: No determinado
A81: B. Condiciones | B81: Costo unitario de producción tercerizada | C81: EE.UU. / Hidrógeno | D81: USD/u. | E81: NO DETERMINADO / PENDIENTE DE CARGA | F81: No determinado
A82: B. Condiciones | B82: Costo unitario de producción tercerizada | C82: China / Combustión | D82: USD/u. | E82: NO DETERMINADO / PENDIENTE DE CARGA | F82: No determinado | G82: 10264.471 | H82: 10358.738 | I82: 10106.74
A83: B. Condiciones | B83: Costo unitario de producción tercerizada | C83: China / Híbrido | D83: USD/u. | E83: NO DETERMINADO / PENDIENTE DE CARGA | F83: No determinado | H83: 16285.824 | I83: 15649.15
A84: B. Condiciones | B84: Costo unitario de producción tercerizada | C84: China / Eléctrico | D84: USD/u. | E84: NO DETERMINADO / PENDIENTE DE CARGA | F84: No determinado
A85: B. Condiciones | B85: Costo unitario de producción tercerizada | C85: China / Hidrógeno | D85: USD/u. | E85: NO DETERMINADO / PENDIENTE DE CARGA | F85: No determinado
A86: B. Condiciones | B86: Costos fijos de gestión de inventario | C86: EE.UU. | D86: miles USD | E86: NO DETERMINADO | F86: No determinado
A87: B. Condiciones | B87: Costos variables de gestión de inventario | C87: EE.UU. | D87: USD/unidad | E87: NO DETERMINADO | F87: No determinado
A88: B. Condiciones | B88: Costos fijos de gestión de inventario | C88: China | D88: miles USD | E88: NO DETERMINADO | F88: No determinado
A89: B. Condiciones | B89: Costos variables de gestión de inventario | C89: China | D89: USD/unidad | E89: NO DETERMINADO | F89: No determinado
A90: B. Condiciones | B90: Costo del Carbono | C90: Todas las áreas | D90: USD/ton | E90: NO DETERMINADO | F90: No determinado
A91: B. Condiciones | B91: Costo de la energía fósil | C91: Todas las áreas | D91: USD/kWh | E91: NO DETERMINADO | F91: No determinado
A92: B. Condiciones | B92: Costo de la energía renovable | C92: Todas las áreas | D92: USD/kWh | E92: NO DETERMINADO | F92: No determinado
A93: B. Condiciones | B93: Costo del agua | C93: Todas las áreas | D93: USD/m3 | E93: NO DETERMINADO | F93: No determinado
A95: SECCIÓN C.D1a · DEMANDA — Mix de Industria (TAM) [SUPUESTO PROPIO — no es un input directo publicado por CESIM]
A96: D1a · MIX INDUSTRIA | B96: Mix de Industria (TAM) | C96: EE.UU. / Combustión | D96: % del TAM | E96: SUPUESTO PROPIO | F96: Ver comentario | G96: n/a (ronda ya jugada) | H96: n/a (ronda ya jugada) | I96: 0.809504
A97: D1a · MIX INDUSTRIA | B97: Mix de Industria (TAM) | C97: EE.UU. / Híbrido | D97: % del TAM | E97: SUPUESTO PROPIO | F97: Ver comentario | G97: n/a (ronda ya jugada) | H97: n/a (ronda ya jugada) | I97: 0.190496
A98: D1a · MIX INDUSTRIA | B98: Mix de Industria (TAM) | C98: EE.UU. / Eléctrico | D98: % del TAM | E98: SUPUESTO PROPIO | F98: Ver comentario | G98: n/a (ronda ya jugada) | H98: n/a (ronda ya jugada) | I98: 0
A99: D1a · MIX INDUSTRIA | B99: Mix de Industria (TAM) | C99: EE.UU. / Hidrógeno | D99: % del TAM | E99: SUPUESTO PROPIO | F99: Ver comentario | G99: n/a (ronda ya jugada) | H99: n/a (ronda ya jugada) | I99: 0
A100: D1a · MIX INDUSTRIA | B100: Mix de Industria (TAM) | C100: China / Combustión | D100: % del TAM | E100: SUPUESTO PROPIO | F100: Ver comentario | G100: n/a (ronda ya jugada) | H100: n/a (ronda ya jugada) | I100: 0.814027
A101: D1a · MIX INDUSTRIA | B101: Mix de Industria (TAM) | C101: China / Híbrido | D101: % del TAM | E101: SUPUESTO PROPIO | F101: Ver comentario | G101: n/a (ronda ya jugada) | H101: n/a (ronda ya jugada) | I101: 0.185973
A102: D1a · MIX INDUSTRIA | B102: Mix de Industria (TAM) | C102: China / Eléctrico | D102: % del TAM | E102: SUPUESTO PROPIO | F102: Ver comentario | G102: n/a (ronda ya jugada) | H102: n/a (ronda ya jugada) | I102: 0
...

Sheet 02_ESTADOS_PROYECTADOS
A1: 02_ESTADOS_PROYECTADOS — Estados financieros con selector GLOBAL/EE.UU./CHINA/EUROPA (B2) y detalle por país agrupado ([+]/[-] a la izquierda) | U1: GLOBAL
A2: SELECTOR DE VISTA (celda B2) → | B2: GLOBAL | C2: GLOBAL = consolidado (Σ 3 países, con eliminaciones). EE.UU./CHINA/EUROPA = ese país únicamente. VISTA DESPLEGADA = igual a GLOBAL en la fila principal (pensada para cuando se quiere ver todo el detalle por país expandido de entrada). El detalle por país de cada línea está SIEMPRE presente debajo, agrupado con el outline nativo de Excel/LibreOffice -- usar [+]/[-] a la izquierda de la grilla para expandir/colapsar, independientemente de lo que diga B2. | U2: EE.UU.
A3: Detalle por país: Ingresos = 'Ingresos de mercados' (externo, sin transferencias internas). Costos = Costos y gastos totales EXCLUYENDO costos de productos importados (misma base de eliminación que GLOBAL). El resto de las líneas suma exacto a GLOBAL. Celdas en VERDE = link, no editar aquí. | U3: CHINA
U4: EUROPA
A5: Concepto | B5: Unidad | G5: R0 | H5: R1 | I5: R2 | J5: R3 | K5: R4 | L5: R5 | M5: R6 | N5: R7 | O5: R8 | P5: R9 | Q5: R10 | R5: R11 | S5: R12 | U5: VISTA DESPLEGADA
A6: ESTADO DE RESULTADOS
A7: Ingresos por ventas | B7: USD | G7: =CHOOSE(MATCH($B$2,$U$1:$U$5,0),_ENGINE_FINANCIERO!G160,_ENGINE_FINANCIERO!G5,_ENGINE_FINANCIERO!G52,_ENGINE_FINANCIERO!G99,_ENGINE_FINANCIERO!G160) -> 39489000000 | H7: =CHOOSE(MATCH($B$2,$U$1:$U$5,0),_ENGINE_FINANCIERO!H160,_ENGINE_FINANCIERO!H5,_ENGINE_FINANCIERO!H52,_ENGINE_FINANCIERO!H99,_ENGINE_FINANCIERO!H160) -> n/a (RDOS R1 Global no desagregado aquí) | I7: =IF(01_INPUTS!I17,CHOOSE(MATCH($B$2,$U$1:$U$5,0),_ENGINE_FINANCIERO!I160,_ENGINE_FINANCIERO!I5,_ENGINE_FINANCIERO!I52,_ENGINE_FINANCIERO!I99,_ENGINE_FINANCIERO!I160),"") -> 7.6940913e+10 | J7: =IF(01_INPUTS!J17,CHOOSE(MATCH($B$2,$U$1:$U$5,0),_ENGINE_FINANCIERO!J160,_ENGINE_FINANCIERO!J5,_ENGINE_FINANCIERO!J52,_ENGINE_FINANCIERO!J99,_ENGINE_FINANCIERO!J160),"") | K7: =IF(01_INPUTS!K17,CHOOSE(MATCH($B$2,$U$1:$U$5,0),_ENGINE_FINANCIERO!K160,_ENGINE_FINANCIERO!K5,_ENGINE_FINANCIERO!K52,_ENGINE_FINANCIERO!K99,_ENGINE_FINANCIERO!K160),"") | L7: =IF(01_INPUTS!L17,CHOOSE(MATCH($B$2,$U$1:$U$5,0),_ENGINE_FINANCIERO!L160,_ENGINE_FINANCIERO!L5,_ENGINE_FINANCIERO!L52,_ENGINE_FINANCIERO!L99,_ENGINE_FINANCIERO!L160),"") | M7: =IF(01_INPUTS!M17,CHOOSE(MATCH($B$2,$U$1:$U$5,0),_ENGINE_FINANCIERO!M160,_ENGINE_FINANCIERO!M5,_ENGINE_FINANCIERO!M52,_ENGINE_FINANCIERO!M99,_ENGINE_FINANCIERO!M160),"") | N7: =IF(01_INPUTS!N17,CHOOSE(MATCH($B$2,$U$1:$U$5,0),_ENGINE_FINANCIERO!N160,_ENGINE_FINANCIERO!N5,_ENGINE_FINANCIERO!N52,_ENGINE_FINANCIERO!N99,_ENGINE_FINANCIERO!N160),"") | O7: =IF(01_INPUTS!O17,CHOOSE(MATCH($B$2,$U$1:$U$5,0),_ENGINE_FINANCIERO!O160,_ENGINE_FINANCIERO!O5,_ENGINE_FINANCIERO!O52,_ENGINE_FINANCIERO!O99,_ENGINE_FINANCIERO!O160),"") | P7: =IF(01_INPUTS!P17,CHOOSE(MATCH($B$2,$U$1:$U$5,0),_ENGINE_FINANCIERO!P160,_ENGINE_FINANCIERO!P5,_ENGINE_FINANCIERO!P52,_ENGINE_FINANCIERO!P99,_ENGINE_FINANCIERO!P160),"") | ... S7: =IF(01_INPUTS!S17,CHOOSE(MATCH($B$2,$U$1:$U$5,0),_ENGINE_FINANCIERO!S160,_ENGINE_FINANCIERO!S5,_ENGINE_FINANCIERO!S52,_ENGINE_FINANCIERO!S99,_ENGINE_FINANCIERO!S160),"")
A8: EE.UU. | B8: USD | G8: =_ENGINE_FINANCIERO!G5 -> 0 | H8: =_ENGINE_FINANCIERO!H5 -> 0 | I8: =IF(01_INPUTS!I17,_ENGINE_FINANCIERO!I5,"") -> 2.5052171e+10 | J8: =IF(01_INPUTS!J17,_ENGINE_FINANCIERO!J5,"") | K8: =IF(01_INPUTS!K17,_ENGINE_FINANCIERO!K5,"") | L8: =IF(01_INPUTS!L17,_ENGINE_FINANCIERO!L5,"") | M8: =IF(01_INPUTS!M17,_ENGINE_FINANCIERO!M5,"") | N8: =IF(01_INPUTS!N17,_ENGINE_FINANCIERO!N5,"") | O8: =IF(01_INPUTS!O17,_ENGINE_FINANCIERO!O5,"") | P8: =IF(01_INPUTS!P17,_ENGINE_FINANCIERO!P5,"") | ... S8: =IF(01_INPUTS!S17,_ENGINE_FINANCIERO!S5,"")
A9: China | B9: USD | G9: =_ENGINE_FINANCIERO!G52 -> 0 | H9: =_ENGINE_FINANCIERO!H52 -> 0 | I9: =IF(01_INPUTS!I17,_ENGINE_FINANCIERO!I52,"") -> 2.0223492e+10 | J9: =IF(01_INPUTS!J17,_ENGINE_FINANCIERO!J52,"") | K9: =IF(01_INPUTS!K17,_ENGINE_FINANCIERO!K52,"") | L9: =IF(01_INPUTS!L17,_ENGINE_FINANCIERO!L52,"") | M9: =IF(01_INPUTS!M17,_ENGINE_FINANCIERO!M52,"") | N9: =IF(01_INPUTS!N17,_ENGINE_FINANCIERO!N52,"") | O9: =IF(01_INPUTS!O17,_ENGINE_FINANCIERO!O52,"") | P9: =IF(01_INPUTS!P17,_ENGINE_FINANCIERO!P52,"") | ... S9: =IF(01_INPUTS!S17,_ENGINE_FINANCIERO!S52,"")
A10: Europa | B10: USD | G10: =_ENGINE_FINANCIERO!G99 -> 0 | H10: =_ENGINE_FINANCIERO!H99 -> 0 | I10: =IF(01_INPUTS!I17,_ENGINE_FINANCIERO!I99,"") -> 3.166525e+10 | J10: =IF(01_INPUTS!J17,_ENGINE_FINANCIERO!J99,"") | K10: =IF(01_INPUTS!K17,_ENGINE_FINANCIERO!K99,"") | L10: =IF(01_INPUTS!L17,_ENGINE_FINANCIERO!L99,"") | M10: =IF(01_INPUTS!M17,_ENGINE_FINANCIERO!M99,"") | N10: =IF(01_INPUTS!N17,_ENGINE_FINANCIERO!N99,"") | O10: =IF(01_INPUTS!O17,_ENGINE_FINANCIERO!O99,"") | P10: =IF(01_INPUTS!P17,_ENGINE_FINANCIERO!P99,"") | ... S10: =IF(01_INPUTS!S17,_ENGINE_FINANCIERO!S99,"")
A11: Costos y gastos totales | B11: USD | G11: =CHOOSE(MATCH($B$2,$U$1:$U$5,0),_ENGINE_FINANCIERO!G161,(_ENGINE_FINANCIERO!G18-_ENGINE_FINANCIERO!G9),(_ENGINE_FINANCIERO!G65-_ENGINE_FINANCIERO!G56),(_ENGINE_FINANCIERO!G112-_ENGINE_FINANCIERO!G103),_ENGINE_FINANCIERO!G161) -> 3.5337849e+10 | H11: =CHOOSE(MATCH($B$2,$U$1:$U$5,0),_ENGINE_FINANCIERO!H161,(_ENGINE_FINANCIERO!H18-_ENGINE_FINANCIERO!H9),(_ENGINE_FINANCIERO!H65-_ENGINE_FINANCIERO!H56),(_ENGINE_FINANCIERO!H112-_ENGINE_FINANCIERO!H103),_ENGINE_FINANCIERO!H161) -> n/a | I11: =IF(01_INPUTS!I17,CHOOSE(MATCH($B$2,$U$1:$U$5,0),_ENGINE_FINANCIERO!I161,(_ENGINE_FINANCIERO!I18-_ENGINE_FINANCIERO!I9),(_ENGINE_FINANCIERO!I65-_ENGINE_FINANCIERO!I56),(_ENGINE_FINANCIERO!I112-_ENGINE_FINANCIERO!I103),_ENGINE_FINANCIERO!I161),"") -> 5.8142483e+10 | J11: =IF(01_INPUTS!J17,CHOOSE(MATCH($B$2,$U$1:$U$5,0),_ENGINE_FINANCIERO!J161,(_ENGINE_FINANCIERO!J18-_ENGINE_FINANCIERO!J9),(_ENGINE_FINANCIERO!J65-_ENGINE_FINANCIERO!J56),(_ENGINE_FINANCIERO!J112-_ENGINE_FINANCIERO!J103),_ENGINE_FINANCIERO!J161),"") | K11: =IF(01_INPUTS!K17,CHOOSE(MATCH($B$2,$U$1:$U$5,0),_ENGINE_FINANCIERO!K161,(_ENGINE_FINANCIERO!K18-_ENGINE_FINANCIERO!K9),(_ENGINE_FINANCIERO!K65-_ENGINE_FINANCIERO!K56),(_ENGINE_FINANCIERO!K112-_ENGINE_FINANCIERO!K103),_ENGINE_FINANCIERO!K161),"") | L11: =IF(01_INPUTS!L17,CHOOSE(MATCH($B$2,$U$1:$U$5,0),_ENGINE_FINANCIERO!L161,(_ENGINE_FINANCIERO!L18-_ENGINE_FINANCIERO!L9),(_ENGINE_FINANCIERO!L65-_ENGINE_FINANCIERO!L56),(_ENGINE_FINANCIERO!L112-_ENGINE_FINANCIERO!L103),_ENGINE_FINANCIERO!L161),"") | M11: =IF(01_INPUTS!M17,CHOOSE(MATCH($B$2,$U$1:$U$5,0),_ENGINE_FINANCIERO!M161,(_ENGINE_FINANCIERO!M18-_ENGINE_FINANCIERO!M9),(_ENGINE_FINANCIERO!M65-_ENGINE_FINANCIERO!M56),(_ENGINE_FINANCIERO!M112-_ENGINE_FINANCIERO!M103),_ENGINE_FINANCIERO!M161),"") | N11: =IF(01_INPUTS!N17,CHOOSE(MATCH($B$2,$U$1:$U$5,0),_ENGINE_FINANCIERO!N161,(_ENGINE_FINANCIERO!N18-_ENGINE_FINANCIERO!N9),(_ENGINE_FINANCIERO!N65-_ENGINE_FINANCIERO!N56),(_ENGINE_FINANCIERO!N112-_ENGINE_FINANCIERO!N103),_ENGINE_FINANCIERO!N161),"") | O11: =IF(01_INPUTS!O17,CHOOSE(MATCH($B$2,$U$1:$U$5,0),_ENGINE_FINANCIERO!O161,(_ENGINE_FINANCIERO!O18-_ENGINE_FINANCIERO!O9),(_ENGINE_FINANCIERO!O65-_ENGINE_FINANCIERO!O56),(_ENGINE_FINANCIERO!O112-_ENGINE_FINANCIERO!O103),_ENGINE_FINANCIERO!O161),"") | P11: =IF(01_INPUTS!P17,CHOOSE(MATCH($B$2,$U$1:$U$5,0),_ENGINE_FINANCIERO!P161,(_ENGINE_FINANCIERO!P18-_ENGINE_FINANCIERO!P9),(_ENGINE_FINANCIERO!P65-_ENGINE_FINANCIERO!P56),(_ENGINE_FINANCIERO!P112-_ENGINE_FINANCIERO!P103),_ENGINE_FINANCIERO!P161),"") | ... S11: =IF(01_INPUTS!S17,CHOOSE(MATCH($B$2,$U$1:$U$5,0),_ENGINE_FINANCIERO!S161,(_ENGINE_FINANCIERO!S18-_ENGINE_FINANCIERO!S9),(_ENGINE_FINANCIERO!S65-_ENGINE_FINANCIERO!S56),(_ENGINE_FINANCIERO!S112-_ENGINE_FINANCIERO!S103),_ENGINE_FINANCIERO!S161),"")
A12: EE.UU. | B12: USD | G12: =(_ENGINE_FINANCIERO!G18-_ENGINE_FINANCIERO!G9) -> 0 | H12: =(_ENGINE_FINANCIERO!H18-_ENGINE_FINANCIERO!H9) -> 63000000 | I12: =IF(01_INPUTS!I17,(_ENGINE_FINANCIERO!I18-_ENGINE_FINANCIERO!I9),"") -> 2.7232405e+10 | J12: =IF(01_INPUTS!J17,(_ENGINE_FINANCIERO!J18-_ENGINE_FINANCIERO!J9),"") | K12: =IF(01_INPUTS!K17,(_ENGINE_FINANCIERO!K18-_ENGINE_FINANCIERO!K9),"") | L12: =IF(01_INPUTS!L17,(_ENGINE_FINANCIERO!L18-_ENGINE_FINANCIERO!L9),"") | M12: =IF(01_INPUTS!M17,(_ENGINE_FINANCIERO!M18-_ENGINE_FINANCIERO!M9),"") | N12: =IF(01_INPUTS!N17,(_ENGINE_FINANCIERO!N18-_ENGINE_FINANCIERO!N9),"") | O12: =IF(01_INPUTS!O17,(_ENGINE_FINANCIERO!O18-_ENGINE_FINANCIERO!O9),"") | P12: =IF(01_INPUTS!P17,(_ENGINE_FINANCIERO!P18-_ENGINE_FINANCIERO!P9),"") | ... S12: =IF(01_INPUTS!S17,(_ENGINE_FINANCIERO!S18-_ENGINE_FINANCIERO!S9),"")
A13: China | B13: USD | G13: =(_ENGINE_FINANCIERO!G65-_ENGINE_FINANCIERO!G56) -> 0 | H13: =(_ENGINE_FINANCIERO!H65-_ENGINE_FINANCIERO!H56) -> 95000000 | I13: =IF(01_INPUTS!I17,(_ENGINE_FINANCIERO!I65-_ENGINE_FINANCIERO!I56),"") -> 2.3565399e+10 | J13: =IF(01_INPUTS!J17,(_ENGINE_FINANCIERO!J65-_ENGINE_FINANCIERO!J56),"") | K13: =IF(01_INPUTS!K17,(_ENGINE_FINANCIERO!K65-_ENGINE_FINANCIERO!K56),"") | L13: =IF(01_INPUTS!L17,(_ENGINE_FINANCIERO!L65-_ENGINE_FINANCIERO!L56),"") | M13: =IF(01_INPUTS!M17,(_ENGINE_FINANCIERO!M65-_ENGINE_FINANCIERO!M56),"") | N13: =IF(01_INPUTS!N17,(_ENGINE_FINANCIERO!N65-_ENGINE_FINANCIERO!N56),"") | O13: =IF(01_INPUTS!O17,(_ENGINE_FINANCIERO!O65-_ENGINE_FINANCIERO!O56),"") | P13: =IF(01_INPUTS!P17,(_ENGINE_FINANCIERO!P65-_ENGINE_FINANCIERO!P56),"") | ... S13: =IF(01_INPUTS!S17,(_ENGINE_FINANCIERO!S65-_ENGINE_FINANCIERO!S56),"")
A14: Europa | B14: USD | G14: =(_ENGINE_FINANCIERO!G112-_ENGINE_FINANCIERO!G103) -> 0 | H14: =(_ENGINE_FINANCIERO!H112-_ENGINE_FINANCIERO!H103) -> 20000000 | I14: =IF(01_INPUTS!I17,(_ENGINE_FINANCIERO!I112-_ENGINE_FINANCIERO!I103),"") -> 7.344679e+09 | J14: =IF(01_INPUTS!J17,(_ENGINE_FINANCIERO!J112-_ENGINE_FINANCIERO!J103),"") | K14: =IF(01_INPUTS!K17,(_ENGINE_FINANCIERO!K112-_ENGINE_FINANCIERO!K103),"") | L14: =IF(01_INPUTS!L17,(_ENGINE_FINANCIERO!L112-_ENGINE_FINANCIERO!L103),"") | M14: =IF(01_INPUTS!M17,(_ENGINE_FINANCIERO!M112-_ENGINE_FINANCIERO!M103),"") | N14: =IF(01_INPUTS!N17,(_ENGINE_FINANCIERO!N112-_ENGINE_FINANCIERO!N103),"") | O14: =IF(01_INPUTS!O17,(_ENGINE_FINANCIERO!O112-_ENGINE_FINANCIERO!O103),"") | P14: =IF(01_INPUTS!P17,(_ENGINE_FINANCIERO!P112-_ENGINE_FINANCIERO!P103),"") | ... S14: =IF(01_INPUTS!S17,(_ENGINE_FINANCIERO!S112-_ENGINE_FINANCIERO!S103),"")
A15: EBITDA | B15: USD | G15: =CHOOSE(MATCH($B$2,$U$1:$U$5,0),_ENGINE_FINANCIERO!G162,_ENGINE_FINANCIERO!G19,_ENGINE_FINANCIERO!G66,_ENGINE_FINANCIERO!G113,_ENGINE_FINANCIERO!G162) -> 4.1511508e+09 | H15: =CHOOSE(MATCH($B$2,$U$1:$U$5,0),_ENGINE_FINANCIERO!H162,_ENGINE_FINANCIERO!H19,_ENGINE_FINANCIERO!H66,_ENGINE_FINANCIERO!H113,_ENGINE_FINANCIERO!H162) -> n/a | I15: =IF(01_INPUTS!I17,CHOOSE(MATCH($B$2,$U$1:$U$5,0),_ENGINE_FINANCIERO!I162,_ENGINE_FINANCIERO!I19,_ENGINE_FINANCIERO!I66,_ENGINE_FINANCIERO!I113,_ENGINE_FINANCIERO!I162),"") -> 1.879843e+10 | J15: =IF(01_INPUTS!J17,CHOOSE(MATCH($B$2,$U$1:$U$5,0),_ENGINE_FINANCIERO!J162,_ENGINE_FINANCIERO!J19,_ENGINE_FINANCIERO!J66,_ENGINE_FINANCIERO!J113,_ENGINE_FINANCIERO!J162),"") | K15: =IF(01_INPUTS!K17,CHOOSE(MATCH($B$2,$U$1:$U$5,0),_ENGINE_FINANCIERO!K162,_ENGINE_FINANCIERO!K19,_ENGINE_FINANCIERO!K66,_ENGINE_FINANCIERO!K113,_ENGINE_FINANCIERO!K162),"") | L15: =IF(01_INPUTS!L17,CHOOSE(MATCH($B$2,$U$1:$U$5,0),_ENGINE_FINANCIERO!L162,_ENGINE_FINANCIERO!L19,_ENGINE_FINANCIERO!L66,_ENGINE_FINANCIERO!L113,_ENGINE_FINANCIERO!L162),"") | M15: =IF(01_INPUTS!M17,CHOOSE(MATCH($B$2,$U$1:$U$5,0),_ENGINE_FINANCIERO!M162,_ENGINE_FINANCIERO!M19,_ENGINE_FINANCIERO!M66,_ENGINE_FINANCIERO!M113,_ENGINE_FINANCIERO!M162),"") | N15: =IF(01_INPUTS!N17,CHOOSE(MATCH($B$2,$U$1:$U$5,0),_ENGINE_FINANCIERO!N162,_ENGINE_FINANCIERO!N19,_ENGINE_FINANCIERO!N66,_ENGINE_FINANCIERO!N113,_ENGINE_FINANCIERO!N162),"") | O15: =IF(01_INPUTS!O17,CHOOSE(MATCH($B$2,$U$1:$U$5,0),_ENGINE_FINANCIERO!O162,_ENGINE_FINANCIERO!O19,_ENGINE_FINANCIERO!O66,_ENGINE_FINANCIERO!O113,_ENGINE_FINANCIERO!O162),"") | P15: =IF(01_INPUTS!P17,CHOOSE(MATCH($B$2,$U$1:$U$5,0),_ENGINE_FINANCIERO!P162,_ENGINE_FINANCIERO!P19,_ENGINE_FINANCIERO!P66,_ENGINE_FINANCIERO!P113,_ENGINE_FINANCIERO!P162),"") | ... S15: =IF(01_INPUTS!S17,CHOOSE(MATCH($B$2,$U$1:$U$5,0),_ENGINE_FINANCIERO!S162,_ENGINE_FINANCIERO!S19,_ENGINE_FINANCIERO!S66,_ENGINE_FINANCIERO!S113,_ENGINE_FINANCIERO!S162),"")
A16: EE.UU. | B16: USD | G16: =_ENGINE_FINANCIERO!G19 -> 0 | H16: =_ENGINE_FINANCIERO!H19 -> -63000000 | I16: =IF(01_INPUTS!I17,_ENGINE_FINANCIERO!I19,"") -> 4.0840869e+09 | J16: =IF(01_INPUTS!J17,_ENGINE_FINANCIERO!J19,"") | K16: =IF(01_INPUTS!K17,_ENGINE_FINANCIERO!K19,"") | L16: =IF(01_INPUTS!L17,_ENGINE_FINANCIERO!L19,"") | M16: =IF(01_INPUTS!M17,_ENGINE_FINANCIERO!M19,"") | N16: =IF(01_INPUTS!N17,_ENGINE_FINANCIERO!N19,"") | O16: =IF(01_INPUTS!O17,_ENGINE_FINANCIERO!O19,"") | P16: =IF(01_INPUTS!P17,_ENGINE_FINANCIERO!P19,"") | ... S16: =IF(01_INPUTS!S17,_ENGINE_FINANCIERO!S19,"")
A17: China | B17: USD | G17: =_ENGINE_FINANCIERO!G66 -> 0 | H17: =_ENGINE_FINANCIERO!H66 -> -95000000 | I17: =IF(01_INPUTS!I17,_ENGINE_FINANCIERO!I66,"") -> 3.5644927e+09 | J17: =IF(01_INPUTS!J17,_ENGINE_FINANCIERO!J66,"") | K17: =IF(01_INPUTS!K17,_ENGINE_FINANCIERO!K66,"") | L17: =IF(01_INPUTS!L17,_ENGINE_FINANCIERO!L66,"") | M17: =IF(01_INPUTS!M17,_ENGINE_FINANCIERO!M66,"") | N17: =IF(01_INPUTS!N17,_ENGINE_FINANCIERO!N66,"") | O17: =IF(01_INPUTS!O17,_ENGINE_FINANCIERO!O66,"") | P17: =IF(01_INPUTS!P17,_ENGINE_FINANCIERO!P66,"") | ... S17: =IF(01_INPUTS!S17,_ENGINE_FINANCIERO!S66,"")
A18: Europa | B18: USD | G18: =_ENGINE_FINANCIERO!G113 -> 0 | H18: =_ENGINE_FINANCIERO!H113 -> -20000000 | I18: =IF(01_INPUTS!I17,_ENGINE_FINANCIERO!I113,"") -> 1.114985e+10 | J18: =IF(01_INPUTS!J17,_ENGINE_FINANCIERO!J113,"") | K18: =IF(01_INPUTS!K17,_ENGINE_FINANCIERO!K113,"") | L18: =IF(01_INPUTS!L17,_ENGINE_FINANCIERO!L113,"") | M18: =IF(01_INPUTS!M17,_ENGINE_FINANCIERO!M113,"") | N18: =IF(01_INPUTS!N17,_ENGINE_FINANCIERO!N113,"") | O18: =IF(01_INPUTS!O17,_ENGINE_FINANCIERO!O113,"") | P18: =IF(01_INPUTS!P17,_ENGINE_FINANCIERO!P113,"") | ... S18: =IF(01_INPUTS!S17,_ENGINE_FINANCIERO!S113,"")
A19: Margen EBITDA (%) — sigue la vista de B2 (sin detalle por país, métrica derivada) | B19: % | G19: =IFERROR(G15/G7,"") -> 0.1051217 | H19: =IFERROR(H15/H7,"") | I19: =IF(01_INPUTS!I17,IFERROR(I15/I7,""),"") -> 0.24432294 | J19: =IF(01_INPUTS!J17,IFERROR(J15/J7,""),"") | K19: =IF(01_INPUTS!K17,IFERROR(K15/K7,""),"") | L19: =IF(01_INPUTS!L17,IFERROR(L15/L7,""),"") | M19: =IF(01_INPUTS!M17,IFERROR(M15/M7,""),"") | N19: =IF(01_INPUTS!N17,IFERROR(N15/N7,""),"") | O19: =IF(01_INPUTS!O17,IFERROR(O15/O7,""),"") | P19: =IF(01_INPUTS!P17,IFERROR(P15/P7,""),"") | ... S19: =IF(01_INPUTS!S17,IFERROR(S15/S7,""),"")
A20: Depreciación | B20: USD | G20: =CHOOSE(MATCH($B$2,$U$1:$U$5,0),_ENGINE_FINANCIERO!G163,_ENGINE_FINANCIERO!G20,_ENGINE_FINANCIERO!G67,_ENGINE_FINANCIERO!G114,_ENGINE_FINANCIERO!G163) -> 1203133800 | H20: =CHOOSE(MATCH($B$2,$U$1:$U$5,0),_ENGINE_FINANCIERO!H163,_ENGINE_FINANCIERO!H20,_ENGINE_FINANCIERO!H67,_ENGINE_FINANCIERO!H114,_ENGINE_FINANCIERO!H163) -> 1082820420 | I20: =IF(01_INPUTS!I17,CHOOSE(MATCH($B$2,$U$1:$U$5,0),_ENGINE_FINANCIERO!I163,_ENGINE_FINANCIERO!I20,_ENGINE_FINANCIERO!I67,_ENGINE_FINANCIERO!I114,_ENGINE_FINANCIERO!I163),"") -> 976338378 | J20: =IF(01_INPUTS!J17,CHOOSE(MATCH($B$2,$U$1:$U$5,0),_ENGINE_FINANCIERO!J163,_ENGINE_FINANCIERO!J20,_ENGINE_FINANCIERO!J67,_ENGINE_FINANCIERO!J114,_ENGINE_FINANCIERO!J163),"") | K20: =IF(01_INPUTS!K17,CHOOSE(MATCH($B$2,$U$1:$U$5,0),_ENGINE_FINANCIERO!K163,_ENGINE_FINANCIERO!K20,_ENGINE_FINANCIERO!K67,_ENGINE_FINANCIERO!K114,_ENGINE_FINANCIERO!K163),"") | L20: =IF(01_INPUTS!L17,CHOOSE(MATCH($B$2,$U$1:$U$5,0),_ENGINE_FINANCIERO!L163,_ENGINE_FINANCIERO!L20,_ENGINE_FINANCIERO!L67,_ENGINE_FINANCIERO!L114,_ENGINE_FINANCIERO!L163),"") | M20: =IF(01_INPUTS!M17,CHOOSE(MATCH($B$2,$U$1:$U$5,0),_ENGINE_FINANCIERO!M163,_ENGINE_FINANCIERO!M20,_ENGINE_FINANCIERO!M67,_ENGINE_FINANCIERO!M114,_ENGINE_FINANCIERO!M163),"") | N20: =IF(01_INPUTS!N17,CHOOSE(MATCH($B$2,$U$1:$U$5,0),_ENGINE_FINANCIERO!N163,_ENGINE_FINANCIERO!N20,_ENGINE_FINANCIERO!N67,_ENGINE_FINANCIERO!N114,_ENGINE_FINANCIERO!N163),"") | O20: =IF(01_INPUTS!O17,CHOOSE(MATCH($B$2,$U$1:$U$5,0),_ENGINE_FINANCIERO!O163,_ENGINE_FINANCIERO!O20,_ENGINE_FINANCIERO!O67,_ENGINE_FINANCIERO!O114,_ENGINE_FINANCIERO!O163),"") | P20: =IF(01_INPUTS!P17,CHOOSE(MATCH($B$2,$U$1:$U$5,0),_ENGINE_FINANCIERO!P163,_ENGINE_FINANCIERO!P20,_ENGINE_FINANCIERO!P67,_ENGINE_FINANCIERO!P114,_ENGINE_FINANCIERO!P163),"") | ... S20: =IF(01_INPUTS!S17,CHOOSE(MATCH($B$2,$U$1:$U$5,0),_ENGINE_FINANCIERO!S163,_ENGINE_FINANCIERO!S20,_ENGINE_FINANCIERO!S67,_ENGINE_FINANCIERO!S114,_ENGINE_FINANCIERO!S163),"")
A21: EE.UU. | B21: USD | G21: =_ENGINE_FINANCIERO!G20 -> 1005068400 | H21: =_ENGINE_FINANCIERO!H20 -> 904561560 | I21: =IF(01_INPUTS!I17,_ENGINE_FINANCIERO!I20,"") -> 815505404 | J21: =IF(01_INPUTS!J17,_ENGINE_FINANCIERO!J20,"") | K21: =IF(01_INPUTS!K17,_ENGINE_FINANCIERO!K20,"") | L21: =IF(01_INPUTS!L17,_ENGINE_FINANCIERO!L20,"") | M21: =IF(01_INPUTS!M17,_ENGINE_FINANCIERO!M20,"") | N21: =IF(01_INPUTS!N17,_ENGINE_FINANCIERO!N20,"") | O21: =IF(01_INPUTS!O17,_ENGINE_FINANCIERO!O20,"") | P21: =IF(01_INPUTS!P17,_ENGINE_FINANCIERO!P20,"") | ... S21: =IF(01_INPUTS!S17,_ENGINE_FINANCIERO!S20,"")
A22: China | B22: USD | G22: =_ENGINE_FINANCIERO!G67 -> 198065400 | H22: =_ENGINE_FINANCIERO!H67 -> 178258860 | I22: =IF(01_INPUTS!I17,_ENGINE_FINANCIERO!I67,"") -> 160832974 | J22: =IF(01_INPUTS!J17,_ENGINE_FINANCIERO!J67,"") | K22: =IF(01_INPUTS!K17,_ENGINE_FINANCIERO!K67,"") | L22: =IF(01_INPUTS!L17,_ENGINE_FINANCIERO!L67,"") | M22: =IF(01_INPUTS!M17,_ENGINE_FINANCIERO!M67,"") | N22: =IF(01_INPUTS!N17,_ENGINE_FINANCIERO!N67,"") | O22: =IF(01_INPUTS!O17,_ENGINE_FINANCIERO!O67,"") | P22: =IF(01_INPUTS!P17,_ENGINE_FINANCIERO!P67,"") | ... S22: =IF(01_INPUTS!S17,_ENGINE_FINANCIERO!S67,"")
A23: Europa | B23: USD | G23: =_ENGINE_FINANCIERO!G114 -> 0 | H23: =_ENGINE_FINANCIERO!H114 -> 0 | I23: =IF(01_INPUTS!I17,_ENGINE_FINANCIERO!I114,"") -> 0 | J23: =IF(01_INPUTS!J17,_ENGINE_FINANCIERO!J114,"") | K23: =IF(01_INPUTS!K17,_ENGINE_FINANCIERO!K114,"") | L23: =IF(01_INPUTS!L17,_ENGINE_FINANCIERO!L114,"") | M23: =IF(01_INPUTS!M17,_ENGINE_FINANCIERO!M114,"") | N23: =IF(01_INPUTS!N17,_ENGINE_FINANCIERO!N114,"") | O23: =IF(01_INPUTS!O17,_ENGINE_FINANCIERO!O114,"") | P23: =IF(01_INPUTS!P17,_ENGINE_FINANCIERO!P114,"") | ... S23: =IF(01_INPUTS!S17,_ENGINE_FINANCIERO!S114,"")
A24: EBIT | B24: USD | G24: =CHOOSE(MATCH($B$2,$U$1:$U$5,0),_ENGINE_FINANCIERO!G164,_ENGINE_FINANCIERO!G21,_ENGINE_FINANCIERO!G68,_ENGINE_FINANCIERO!G115,_ENGINE_FINANCIERO!G164) -> 2.948017e+09 | H24: =CHOOSE(MATCH($B$2,$U$1:$U$5,0),_ENGINE_FINANCIERO!H164,_ENGINE_FINANCIERO!H21,_ENGINE_FINANCIERO!H68,_ENGINE_FINANCIERO!H115,_ENGINE_FINANCIERO!H164) -> n/a | I24: =IF(01_INPUTS!I17,CHOOSE(MATCH($B$2,$U$1:$U$5,0),_ENGINE_FINANCIERO!I164,_ENGINE_FINANCIERO!I21,_ENGINE_FINANCIERO!I68,_ENGINE_FINANCIERO!I115,_ENGINE_FINANCIERO!I164),"") -> 1.7822091e+10 | J24: =IF(01_INPUTS!J17,CHOOSE(MATCH($B$2,$U$1:$U$5,0),_ENGINE_FINANCIERO!J164,_ENGINE_FINANCIERO!J21,_ENGINE_FINANCIERO!J68,_ENGINE_FINANCIERO!J115,_ENGINE_FINANCIERO!J164),"") | K24: =IF(01_INPUTS!K17,CHOOSE(MATCH($B$2,$U$1:$U$5,0),_ENGINE_FINANCIERO!K164,_ENGINE_FINANCIERO!K21,_ENGINE_FINANCIERO!K68,_ENGINE_FINANCIERO!K115,_ENGINE_FINANCIERO!K164),"") | L24: =IF(01_INPUTS!L17,CHOOSE(MATCH($B$2,$U$1:$U$5,0),_ENGINE_FINANCIERO!L164,_ENGINE_FINANCIERO!L21,_ENGINE_FINANCIERO!L68,_ENGINE_FINANCIERO!L115,_ENGINE_FINANCIERO!L164),"") | M24: =IF(01_INPUTS!M17,CHOOSE(MATCH($B$2,$U$1:$U$5,0),_ENGINE_FINANCIERO!M164,_ENGINE_FINANCIERO!M21,_ENGINE_FINANCIERO!M68,_ENGINE_FINANCIERO!M115,_ENGINE_FINANCIERO!M164),"") | N24: =IF(01_INPUTS!N17,CHOOSE(MATCH($B$2,$U$1:$U$5,0),_ENGINE_FINANCIERO!N164,_ENGINE_FINANCIERO!N21,_ENGINE_FINANCIERO!N68,_ENGINE_FINANCIERO!N115,_ENGINE_FINANCIERO!N164),"") | O24: =IF(01_INPUTS!O17,CHOOSE(MATCH($B$2,$U$1:$U$5,0),_ENGINE_FINANCIERO!O164,_ENGINE_FINANCIERO!O21,_ENGINE_FINANCIERO!O68,_ENGINE_FINANCIERO!O115,_ENGINE_FINANCIERO!O164),"") | P24: =IF(01_INPUTS!P17,CHOOSE(MATCH($B$2,$U$1:$U$5,0),_ENGINE_FINANCIERO!P164,_ENGINE_FINANCIERO!P21,_ENGINE_FINANCIERO!P68,_ENGINE_FINANCIERO!P115,_ENGINE_FINANCIERO!P164),"") | ... S24: =IF(01_INPUTS!S17,CHOOSE(MATCH($B$2,$U$1:$U$5,0),_ENGINE_FINANCIERO!S164,_ENGINE_FINANCIERO!S21,_ENGINE_FINANCIERO!S68,_ENGINE_FINANCIERO!S115,_ENGINE_FINANCIERO!S164),"")
A25: EE.UU. | B25: USD | G25: =_ENGINE_FINANCIERO!G21 -> -1005068400 | H25: =_ENGINE_FINANCIERO!H21 -> -967561560 | I25: =IF(01_INPUTS!I17,_ENGINE_FINANCIERO!I21,"") -> 3.2685815e+09 | J25: =IF(01_INPUTS!J17,_ENGINE_FINANCIERO!J21,"") | K25: =IF(01_INPUTS!K17,_ENGINE_FINANCIERO!K21,"") | L25: =IF(01_INPUTS!L17,_ENGINE_FINANCIERO!L21,"") | M25: =IF(01_INPUTS!M17,_ENGINE_FINANCIERO!M21,"") | N25: =IF(01_INPUTS!N17,_ENGINE_FINANCIERO!N21,"") | O25: =IF(01_INPUTS!O17,_ENGINE_FINANCIERO!O21,"") | P25: =IF(01_INPUTS!P17,_ENGINE_FINANCIERO!P21,"") | ... S25: =IF(01_INPUTS!S17,_ENGINE_FINANCIERO!S21,"")
A26: China | B26: USD | G26: =_ENGINE_FINANCIERO!G68 -> -198065400 | H26: =_ENGINE_FINANCIERO!H68 -> -273258860 | I26: =IF(01_INPUTS!I17,_ENGINE_FINANCIERO!I68,"") -> 3.4036597e+09 | J26: =IF(01_INPUTS!J17,_ENGINE_FINANCIERO!J68,"") | K26: =IF(01_INPUTS!K17,_ENGINE_FINANCIERO!K68,"") | L26: =IF(01_INPUTS!L17,_ENGINE_FINANCIERO!L68,"") | M26: =IF(01_INPUTS!M17,_ENGINE_FINANCIERO!M68,"") | N26: =IF(01_INPUTS!N17,_ENGINE_FINANCIERO!N68,"") | O26: =IF(01_INPUTS!O17,_ENGINE_FINANCIERO!O68,"") | P26: =IF(01_INPUTS!P17,_ENGINE_FINANCIERO!P68,"") | ... S26: =IF(01_INPUTS!S17,_ENGINE_FINANCIERO!S68,"")
A27: Europa | B27: USD | G27: =_ENGINE_FINANCIERO!G115 -> 0 | H27: =_ENGINE_FINANCIERO!H115 -> -20000000 | I27: =IF(01_INPUTS!I17,_ENGINE_FINANCIERO!I115,"") -> 1.114985e+10 | J27: =IF(01_INPUTS!J17,_ENGINE_FINANCIERO!J115,"") | K27: =IF(01_INPUTS!K17,_ENGINE_FINANCIERO!K115,"") | L27: =IF(01_INPUTS!L17,_ENGINE_FINANCIERO!L115,"") | M27: =IF(01_INPUTS!M17,_ENGINE_FINANCIERO!M115,"") | N27: =IF(01_INPUTS!N17,_ENGINE_FINANCIERO!N115,"") | O27: =IF(01_INPUTS!O17,_ENGINE_FINANCIERO!O115,"") | P27: =IF(01_INPUTS!P17,_ENGINE_FINANCIERO!P115,"") | ... S27: =IF(01_INPUTS!S17,_ENGINE_FINANCIERO!S115,"")
A28: Gastos financieros netos | B28: USD | G28: =CHOOSE(MATCH($B$2,$U$1:$U$5,0),_ENGINE_FINANCIERO!G165,_ENGINE_FINANCIERO!G22,_ENGINE_FINANCIERO!G69,_ENGINE_FINANCIERO!G116,_ENGINE_FINANCIERO!G165) -> 6.4270758e+08 | H28: =CHOOSE(MATCH($B$2,$U$1:$U$5,0),_ENGINE_FINANCIERO!H165,_ENGINE_FINANCIERO!H22,_ENGINE_FINANCIERO!H69,_ENGINE_FINANCIERO!H116,_ENGINE_FINANCIERO!H165) -> n/a | I28: =IF(01_INPUTS!I17,CHOOSE(MATCH($B$2,$U$1:$U$5,0),_ENGINE_FINANCIERO!I165,_ENGINE_FINANCIERO!I22,_ENGINE_FINANCIERO!I69,_ENGINE_FINANCIERO!I116,_ENGINE_FINANCIERO!I165),"") -> 3.7475015e+08 | J28: =IF(01_INPUTS!J17,CHOOSE(MATCH($B$2,$U$1:$U$5,0),_ENGINE_FINANCIERO!J165,_ENGINE_FINANCIERO!J22,_ENGINE_FINANCIERO!J69,_ENGINE_FINANCIERO!J116,_ENGINE_FINANCIERO!J165),"") | K28: =IF(01_INPUTS!K17,CHOOSE(MATCH($B$2,$U$1:$U$5,0),_ENGINE_FINANCIERO!K165,_ENGINE_FINANCIERO!K22,_ENGINE_FINANCIERO!K69,_ENGINE_FINANCIERO!K116,_ENGINE_FINANCIERO!K165),"") | L28: =IF(01_INPUTS!L17,CHOOSE(MATCH($B$2,$U$1:$U$5,0),_ENGINE_FINANCIERO!L165,_ENGINE_FINANCIERO!L22,_ENGINE_FINANCIERO!L69,_ENGINE_FINANCIERO!L116,_ENGINE_FINANCIERO!L165),"") | M28: =IF(01_INPUTS!M17,CHOOSE(MATCH($B$2,$U$1:$U$5,0),_ENGINE_FINANCIERO!M165,_ENGINE_FINANCIERO!M22,_ENGINE_FINANCIERO!M69,_ENGINE_FINANCIERO!M116,_ENGINE_FINANCIERO!M165),"") | N28: =IF(01_INPUTS!N17,CHOOSE(MATCH($B$2,$U$1:$U$5,0),_ENGINE_FINANCIERO!N165,_ENGINE_FINANCIERO!N22,_ENGINE_FINANCIERO!N69,_ENGINE_FINANCIERO!N116,_ENGINE_FINANCIERO!N165),"") | O28: =IF(01_INPUTS!O17,CHOOSE(MATCH($B$2,$U$1:$U$5,0),_ENGINE_FINANCIERO!O165,_ENGINE_FINANCIERO!O22,_ENGINE_FINANCIERO!O69,_ENGINE_FINANCIERO!O116,_ENGINE_FINANCIERO!O165),"") | P28: =IF(01_INPUTS!P17,CHOOSE(MATCH($B$2,$U$1:$U$5,0),_ENGINE_FINANCIERO!P165,_ENGINE_FINANCIERO!P22,_ENGINE_FINANCIERO!P69,_ENGINE_FINANCIERO!P116,_ENGINE_FINANCIERO!P165),"") | ... S28: =IF(01_INPUTS!S17,CHOOSE(MATCH($B$2,$U$1:$U$5,0),_ENGINE_FINANCIERO!S165,_ENGINE_FINANCIERO!S22,_ENGINE_FINANCIERO!S69,_ENGINE_FINANCIERO!S116,_ENGINE_FINANCIERO!S165),"")
A29: EE.UU. | B29: USD | G29: =_ENGINE_FINANCIERO!G22 -> 5.2918124e+08 | H29: =_ENGINE_FINANCIERO!H22 -> 4.5358412e+08 | I29: =IF(01_INPUTS!I17,_ENGINE_FINANCIERO!I22,"") -> 5.5138856e+08 | J29: =IF(01_INPUTS!J17,_ENGINE_FINANCIERO!J22,"") | K29: =IF(01_INPUTS!K17,_ENGINE_FINANCIERO!K22,"") | L29: =IF(01_INPUTS!L17,_ENGINE_FINANCIERO!L22,"") | M29: =IF(01_INPUTS!M17,_ENGINE_FINANCIERO!M22,"") | N29: =IF(01_INPUTS!N17,_ENGINE_FINANCIERO!N22,"") | O29: =IF(01_INPUTS!O17,_ENGINE_FINANCIERO!O22,"") | P29: =IF(01_INPUTS!P17,_ENGINE_FINANCIERO!P22,"") | ... S29: =IF(01_INPUTS!S17,_ENGINE_FINANCIERO!S22,"")
A30: China | B30: USD | G30: =_ENGINE_FINANCIERO!G69 -> 1.19425e+08 | H30: =_ENGINE_FINANCIERO!H69 -> -72726647 | I30: =IF(01_INPUTS!I17,_ENGINE_FINANCIERO!I69,"") -> -1.2537651e+08 | J30: =IF(01_INPUTS!J17,_ENGINE_FINANCIERO!J69,"") | K30: =IF(01_INPUTS!K17,_ENGINE_FINANCIERO!K69,"") | L30: =IF(01_INPUTS!L17,_ENGINE_FINANCIERO!L69,"") | M30: =IF(01_INPUTS!M17,_ENGINE_FINANCIERO!M69,"") | N30: =IF(01_INPUTS!N17,_ENGINE_FINANCIERO!N69,"") | O30: =IF(01_INPUTS!O17,_ENGINE_FINANCIERO!O69,"") | P30: =IF(01_INPUTS!P17,_ENGINE_FINANCIERO!P69,"") | ... S30: =IF(01_INPUTS!S17,_ENGINE_FINANCIERO!S69,"")
A31: Europa | B31: USD | G31: =_ENGINE_FINANCIERO!G116 -> -5898652.7 | H31: =_ENGINE_FINANCIERO!H116 -> -43304006 | I31: =IF(01_INPUTS!I17,_ENGINE_FINANCIERO!I116,"") -> -51261897 | J31: =IF(01_INPUTS!J17,_ENGINE_FINANCIERO!J116,"") | K31: =IF(01_INPUTS!K17,_ENGINE_FINANCIERO!K116,"") | L31: =IF(01_INPUTS!L17,_ENGINE_FINANCIERO!L116,"") | M31: =IF(01_INPUTS!M17,_ENGINE_FINANCIERO!M116,"") | N31: =IF(01_INPUTS!N17,_ENGINE_FINANCIERO!N116,"") | O31: =IF(01_INPUTS!O17,_ENGINE_FINANCIERO!O116,"") | P31: =IF(01_INPUTS!P17,_ENGINE_FINANCIERO!P116,"") | ... S31: =IF(01_INPUTS!S17,_ENGINE_FINANCIERO!S116,"")
A32: Beneficio antes de impuestos | B32: USD | G32: =CHOOSE(MATCH($B$2,$U$1:$U$5,0),_ENGINE_FINANCIERO!G166,_ENGINE_FINANCIERO!G23,_ENGINE_FINANCIERO!G70,_ENGINE_FINANCIERO!G117,_ENGINE_FINANCIERO!G166) -> 2.3053094e+09 | H32: =CHOOSE(MATCH($B$2,$U$1:$U$5,0),_ENGINE_FINANCIERO!H166,_ENGINE_FINANCIERO!H23,_ENGINE_FINANCIERO!H70,_ENGINE_FINANCIERO!H117,_ENGINE_FINANCIERO!H166) -> n/a | I32: =IF(01_INPUTS!I17,CHOOSE(MATCH($B$2,$U$1:$U$5,0),_ENGINE_FINANCIERO!I166,_ENGINE_FINANCIERO!I23,_ENGINE_FINANCIERO!I70,_ENGINE_FINANCIERO!I117,_ENGINE_FINANCIERO!I166),"") -> 1.7447341e+10 | J32: =IF(01_INPUTS!J17,CHOOSE(MATCH($B$2,$U$1:$U$5,0),_ENGINE_FINANCIERO!J166,_ENGINE_FINANCIERO!J23,_ENGINE_FINANCIERO!J70,_ENGINE_FINANCIERO!J117,_ENGINE_FINANCIERO!J166),"") | K32: =IF(01_INPUTS!K17,CHOOSE(MATCH($B$2,$U$1:$U$5,0),_ENGINE_FINANCIERO!K166,_ENGINE_FINANCIERO!K23,_ENGINE_FINANCIERO!K70,_ENGINE_FINANCIERO!K117,_ENGINE_FINANCIERO!K166),"") | L32: =IF(01_INPUTS!L17,CHOOSE(MATCH($B$2,$U$1:$U$5,0),_ENGINE_FINANCIERO!L166,_ENGINE_FINANCIERO!L23,_ENGINE_FINANCIERO!L70,_ENGINE_FINANCIERO!L117,_ENGINE_FINANCIERO!L166),"") | M32: =IF(01_INPUTS!M17,CHOOSE(MATCH($B$2,$U$1:$U$5,0),_ENGINE_FINANCIERO!M166,_ENGINE_FINANCIERO!M23,_ENGINE_FINANCIERO!M70,_ENGINE_FINANCIERO!M117,_ENGINE_FINANCIERO!M166),"") | N32: =IF(01_INPUTS!N17,CHOOSE(MATCH($B$2,$U$1:$U$5,0),_ENGINE_FINANCIERO!N166,_ENGINE_FINANCIERO!N23,_ENGINE_FINANCIERO!N70,_ENGINE_FINANCIERO!N117,_ENGINE_FINANCIERO!N166),"") | O32: =IF(01_INPUTS!O17,CHOOSE(MATCH($B$2,$U$1:$U$5,0),_ENGINE_FINANCIERO!O166,_ENGINE_FINANCIERO!O23,_ENGINE_FINANCIERO!O70,_ENGINE_FINANCIERO!O117,_ENGINE_FINANCIERO!O166),"") | P32: =IF(01_INPUTS!P17,CHOOSE(MATCH($B$2,$U$1:$U$5,0),_ENGINE_FINANCIERO!P166,_ENGINE_FINANCIERO!P23,_ENGINE_FINANCIERO!P70,_ENGINE_FINANCIERO!P117,_ENGINE_FINANCIERO!P166),"") | ... S32: =IF(01_INPUTS!S17,CHOOSE(MATCH($B$2,$U$1:$U$5,0),_ENGINE_FINANCIERO!S166,_ENGINE_FINANCIERO!S23,_ENGINE_FINANCIERO!S70,_ENGINE_FINANCIERO!S117,_ENGINE_FINANCIERO!S166),"")
A33: EE.UU. | B33: USD | G33: =_ENGINE_FINANCIERO!G23 -> 9.6797274e+08 | H33: =_ENGINE_FINANCIERO!H23 -> 1.5018073e+09 | I33: =IF(01_INPUTS!I17,_ENGINE_FINANCIERO!I23,"") -> 2.7171929e+09 | J33: =IF(01_INPUTS!J17,_ENGINE_FINANCIERO!J23,"") | K33: =IF(01_INPUTS!K17,_ENGINE_FINANCIERO!K23,"") | L33: =IF(01_INPUTS!L17,_ENGINE_FINANCIERO!L23,"") | M33: =IF(01_INPUTS!M17,_ENGINE_FINANCIERO!M23,"") | N33: =IF(01_INPUTS!N17,_ENGINE_FINANCIERO!N23,"") | O33: =IF(01_INPUTS!O17,_ENGINE_FINANCIERO!O23,"") | P33: =IF(01_INPUTS!P17,_ENGINE_FINANCIERO!P23,"") | ... S33: =IF(01_INPUTS!S17,_ENGINE_FINANCIERO!S23,"")
A34: China | B34: USD | G34: =_ENGINE_FINANCIERO!G70 -> 5.1717431e+08 | H34: =_ENGINE_FINANCIERO!H70 -> 2.0651992e+09 | I34: =IF(01_INPUTS!I17,_ENGINE_FINANCIERO!I70,"") -> 3.5290362e+09 | J34: =IF(01_INPUTS!J17,_ENGINE_FINANCIERO!J70,"") | K34: =IF(01_INPUTS!K17,_ENGINE_FINANCIERO!K70,"") | L34: =IF(01_INPUTS!L17,_ENGINE_FINANCIERO!L70,"") | M34: =IF(01_INPUTS!M17,_ENGINE_FINANCIERO!M70,"") | N34: =IF(01_INPUTS!N17,_ENGINE_FINANCIERO!N70,"") | O34: =IF(01_INPUTS!O17,_ENGINE_FINANCIERO!O70,"") | P34: =IF(01_INPUTS!P17,_ENGINE_FINANCIERO!P70,"") | ... S34: =IF(01_INPUTS!S17,_ENGINE_FINANCIERO!S70,"")
A35: Europa | B35: USD | G35: =_ENGINE_FINANCIERO!G117 -> 8.2016234e+08 | H35: =_ENGINE_FINANCIERO!H117 -> 1.2178457e+09 | I35: =IF(01_INPUTS!I17,_ENGINE_FINANCIERO!I117,"") -> 1.1201112e+10 | J35: =IF(01_INPUTS!J17,_ENGINE_FINANCIERO!J117,"") | K35: =IF(01_INPUTS!K17,_ENGINE_FINANCIERO!K117,"") | L35: =IF(01_INPUTS!L17,_ENGINE_FINANCIERO!L117,"") | M35: =IF(01_INPUTS!M17,_ENGINE_FINANCIERO!M117,"") | N35: =IF(01_INPUTS!N17,_ENGINE_FINANCIERO!N117,"") | O35: =IF(01_INPUTS!O17,_ENGINE_FINANCIERO!O117,"") | P35: =IF(01_INPUTS!P17,_ENGINE_FINANCIERO!P117,"") | ... S35: =IF(01_INPUTS!S17,_ENGINE_FINANCIERO!S117,"")
A36: Impuesto sobre el beneficio | B36: USD | G36: =CHOOSE(MATCH($B$2,$U$1:$U$5,0),_ENGINE_FINANCIERO!G167,_ENGINE_FINANCIERO!G28,_ENGINE_FINANCIERO!G75,_ENGINE_FINANCIERO!G122,_ENGINE_FINANCIERO!G167) -> 5.6369141e+08 | H36: =CHOOSE(MATCH($B$2,$U$1:$U$5,0),_ENGINE_FINANCIERO!H167,_ENGINE_FINANCIERO!H28,_ENGINE_FINANCIERO!H75,_ENGINE_FINANCIERO!H122,_ENGINE_FINANCIERO!H167) -> n/a | I36: =IF(01_INPUTS!I17,CHOOSE(MATCH($B$2,$U$1:$U$5,0),_ENGINE_FINANCIERO!I167,_ENGINE_FINANCIERO!I28,_ENGINE_FINANCIERO!I75,_ENGINE_FINANCIERO!I122,_ENGINE_FINANCIERO!I167),"") -> 3.832275e+09 | J36: =IF(01_INPUTS!J17,CHOOSE(MATCH($B$2,$U$1:$U$5,0),_ENGINE_FINANCIERO!J167,_ENGINE_FINANCIERO!J28,_ENGINE_FINANCIERO!J75,_ENGINE_FINANCIERO!J122,_ENGINE_FINANCIERO!J167),"") | K36: =IF(01_INPUTS!K17,CHOOSE(MATCH($B$2,$U$1:$U$5,0),_ENGINE_FINANCIERO!K167,_ENGINE_FINANCIERO!K28,_ENGINE_FINANCIERO!K75,_ENGINE_FINANCIERO!K122,_ENGINE_FINANCIERO!K167),"") | L36: =IF(01_INPUTS!L17,CHOOSE(MATCH($B$2,$U$1:$U$5,0),_ENGINE_FINANCIERO!L167,_ENGINE_FINANCIERO!L28,_ENGINE_FINANCIERO!L75,_ENGINE_FINANCIERO!L122,_ENGINE_FINANCIERO!L167),"") | M36: =IF(01_INPUTS!M17,CHOOSE(MATCH($B$2,$U$1:$U$5,0),_ENGINE_FINANCIERO!M167,_ENGINE_FINANCIERO!M28,_ENGINE_FINANCIERO!M75,_ENGINE_FINANCIERO!M122,_ENGINE_FINANCIERO!M167),"") | N36: =IF(01_INPUTS!N17,CHOOSE(MATCH($B$2,$U$1:$U$5,0),_ENGINE_FINANCIERO!N167,_ENGINE_FINANCIERO!N28,_ENGINE_FINANCIERO!N75,_ENGINE_FINANCIERO!N122,_ENGINE_FINANCIERO!N167),"") | O36: =IF(01_INPUTS!O17,CHOOSE(MATCH($B$2,$U$1:$U$5,0),_ENGINE_FINANCIERO!O167,_ENGINE_FINANCIERO!O28,_ENGINE_FINANCIERO!O75,_ENGINE_FINANCIERO!O122,_ENGINE_FINANCIERO!O167),"") | P36: =IF(01_INPUTS!P17,CHOOSE(MATCH($B$2,$U$1:$U$5,0),_ENGINE_FINANCIERO!P167,_ENGINE_FINANCIERO!P28,_ENGINE_FINANCIERO!P75,_ENGINE_FINANCIERO!P122,_ENGINE_FINANCIERO!P167),"") | ... S36: =IF(01_INPUTS!S17,CHOOSE(MATCH($B$2,$U$1:$U$5,0),_ENGINE_FINANCIERO!S167,_ENGINE_FINANCIERO!S28,_ENGINE_FINANCIERO!S75,_ENGINE_FINANCIERO!S122,_ENGINE_FINANCIERO!S167),"")
A37: EE.UU. | B37: USD | G37: =_ENGINE_FINANCIERO!G28 -> 2.12954e+08 | H37: =_ENGINE_FINANCIERO!H28 -> 3.3039761e+08 | I37: =IF(01_INPUTS!I17,_ENGINE_FINANCIERO!I28,"") -> 5.9778245e+08 | J37: =IF(01_INPUTS!J17,_ENGINE_FINANCIERO!J28,"") | K37: =IF(01_INPUTS!K17,_ENGINE_FINANCIERO!K28,"") | L37: =IF(01_INPUTS!L17,_ENGINE_FINANCIERO!L28,"") | M37: =IF(01_INPUTS!M17,_ENGINE_FINANCIERO!M28,"") | N37: =IF(01_INPUTS!N17,_ENGINE_FINANCIERO!N28,"") | O37: =IF(01_INPUTS!O17,_ENGINE_FINANCIERO!O28,"") | P37: =IF(01_INPUTS!P17,_ENGINE_FINANCIERO!P28,"") | ... S37: =IF(01_INPUTS!S17,_ENGINE_FINANCIERO!S28,"")
A38: China | B38: USD | G38: =_ENGINE_FINANCIERO!G75 -> 1.2929358e+08 | H38: =_ENGINE_FINANCIERO!H75 -> 5.1629981e+08 | I38: =IF(01_INPUTS!I17,_ENGINE_FINANCIERO!I75,"") -> 8.8225905e+08 | J38: =IF(01_INPUTS!J17,_ENGINE_FINANCIERO!J75,"") | K38: =IF(01_INPUTS!K17,_ENGINE_FINANCIERO!K75,"") | L38: =IF(01_INPUTS!L17,_ENGINE_FINANCIERO!L75,"") | M38: =IF(01_INPUTS!M17,_ENGINE_FINANCIERO!M75,"") | N38: =IF(01_INPUTS!N17,_ENGINE_FINANCIERO!N75,"") | O38: =IF(01_INPUTS!O17,_ENGINE_FINANCIERO!O75,"") | P38: =IF(01_INPUTS!P17,_ENGINE_FINANCIERO!P75,"") | ... S38: =IF(01_INPUTS!S17,_ENGINE_FINANCIERO!S75,"")
A39: Europa | B39: USD | G39: =_ENGINE_FINANCIERO!G122 -> 2.2144383e+08 | H39: =_ENGINE_FINANCIERO!H122 -> 3.2881833e+08 | I39: =IF(01_INPUTS!I17,_ENGINE_FINANCIERO!I122,"") -> 2.3522335e+09 | J39: =IF(01_INPUTS!J17,_ENGINE_FINANCIERO!J122,"") | K39: =IF(01_INPUTS!K17,_ENGINE_FINANCIERO!K122,"") | L39: =IF(01_INPUTS!L17,_ENGINE_FINANCIERO!L122,"") | M39: =IF(01_INPUTS!M17,_ENGINE_FINANCIERO!M122,"") | N39: =IF(01_INPUTS!N17,_ENGINE_FINANCIERO!N122,"") | O39: =IF(01_INPUTS!O17,_ENGINE_FINANCIERO!O122,"") | P39: =IF(01_INPUTS!P17,_ENGINE_FINANCIERO!P122,"") | ... S39: =IF(01_INPUTS!S17,_ENGINE_FINANCIERO!S122,"")
A40: Beneficio de la ronda (neto) | B40: USD | G40: =CHOOSE(MATCH($B$2,$U$1:$U$5,0),_ENGINE_FINANCIERO!G168,_ENGINE_FINANCIERO!G29,_ENGINE_FINANCIERO!G76,_ENGINE_FINANCIERO!G123,_ENGINE_FINANCIERO!G168) -> 1.741618e+09 | H40: =CHOOSE(MATCH($B$2,$U$1:$U$5,0),_ENGINE_FINANCIERO!H168,_ENGINE_FINANCIERO!H29,_ENGINE_FINANCIERO!H76,_ENGINE_FINANCIERO!H123,_ENGINE_FINANCIERO!H168) -> 3.6093365e+09 | I40: =IF(01_INPUTS!I17,CHOOSE(MATCH($B$2,$U$1:$U$5,0),_ENGINE_FINANCIERO!I168,_ENGINE_FINANCIERO!I29,_ENGINE_FINANCIERO!I76,_ENGINE_FINANCIERO!I123,_ENGINE_FINANCIERO!I168),"") -> 1.3615066e+10 | J40: =IF(01_INPUTS!J17,CHOOSE(MATCH($B$2,$U$1:$U$5,0),_ENGINE_FINANCIERO!J168,_ENGINE_FINANCIERO!J29,_ENGINE_FINANCIERO!J76,_ENGINE_FINANCIERO!J123,_ENGINE_FINANCIERO!J168),"") | K40: =IF(01_INPUTS!K17,CHOOSE(MATCH($B$2,$U$1:$U$5,0),_ENGINE_FINANCIERO!K168,_ENGINE_FINANCIERO!K29,_ENGINE_FINANCIERO!K76,_ENGINE_FINANCIERO!K123,_ENGINE_FINANCIERO!K168),"") | L40: =IF(01_INPUTS!L17,CHOOSE(MATCH($B$2,$U$1:$U$5,0),_ENGINE_FINANCIERO!L168,_ENGINE_FINANCIERO!L29,_ENGINE_FINANCIERO!L76,_ENGINE_FINANCIERO!L123,_ENGINE_FINANCIERO!L168),"") | M40: =IF(01_INPUTS!M17,CHOOSE(MATCH($B$2,$U$1:$U$5,0),_ENGINE_FINANCIERO!M168,_ENGINE_FINANCIERO!M29,_ENGINE_FINANCIERO!M76,_ENGINE_FINANCIERO!M123,_ENGINE_FINANCIERO!M168),"") | N40: =IF(01_INPUTS!N17,CHOOSE(MATCH($B$2,$U$1:$U$5,0),_ENGINE_FINANCIERO!N168,_ENGINE_FINANCIERO!N29,_ENGINE_FINANCIERO!N76,_ENGINE_FINANCIERO!N123,_ENGINE_FINANCIERO!N168),"") | O40: =IF(01_INPUTS!O17,CHOOSE(MATCH($B$2,$U$1:$U$5,0),_ENGINE_FINANCIERO!O168,_ENGINE_FINANCIERO!O29,_ENGINE_FINANCIERO!O76,_ENGINE_FINANCIERO!O123,_ENGINE_FINANCIERO!O168),"") | P40: =IF(01_INPUTS!P17,CHOOSE(MATCH($B$2,$U$1:$U$5,0),_ENGINE_FINANCIERO!P168,_ENGINE_FINANCIERO!P29,_ENGINE_FINANCIERO!P76,_ENGINE_FINANCIERO!P123,_ENGINE_FINANCIERO!P168),"") | ... S40: =IF(01_INPUTS!S17,CHOOSE(MATCH($B$2,$U$1:$U$5,0),_ENGINE_FINANCIERO!S168,_ENGINE_FINANCIERO!S29,_ENGINE_FINANCIERO!S76,_ENGINE_FINANCIERO!S123,_ENGINE_FINANCIERO!S168),"")
A41: EE.UU. | B41: USD | G41: =_ENGINE_FINANCIERO!G29 -> 7.5501874e+08 | H41: =_ENGINE_FINANCIERO!H29 -> 1.1714097e+09 | I41: =IF(01_INPUTS!I17,_ENGINE_FINANCIERO!I29,"") -> 2.1194105e+09 | J41: =IF(01_INPUTS!J17,_ENGINE_FINANCIERO!J29,"") | K41: =IF(01_INPUTS!K17,_ENGINE_FINANCIERO!K29,"") | L41: =IF(01_INPUTS!L17,_ENGINE_FINANCIERO!L29,"") | M41: =IF(01_INPUTS!M17,_ENGINE_FINANCIERO!M29,"") | N41: =IF(01_INPUTS!N17,_ENGINE_FINANCIERO!N29,"") | O41: =IF(01_INPUTS!O17,_ENGINE_FINANCIERO!O29,"") | P41: =IF(01_INPUTS!P17,_ENGINE_FINANCIERO!P29,"") | ... S41: =IF(01_INPUTS!S17,_ENGINE_FINANCIERO!S29,"")
A42: China | B42: USD | G42: =_ENGINE_FINANCIERO!G76 -> 3.8788074e+08 | H42: =_ENGINE_FINANCIERO!H76 -> 1.5488994e+09 | I42: =IF(01_INPUTS!I17,_ENGINE_FINANCIERO!I76,"") -> 2.6467772e+09 | J42: =IF(01_INPUTS!J17,_ENGINE_FINANCIERO!J76,"") | K42: =IF(01_INPUTS!K17,_ENGINE_FINANCIERO!K76,"") | L42: =IF(01_INPUTS!L17,_ENGINE_FINANCIERO!L76,"") | M42: =IF(01_INPUTS!M17,_ENGINE_FINANCIERO!M76,"") | N42: =IF(01_INPUTS!N17,_ENGINE_FINANCIERO!N76,"") | O42: =IF(01_INPUTS!O17,_ENGINE_FINANCIERO!O76,"") | P42: =IF(01_INPUTS!P17,_ENGINE_FINANCIERO!P76,"") | ... S42: =IF(01_INPUTS!S17,_ENGINE_FINANCIERO!S76,"")
A43: Europa | B43: USD | G43: =_ENGINE_FINANCIERO!G123 -> 5.9871851e+08 | H43: =_ENGINE_FINANCIERO!H123 -> 8.8902733e+08 | I43: =IF(01_INPUTS!I17,_ENGINE_FINANCIERO!I123,"") -> 8.8488786e+09 | J43: =IF(01_INPUTS!J17,_ENGINE_FINANCIERO!J123,"") | K43: =IF(01_INPUTS!K17,_ENGINE_FINANCIERO!K123,"") | L43: =IF(01_INPUTS!L17,_ENGINE_FINANCIERO!L123,"") | M43: =IF(01_INPUTS!M17,_ENGINE_FINANCIERO!M123,"") | N43: =IF(01_INPUTS!N17,_ENGINE_FINANCIERO!N123,"") | O43: =IF(01_INPUTS!O17,_ENGINE_FINANCIERO!O123,"") | P43: =IF(01_INPUTS!P17,_ENGINE_FINANCIERO!P123,"") | ... S43: =IF(01_INPUTS!S17,_ENGINE_FINANCIERO!S123,"")
A45: BALANCE
A46: Activo fijo (neto) | B46: USD | G46: =CHOOSE(MATCH($B$2,$U$1:$U$5,0),_ENGINE_FINANCIERO!G172,_ENGINE_FINANCIERO!G30,_ENGINE_FINANCIERO!G77,_ENGINE_FINANCIERO!G124,_ENGINE_FINANCIERO!G172) -> 10828204200 | H46: =CHOOSE(MATCH($B$2,$U$1:$U$5,0),_ENGINE_FINANCIERO!H172,_ENGINE_FINANCIERO!H30,_ENGINE_FINANCIERO!H77,_ENGINE_FINANCIERO!H124,_ENGINE_FINANCIERO!H172) -> 9763383780 | I46: =IF(01_INPUTS!I17,CHOOSE(MATCH($B$2,$U$1:$U$5,0),_ENGINE_FINANCIERO!I172,_ENGINE_FINANCIERO!I30,_ENGINE_FINANCIERO!I77,_ENGINE_FINANCIERO!I124,_ENGINE_FINANCIERO!I172),"") -> 8787045402 | J46: =IF(01_INPUTS!J17,CHOOSE(MATCH($B$2,$U$1:$U$5,0),_ENGINE_FINANCIERO!J172,_ENGINE_FINANCIERO!J30,_ENGINE_FINANCIERO!J77,_ENGINE_FINANCIERO!J124,_ENGINE_FINANCIERO!J172),"") | K46: =IF(01_INPUTS!K17,CHOOSE(MATCH($B$2,$U$1:$U$5,0),_ENGINE_FINANCIERO!K172,_ENGINE_FINANCIERO!K30,_ENGINE_FINANCIERO!K77,_ENGINE_FINANCIERO!K124,_ENGINE_FINANCIERO!K172),"") | L46: =IF(01_INPUTS!L17,CHOOSE(MATCH($B$2,$U$1:$U$5,0),_ENGINE_FINANCIERO!L172,_ENGINE_FINANCIERO!L30,_ENGINE_FINANCIERO!L77,_ENGINE_FINANCIERO!L124,_ENGINE_FINANCIERO!L172),"") | M46: =IF(01_INPUTS!M17,CHOOSE(MATCH($B$2,$U$1:$U$5,0),_ENGINE_FINANCIERO!M172,_ENGINE_FINANCIERO!M30,_ENGINE_FINANCIERO!M77,_ENGINE_FINANCIERO!M124,_ENGINE_FINANCIERO!M172),"") | N46: =IF(01_INPUTS!N17,CHOOSE(MATCH($B$2,$U$1:$U$5,0),_ENGINE_FINANCIERO!N172,_ENGINE_FINANCIERO!N30,_ENGINE_FINANCIERO!N77,_ENGINE_FINANCIERO!N124,_ENGINE_FINANCIERO!N172),"") | O46: =IF(01_INPUTS!O17,CHOOSE(MATCH($B$2,$U$1:$U$5,0),_ENGINE_FINANCIERO!O172,_ENGINE_FINANCIERO!O30,_ENGINE_FINANCIERO!O77,_ENGINE_FINANCIERO!O124,_ENGINE_FINANCIERO!O172),"") | P46: =IF(01_INPUTS!P17,CHOOSE(MATCH($B$2,$U$1:$U$5,0),_ENGINE_FINANCIERO!P172,_ENGINE_FINANCIERO!P30,_ENGINE_FINANCIERO!P77,_ENGINE_FINANCIERO!P124,_ENGINE_FINANCIERO!P172),"") | ... S46: =IF(01_INPUTS!S17,CHOOSE(MATCH($B$2,$U$1:$U$5,0),_ENGINE_FINANCIERO!S172,_ENGINE_FINANCIERO!S30,_ENGINE_FINANCIERO!S77,_ENGINE_FINANCIERO!S124,_ENGINE_FINANCIERO!S172),"")
A47: EE.UU. | B47: USD | G47: =_ENGINE_FINANCIERO!G30 -> 9045615600 | H47: =_ENGINE_FINANCIERO!H30 -> 8155054040 | I47: =IF(01_INPUTS!I17,_ENGINE_FINANCIERO!I30,"") -> 7339548636 | J47: =IF(01_INPUTS!J17,_ENGINE_FINANCIERO!J30,"") | K47: =IF(01_INPUTS!K17,_ENGINE_FINANCIERO!K30,"") | L47: =IF(01_INPUTS!L17,_ENGINE_FINANCIERO!L30,"") | M47: =IF(01_INPUTS!M17,_ENGINE_FINANCIERO!M30,"") | N47: =IF(01_INPUTS!N17,_ENGINE_FINANCIERO!N30,"") | O47: =IF(01_INPUTS!O17,_ENGINE_FINANCIERO!O30,"") | P47: =IF(01_INPUTS!P17,_ENGINE_FINANCIERO!P30,"") | ... S47: =IF(01_INPUTS!S17,_ENGINE_FINANCIERO!S30,"")
A48: China | B48: USD | G48: =_ENGINE_FINANCIERO!G77 -> 1782588600 | H48: =_ENGINE_FINANCIERO!H77 -> 1608329740 | I48: =IF(01_INPUTS!I17,_ENGINE_FINANCIERO!I77,"") -> 1447496766 | J48: =IF(01_INPUTS!J17,_ENGINE_FINANCIERO!J77,"") | K48: =IF(01_INPUTS!K17,_ENGINE_FINANCIERO!K77,"") | L48: =IF(01_INPUTS!L17,_ENGINE_FINANCIERO!L77,"") | M48: =IF(01_INPUTS!M17,_ENGINE_FINANCIERO!M77,"") | N48: =IF(01_INPUTS!N17,_ENGINE_FINANCIERO!N77,"") | O48: =IF(01_INPUTS!O17,_ENGINE_FINANCIERO!O77,"") | P48: =IF(01_INPUTS!P17,_ENGINE_FINANCIERO!P77,"") | ... S48: =IF(01_INPUTS!S17,_ENGINE_FINANCIERO!S77,"")
A49: Europa | B49: USD | G49: =_ENGINE_FINANCIERO!G124 -> 0 | H49: =_ENGINE_FINANCIERO!H124 -> 0 | I49: =IF(01_INPUTS!I17,_ENGINE_FINANCIERO!I124,"") -> 0 | J49: =IF(01_INPUTS!J17,_ENGINE_FINANCIERO!J124,"") | K49: =IF(01_INPUTS!K17,_ENGINE_FINANCIERO!K124,"") | L49: =IF(01_INPUTS!L17,_ENGINE_FINANCIERO!L124,"") | M49: =IF(01_INPUTS!M17,_ENGINE_FINANCIERO!M124,"") | N49: =IF(01_INPUTS!N17,_ENGINE_FINANCIERO!N124,"") | O49: =IF(01_INPUTS!O17,_ENGINE_FINANCIERO!O124,"") | P49: =IF(01_INPUTS!P17,_ENGINE_FINANCIERO!P124,"") | ... S49: =IF(01_INPUTS!S17,_ENGINE_FINANCIERO!S124,"")
A50: Inventario | B50: USD | G50: =CHOOSE(MATCH($B$2,$U$1:$U$5,0),_ENGINE_FINANCIERO!G173,_ENGINE_FINANCIERO!G31,_ENGINE_FINANCIERO!G78,_ENGINE_FINANCIERO!G125,_ENGINE_FINANCIERO!G173) -> 0 | H50: =CHOOSE(MATCH($B$2,$U$1:$U$5,0),_ENGINE_FINANCIERO!H173,_ENGINE_FINANCIERO!H31,_ENGINE_FINANCIERO!H78,_ENGINE_FINANCIERO!H125,_ENGINE_FINANCIERO!H173) -> 8.3132553e+09 | I50: =IF(01_INPUTS!I17,CHOOSE(MATCH($B$2,$U$1:$U$5,0),_ENGINE_FINANCIERO!I173,_ENGINE_FINANCIERO!I31,_ENGINE_FINANCIERO!I78,_ENGINE_FINANCIERO!I125,_ENGINE_FINANCIERO!I173),"") -> 6.7028222e+08 | J50: =IF(01_INPUTS!J17,CHOOSE(MATCH($B$2,$U$1:$U$5,0),_ENGINE_FINANCIERO!J173,_ENGINE_FINANCIERO!J31,_ENGINE_FINANCIERO!J78,_ENGINE_FINANCIERO!J125,_ENGINE_FINANCIERO!J173),"") | K50: =IF(01_INPUTS!K17,CHOOSE(MATCH($B$2,$U$1:$U$5,0),_ENGINE_FINANCIERO!K173,_ENGINE_FINANCIERO!K31,_ENGINE_FINANCIERO!K78,_ENGINE_FINANCIERO!K125,_ENGINE_FINANCIERO!K173),"") | L50: =IF(01_INPUTS!L17,CHOOSE(MATCH($B$2,$U$1:$U$5,0),_ENGINE_FINANCIERO!L173,_ENGINE_FINANCIERO!L31,_ENGINE_FINANCIERO!L78,_ENGINE_FINANCIERO!L125,_ENGINE_FINANCIERO!L173),"") | M50: =IF(01_INPUTS!M17,CHOOSE(MATCH($B$2,$U$1:$U$5,0),_ENGINE_FINANCIERO!M173,_ENGINE_FINANCIERO!M31,_ENGINE_FINANCIERO!M78,_ENGINE_FINANCIERO!M125,_ENGINE_FINANCIERO!M173),"") | N50: =IF(01_INPUTS!N17,CHOOSE(MATCH($B$2,$U$1:$U$5,0),_ENGINE_FINANCIERO!N173,_ENGINE_FINANCIERO!N31,_ENGINE_FINANCIERO!N78,_ENGINE_FINANCIERO!N125,_ENGINE_FINANCIERO!N173),"") | O50: =IF(01_INPUTS!O17,CHOOSE(MATCH($B$2,$U$1:$U$5,0),_ENGINE_FINANCIERO!O173,_ENGINE_FINANCIERO!O31,_ENGINE_FINANCIERO!O78,_ENGINE_FINANCIERO!O125,_ENGINE_FINANCIERO!O173),"") | P50: =IF(01_INPUTS!P17,CHOOSE(MATCH($B$2,$U$1:$U$5,0),_ENGINE_FINANCIERO!P173,_ENGINE_FINANCIERO!P31,_ENGINE_FINANCIERO!P78,_ENGINE_FINANCIERO!P125,_ENGINE_FINANCIERO!P173),"") | ... S50: =IF(01_INPUTS!S17,CHOOSE(MATCH($B$2,$U$1:$U$5,0),_ENGINE_FINANCIERO!S173,_ENGINE_FINANCIERO!S31,_ENGINE_FINANCIERO!S78,_ENGINE_FINANCIERO!S125,_ENGINE_FINANCIERO!S173),"")
A51: EE.UU. | B51: USD | G51: =_ENGINE_FINANCIERO!G31 -> 0 | H51: =_ENGINE_FINANCIERO!H31 -> 6.1747921e+09 | I51: =IF(01_INPUTS!I17,_ENGINE_FINANCIERO!I31,"") -> 5.3587427e+08 | J51: =IF(01_INPUTS!J17,_ENGINE_FINANCIERO!J31,"") | K51: =IF(01_INPUTS!K17,_ENGINE_FINANCIERO!K31,"") | L51: =IF(01_INPUTS!L17,_ENGINE_FINANCIERO!L31,"") | M51: =IF(01_INPUTS!M17,_ENGINE_FINANCIERO!M31,"") | N51: =IF(01_INPUTS!N17,_ENGINE_FINANCIERO!N31,"") | O51: =IF(01_INPUTS!O17,_ENGINE_FINANCIERO!O31,"") | P51: =IF(01_INPUTS!P17,_ENGINE_FINANCIERO!P31,"") | ... S51: =IF(01_INPUTS!S17,_ENGINE_FINANCIERO!S31,"")
A52: China | B52: USD | G52: =_ENGINE_FINANCIERO!G78 -> 0 | H52: =_ENGINE_FINANCIERO!H78 -> 2.1384632e+09 | I52: =IF(01_INPUTS!I17,_ENGINE_FINANCIERO!I78,"") -> 1.3440796e+08 | J52: =IF(01_INPUTS!J17,_ENGINE_FINANCIERO!J78,"") | K52: =IF(01_INPUTS!K17,_ENGINE_FINANCIERO!K78,"") | L52: =IF(01_INPUTS!L17,_ENGINE_FINANCIERO!L78,"") | M52: =IF(01_INPUTS!M17,_ENGINE_FINANCIERO!M78,"") | N52: =IF(01_INPUTS!N17,_ENGINE_FINANCIERO!N78,"") | O52: =IF(01_INPUTS!O17,_ENGINE_FINANCIERO!O78,"") | P52: =IF(01_INPUTS!P17,_ENGINE_FINANCIERO!P78,"") | ... S52: =IF(01_INPUTS!S17,_ENGINE_FINANCIERO!S78,"")
A53: Europa | B53: USD | G53: =_ENGINE_FINANCIERO!G125 -> 0 | H53: =_ENGINE_FINANCIERO!H125 -> 0 | I53: =IF(01_INPUTS!I17,_ENGINE_FINANCIERO!I125,"") -> 0 | J53: =IF(01_INPUTS!J17,_ENGINE_FINANCIERO!J125,"") | K53: =IF(01_INPUTS!K17,_ENGINE_FINANCIERO!K125,"") | L53: =IF(01_INPUTS!L17,_ENGINE_FINANCIERO!L125,"") | M53: =IF(01_INPUTS!M17,_ENGINE_FINANCIERO!M125,"") | N53: =IF(01_INPUTS!N17,_ENGINE_FINANCIERO!N125,"") | O53: =IF(01_INPUTS!O17,_ENGINE_FINANCIERO!O125,"") | P53: =IF(01_INPUTS!P17,_ENGINE_FINANCIERO!P125,"") | ... S53: =IF(01_INPUTS!S17,_ENGINE_FINANCIERO!S125,"")
A54: Cuentas por Cobrar | B54: USD | G54: =CHOOSE(MATCH($B$2,$U$1:$U$5,0),_ENGINE_FINANCIERO!G174,_ENGINE_FINANCIERO!G32,_ENGINE_FINANCIERO!G79,_ENGINE_FINANCIERO!G126,_ENGINE_FINANCIERO!G174) -> 1520326500 | H54: =CHOOSE(MATCH($B$2,$U$1:$U$5,0),_ENGINE_FINANCIERO!H174,_ENGINE_FINANCIERO!H32,_ENGINE_FINANCIERO!H79,_ENGINE_FINANCIERO!H126,_ENGINE_FINANCIERO!H174) -> 1.7894615e+09 | I54: =IF(01_INPUTS!I17,CHOOSE(MATCH($B$2,$U$1:$U$5,0),_ENGINE_FINANCIERO!I174,_ENGINE_FINANCIERO!I32,_ENGINE_FINANCIERO!I79,_ENGINE_FINANCIERO!I126,_ENGINE_FINANCIERO!I174),"") -> 3.1705139e+09 | J54: =IF(01_INPUTS!J17,CHOOSE(MATCH($B$2,$U$1:$U$5,0),_ENGINE_FINANCIERO!J174,_ENGINE_FINANCIERO!J32,_ENGINE_FINANCIERO!J79,_ENGINE_FINANCIERO!J126,_ENGINE_FINANCIERO!J174),"") | K54: =IF(01_INPUTS!K17,CHOOSE(MATCH($B$2,$U$1:$U$5,0),_ENGINE_FINANCIERO!K174,_ENGINE_FINANCIERO!K32,_ENGINE_FINANCIERO!K79,_ENGINE_FINANCIERO!K126,_ENGINE_FINANCIERO!K174),"") | L54: =IF(01_INPUTS!L17,CHOOSE(MATCH($B$2,$U$1:$U$5,0),_ENGINE_FINANCIERO!L174,_ENGINE_FINANCIERO!L32,_ENGINE_FINANCIERO!L79,_ENGINE_FINANCIERO!L126,_ENGINE_FINANCIERO!L174),"") | M54: =IF(01_INPUTS!M17,CHOOSE(MATCH($B$2,$U$1:$U$5,0),_ENGINE_FINANCIERO!M174,_ENGINE_FINANCIERO!M32,_ENGINE_FINANCIERO!M79,_ENGINE_FINANCIERO!M126,_ENGINE_FINANCIERO!M174),"") | N54: =IF(01_INPUTS!N17,CHOOSE(MATCH($B$2,$U$1:$U$5,0),_ENGINE_FINANCIERO!N174,_ENGINE_FINANCIERO!N32,_ENGINE_FINANCIERO!N79,_ENGINE_FINANCIERO!N126,_ENGINE_FINANCIERO!N174),"") | O54: =IF(01_INPUTS!O17,CHOOSE(MATCH($B$2,$U$1:$U$5,0),_ENGINE_FINANCIERO!O174,_ENGINE_FINANCIERO!O32,_ENGINE_FINANCIERO!O79,_ENGINE_FINANCIERO!O126,_ENGINE_FINANCIERO!O174),"") | P54: =IF(01_INPUTS!P17,CHOOSE(MATCH($B$2,$U$1:$U$5,0),_ENGINE_FINANCIERO!P174,_ENGINE_FINANCIERO!P32,_ENGINE_FINANCIERO!P79,_ENGINE_FINANCIERO!P126,_ENGINE_FINANCIERO!P174),"") | ... S54: =IF(01_INPUTS!S17,CHOOSE(MATCH($B$2,$U$1:$U$5,0),_ENGINE_FINANCIERO!S174,_ENGINE_FINANCIERO!S32,_ENGINE_FINANCIERO!S79,_ENGINE_FINANCIERO!S126,_ENGINE_FINANCIERO!S174),"")
A55: EE.UU. | B55: USD | G55: =_ENGINE_FINANCIERO!G32 -> 516381250 | H55: =_ENGINE_FINANCIERO!H32 -> 7.565281e+08 | I55: =IF(01_INPUTS!I17,_ENGINE_FINANCIERO!I32,"") -> 9.1460691e+08 | J55: =IF(01_INPUTS!J17,_ENGINE_FINANCIERO!J32,"") | K55: =IF(01_INPUTS!K17,_ENGINE_FINANCIERO!K32,"") | L55: =IF(01_INPUTS!L17,_ENGINE_FINANCIERO!L32,"") | M55: =IF(01_INPUTS!M17,_ENGINE_FINANCIERO!M32,"") | N55: =IF(01_INPUTS!N17,_ENGINE_FINANCIERO!N32,"") | O55: =IF(01_INPUTS!O17,_ENGINE_FINANCIERO!O32,"") | P55: =IF(01_INPUTS!P17,_ENGINE_FINANCIERO!P32,"") | ... S55: =IF(01_INPUTS!S17,_ENGINE_FINANCIERO!S32,"")
A56: China | B56: USD | G56: =_ENGINE_FINANCIERO!G79 -> 346981250 | H56: =_ENGINE_FINANCIERO!H79 -> 5.0958602e+08 | I56: =IF(01_INPUTS!I17,_ENGINE_FINANCIERO!I79,"") -> 1.0367948e+09 | J56: =IF(01_INPUTS!J17,_ENGINE_FINANCIERO!J79,"") | K56: =IF(01_INPUTS!K17,_ENGINE_FINANCIERO!K79,"") | L56: =IF(01_INPUTS!L17,_ENGINE_FINANCIERO!L79,"") | M56: =IF(01_INPUTS!M17,_ENGINE_FINANCIERO!M79,"") | N56: =IF(01_INPUTS!N17,_ENGINE_FINANCIERO!N79,"") | O56: =IF(01_INPUTS!O17,_ENGINE_FINANCIERO!O79,"") | P56: =IF(01_INPUTS!P17,_ENGINE_FINANCIERO!P79,"") | ... S56: =IF(01_INPUTS!S17,_ENGINE_FINANCIERO!S79,"")
A57: Europa | B57: USD | G57: =_ENGINE_FINANCIERO!G126 -> 656964000 | H57: =_ENGINE_FINANCIERO!H126 -> 5.2334734e+08 | I57: =IF(01_INPUTS!I17,_ENGINE_FINANCIERO!I126,"") -> 1.2191121e+09 | J57: =IF(01_INPUTS!J17,_ENGINE_FINANCIERO!J126,"") | K57: =IF(01_INPUTS!K17,_ENGINE_FINANCIERO!K126,"") | L57: =IF(01_INPUTS!L17,_ENGINE_FINANCIERO!L126,"") | M57: =IF(01_INPUTS!M17,_ENGINE_FINANCIERO!M126,"") | N57: =IF(01_INPUTS!N17,_ENGINE_FINANCIERO!N126,"") | O57: =IF(01_INPUTS!O17,_ENGINE_FINANCIERO!O126,"") | P57: =IF(01_INPUTS!P17,_ENGINE_FINANCIERO!P126,"") | ... S57: =IF(01_INPUTS!S17,_ENGINE_FINANCIERO!S126,"")
A58: Efectivo y equivalentes | B58: USD | G58: =CHOOSE(MATCH($B$2,$U$1:$U$5,0),_ENGINE_FINANCIERO!G175,_ENGINE_FINANCIERO!G33,_ENGINE_FINANCIERO!G80,_ENGINE_FINANCIERO!G127,_ENGINE_FINANCIERO!G175) -> 1.0817319e+10 | H58: =CHOOSE(MATCH($B$2,$U$1:$U$5,0),_ENGINE_FINANCIERO!H175,_ENGINE_FINANCIERO!H33,_ENGINE_FINANCIERO!H80,_ENGINE_FINANCIERO!H127,_ENGINE_FINANCIERO!H175) -> 5.0785888e+09 | I58: =IF(01_INPUTS!I17,CHOOSE(MATCH($B$2,$U$1:$U$5,0),_ENGINE_FINANCIERO!I175,_ENGINE_FINANCIERO!I33,_ENGINE_FINANCIERO!I80,_ENGINE_FINANCIERO!I127,_ENGINE_FINANCIERO!I175),"") -> 2.3640855e+10 | J58: =IF(01_INPUTS!J17,CHOOSE(MATCH($B$2,$U$1:$U$5,0),_ENGINE_FINANCIERO!J175,_ENGINE_FINANCIERO!J33,_ENGINE_FINANCIERO!J80,_ENGINE_FINANCIERO!J127,_ENGINE_FINANCIERO!J175),"") | K58: =IF(01_INPUTS!K17,CHOOSE(MATCH($B$2,$U$1:$U$5,0),_ENGINE_FINANCIERO!K175,_ENGINE_FINANCIERO!K33,_ENGINE_FINANCIERO!K80,_ENGINE_FINANCIERO!K127,_ENGINE_FINANCIERO!K175),"") | L58: =IF(01_INPUTS!L17,CHOOSE(MATCH($B$2,$U$1:$U$5,0),_ENGINE_FINANCIERO!L175,_ENGINE_FINANCIERO!L33,_ENGINE_FINANCIERO!L80,_ENGINE_FINANCIERO!L127,_ENGINE_FINANCIERO!L175),"") | M58: =IF(01_INPUTS!M17,CHOOSE(MATCH($B$2,$U$1:$U$5,0),_ENGINE_FINANCIERO!M175,_ENGINE_FINANCIERO!M33,_ENGINE_FINANCIERO!M80,_ENGINE_FINANCIERO!M127,_ENGINE_FINANCIERO!M175),"") | N58: =IF(01_INPUTS!N17,CHOOSE(MATCH($B$2,$U$1:$U$5,0),_ENGINE_FINANCIERO!N175,_ENGINE_FINANCIERO!N33,_ENGINE_FINANCIERO!N80,_ENGINE_FINANCIERO!N127,_ENGINE_FINANCIERO!N175),"") | O58: =IF(01_INPUTS!O17,CHOOSE(MATCH($B$2,$U$1:$U$5,0),_ENGINE_FINANCIERO!O175,_ENGINE_FINANCIERO!O33,_ENGINE_FINANCIERO!O80,_ENGINE_FINANCIERO!O127,_ENGINE_FINANCIERO!O175),"") | P58: =IF(01_INPUTS!P17,CHOOSE(MATCH($B$2,$U$1:$U$5,0),_ENGINE_FINANCIERO!P175,_ENGINE_FINANCIERO!P33,_ENGINE_FINANCIERO!P80,_ENGINE_FINANCIERO!P127,_ENGINE_FINANCIERO!P175),"") | ... S58: =IF(01_INPUTS!S17,CHOOSE(MATCH($B$2,$U$1:$U$5,0),_ENGINE_FINANCIERO!S175,_ENGINE_FINANCIERO!S33,_ENGINE_FINANCIERO!S80,_ENGINE_FINANCIERO!S127,_ENGINE_FINANCIERO!S175),"")
A59: EE.UU. | B59: USD | G59: =_ENGINE_FINANCIERO!G33 -> 9.2740828e+09 | H59: =_ENGINE_FINANCIERO!H33 -> 1.090286e+09 | I59: =IF(01_INPUTS!I17,_ENGINE_FINANCIERO!I33,"") -> 6.669795e+09 | J59: =IF(01_INPUTS!J17,_ENGINE_FINANCIERO!J33,"") | K59: =IF(01_INPUTS!K17,_ENGINE_FINANCIERO!K33,"") | L59: =IF(01_INPUTS!L17,_ENGINE_FINANCIERO!L33,"") | M59: =IF(01_INPUTS!M17,_ENGINE_FINANCIERO!M33,"") | N59: =IF(01_INPUTS!N17,_ENGINE_FINANCIERO!N33,"") | O59: =IF(01_INPUTS!O17,_ENGINE_FINANCIERO!O33,"") | P59: =IF(01_INPUTS!P17,_ENGINE_FINANCIERO!P33,"") | ... S59: =IF(01_INPUTS!S17,_ENGINE_FINANCIERO!S33,"")
A60: China | B60: USD | G60: =_ENGINE_FINANCIERO!G80 -> 3.6503243e+08 | H60: =_ENGINE_FINANCIERO!H80 -> 2.2795729e+09 | I60: =IF(01_INPUTS!I17,_ENGINE_FINANCIERO!I80,"") -> 7.0484868e+09 | J60: =IF(01_INPUTS!J17,_ENGINE_FINANCIERO!J80,"") | K60: =IF(01_INPUTS!K17,_ENGINE_FINANCIERO!K80,"") | L60: =IF(01_INPUTS!L17,_ENGINE_FINANCIERO!L80,"") | M60: =IF(01_INPUTS!M17,_ENGINE_FINANCIERO!M80,"") | N60: =IF(01_INPUTS!N17,_ENGINE_FINANCIERO!N80,"") | O60: =IF(01_INPUTS!O17,_ENGINE_FINANCIERO!O80,"") | P60: =IF(01_INPUTS!P17,_ENGINE_FINANCIERO!P80,"") | ... S60: =IF(01_INPUTS!S17,_ENGINE_FINANCIERO!S80,"")
A61: Europa | B61: USD | G61: =_ENGINE_FINANCIERO!G127 -> 1.1782038e+09 | H61: =_ENGINE_FINANCIERO!H127 -> 1.7087299e+09 | I61: =IF(01_INPUTS!I17,_ENGINE_FINANCIERO!I127,"") -> 9.9225733e+09 | J61: =IF(01_INPUTS!J17,_ENGINE_FINANCIERO!J127,"") | K61: =IF(01_INPUTS!K17,_ENGINE_FINANCIERO!K127,"") | L61: =IF(01_INPUTS!L17,_ENGINE_FINANCIERO!L127,"") | M61: =IF(01_INPUTS!M17,_ENGINE_FINANCIERO!M127,"") | N61: =IF(01_INPUTS!N17,_ENGINE_FINANCIERO!N127,"") | O61: =IF(01_INPUTS!O17,_ENGINE_FINANCIERO!O127,"") | P61: =IF(01_INPUTS!P17,_ENGINE_FINANCIERO!P127,"") | ... S61: =IF(01_INPUTS!S17,_ENGINE_FINANCIERO!S127,"")
A62: Activos Totales | B62: USD | G62: =CHOOSE(MATCH($B$2,$U$1:$U$5,0),_ENGINE_FINANCIERO!G176,_ENGINE_FINANCIERO!G34,_ENGINE_FINANCIERO!G81,_ENGINE_FINANCIERO!G128,_ENGINE_FINANCIERO!G176) -> 2.316585e+10 | H62: =CHOOSE(MATCH($B$2,$U$1:$U$5,0),_ENGINE_FINANCIERO!H176,_ENGINE_FINANCIERO!H34,_ENGINE_FINANCIERO!H81,_ENGINE_FINANCIERO!H128,_ENGINE_FINANCIERO!H176) -> 2.4944689e+10 | I62: =IF(01_INPUTS!I17,CHOOSE(MATCH($B$2,$U$1:$U$5,0),_ENGINE_FINANCIERO!I176,_ENGINE_FINANCIERO!I34,_ENGINE_FINANCIERO!I81,_ENGINE_FINANCIERO!I128,_ENGINE_FINANCIERO!I176),"") -> 3.6268697e+10 | J62: =IF(01_INPUTS!J17,CHOOSE(MATCH($B$2,$U$1:$U$5,0),_ENGINE_FINANCIERO!J176,_ENGINE_FINANCIERO!J34,_ENGINE_FINANCIERO!J81,_ENGINE_FINANCIERO!J128,_ENGINE_FINANCIERO!J176),"") | K62: =IF(01_INPUTS!K17,CHOOSE(MATCH($B$2,$U$1:$U$5,0),_ENGINE_FINANCIERO!K176,_ENGINE_FINANCIERO!K34,_ENGINE_FINANCIERO!K81,_ENGINE_FINANCIERO!K128,_ENGINE_FINANCIERO!K176),"") | L62: =IF(01_INPUTS!L17,CHOOSE(MATCH($B$2,$U$1:$U$5,0),_ENGINE_FINANCIERO!L176,_ENGINE_FINANCIERO!L34,_ENGINE_FINANCIERO!L81,_ENGINE_FINANCIERO!L128,_ENGINE_FINANCIERO!L176),"") | M62: =IF(01_INPUTS!M17,CHOOSE(MATCH($B$2,$U$1:$U$5,0),_ENGINE_FINANCIERO!M176,_ENGINE_FINANCIERO!M34,_ENGINE_FINANCIERO!M81,_ENGINE_FINANCIERO!M128,_ENGINE_FINANCIERO!M176),"") | N62: =IF(01_INPUTS!N17,CHOOSE(MATCH($B$2,$U$1:$U$5,0),_ENGINE_FINANCIERO!N176,_ENGINE_FINANCIERO!N34,_ENGINE_FINANCIERO!N81,_ENGINE_FINANCIERO!N128,_ENGINE_FINANCIERO!N176),"") | O62: =IF(01_INPUTS!O17,CHOOSE(MATCH($B$2,$U$1:$U$5,0),_ENGINE_FINANCIERO!O176,_ENGINE_FINANCIERO!O34,_ENGINE_FINANCIERO!O81,_ENGINE_FINANCIERO!O128,_ENGINE_FINANCIERO!O176),"") | P62: =IF(01_INPUTS!P17,CHOOSE(MATCH($B$2,$U$1:$U$5,0),_ENGINE_FINANCIERO!P176,_ENGINE_FINANCIERO!P34,_ENGINE_FINANCIERO!P81,_ENGINE_FINANCIERO!P128,_ENGINE_FINANCIERO!P176),"") | ... S62: =IF(01_INPUTS!S17,CHOOSE(MATCH($B$2,$U$1:$U$5,0),_ENGINE_FINANCIERO!S176,_ENGINE_FINANCIERO!S34,_ENGINE_FINANCIERO!S81,_ENGINE_FINANCIERO!S128,_ENGINE_FINANCIERO!S176),"")
A63: EE.UU. | B63: USD | G63: =_ENGINE_FINANCIERO!G34 -> 1.883608e+10 | H63: =_ENGINE_FINANCIERO!H34 -> 1.617666e+10 | I63: =IF(01_INPUTS!I17,_ENGINE_FINANCIERO!I34,"") -> 1.5459825e+10 | J63: =IF(01_INPUTS!J17,_ENGINE_FINANCIERO!J34,"") | K63: =IF(01_INPUTS!K17,_ENGINE_FINANCIERO!K34,"") | L63: =IF(01_INPUTS!L17,_ENGINE_FINANCIERO!L34,"") | M63: =IF(01_INPUTS!M17,_ENGINE_FINANCIERO!M34,"") | N63: =IF(01_INPUTS!N17,_ENGINE_FINANCIERO!N34,"") | O63: =IF(01_INPUTS!O17,_ENGINE_FINANCIERO!O34,"") | P63: =IF(01_INPUTS!P17,_ENGINE_FINANCIERO!P34,"") | ... S63: =IF(01_INPUTS!S17,_ENGINE_FINANCIERO!S34,"")
A64: China | B64: USD | G64: =_ENGINE_FINANCIERO!G81 -> 2.4946023e+09 | H64: =_ENGINE_FINANCIERO!H81 -> 6.5359519e+09 | I64: =IF(01_INPUTS!I17,_ENGINE_FINANCIERO!I81,"") -> 9.6671863e+09 | J64: =IF(01_INPUTS!J17,_ENGINE_FINANCIERO!J81,"") | K64: =IF(01_INPUTS!K17,_ENGINE_FINANCIERO!K81,"") | L64: =IF(01_INPUTS!L17,_ENGINE_FINANCIERO!L81,"") | M64: =IF(01_INPUTS!M17,_ENGINE_FINANCIERO!M81,"") | N64: =IF(01_INPUTS!N17,_ENGINE_FINANCIERO!N81,"") | O64: =IF(01_INPUTS!O17,_ENGINE_FINANCIERO!O81,"") | P64: =IF(01_INPUTS!P17,_ENGINE_FINANCIERO!P81,"") | ... S64: =IF(01_INPUTS!S17,_ENGINE_FINANCIERO!S81,"")
A65: Europa | B65: USD | G65: =_ENGINE_FINANCIERO!G128 -> 1.8351678e+09 | H65: =_ENGINE_FINANCIERO!H128 -> 2.2320772e+09 | I65: =IF(01_INPUTS!I17,_ENGINE_FINANCIERO!I128,"") -> 1.1141685e+10 | J65: =IF(01_INPUTS!J17,_ENGINE_FINANCIERO!J128,"") | K65: =IF(01_INPUTS!K17,_ENGINE_FINANCIERO!K128,"") | L65: =IF(01_INPUTS!L17,_ENGINE_FINANCIERO!L128,"") | M65: =IF(01_INPUTS!M17,_ENGINE_FINANCIERO!M128,"") | N65: =IF(01_INPUTS!N17,_ENGINE_FINANCIERO!N128,"") | O65: =IF(01_INPUTS!O17,_ENGINE_FINANCIERO!O128,"") | P65: =IF(01_INPUTS!P17,_ENGINE_FINANCIERO!P128,"") | ... S65: =IF(01_INPUTS!S17,_ENGINE_FINANCIERO!S128,"")
A66: Deudas a largo plazo | B66: USD | G66: =CHOOSE(MATCH($B$2,$U$1:$U$5,0),_ENGINE_FINANCIERO!G182,_ENGINE_FINANCIERO!G39,_ENGINE_FINANCIERO!G86,_ENGINE_FINANCIERO!G133,_ENGINE_FINANCIERO!G182) -> 11900000000 | H66: =CHOOSE(MATCH($B$2,$U$1:$U$5,0),_ENGINE_FINANCIERO!H182,_ENGINE_FINANCIERO!H39,_ENGINE_FINANCIERO!H86,_ENGINE_FINANCIERO!H133,_ENGINE_FINANCIERO!H182) -> 11900000000 | I66: =IF(01_INPUTS!I17,CHOOSE(MATCH($B$2,$U$1:$U$5,0),_ENGINE_FINANCIERO!I182,_ENGINE_FINANCIERO!I39,_ENGINE_FINANCIERO!I86,_ENGINE_FINANCIERO!I133,_ENGINE_FINANCIERO!I182),"") -> 11900000000 | J66: =IF(01_INPUTS!J17,CHOOSE(MATCH($B$2,$U$1:$U$5,0),_ENGINE_FINANCIERO!J182,_ENGINE_FINANCIERO!J39,_ENGINE_FINANCIERO!J86,_ENGINE_FINANCIERO!J133,_ENGINE_FINANCIERO!J182),"") | K66: =IF(01_INPUTS!K17,CHOOSE(MATCH($B$2,$U$1:$U$5,0),_ENGINE_FINANCIERO!K182,_ENGINE_FINANCIERO!K39,_ENGINE_FINANCIERO!K86,_ENGINE_FINANCIERO!K133,_ENGINE_FINANCIERO!K182),"") | L66: =IF(01_INPUTS!L17,CHOOSE(MATCH($B$2,$U$1:$U$5,0),_ENGINE_FINANCIERO!L182,_ENGINE_FINANCIERO!L39,_ENGINE_FINANCIERO!L86,_ENGINE_FINANCIERO!L133,_ENGINE_FINANCIERO!L182),"") | M66: =IF(01_INPUTS!M17,CHOOSE(MATCH($B$2,$U$1:$U$5,0),_ENGINE_FINANCIERO!M182,_ENGINE_FINANCIERO!M39,_ENGINE_FINANCIERO!M86,_ENGINE_FINANCIERO!M133,_ENGINE_FINANCIERO!M182),"") | N66: =IF(01_INPUTS!N17,CHOOSE(MATCH($B$2,$U$1:$U$5,0),_ENGINE_FINANCIERO!N182,_ENGINE_FINANCIERO!N39,_ENGINE_FINANCIERO!N86,_ENGINE_FINANCIERO!N133,_ENGINE_FINANCIERO!N182),"") | O66: =IF(01_INPUTS!O17,CHOOSE(MATCH($B$2,$U$1:$U$5,0),_ENGINE_FINANCIERO!O182,_ENGINE_FINANCIERO!O39,_ENGINE_FINANCIERO!O86,_ENGINE_FINANCIERO!O133,_ENGINE_FINANCIERO!O182),"") | P66: =IF(01_INPUTS!P17,CHOOSE(MATCH($B$2,$U$1:$U$5,0),_ENGINE_FINANCIERO!P182,_ENGINE_FINANCIERO!P39,_ENGINE_FINANCIERO!P86,_ENGINE_FINANCIERO!P133,_ENGINE_FINANCIERO!P182),"") | ... S66: =IF(01_INPUTS!S17,CHOOSE(MATCH($B$2,$U$1:$U$5,0),_ENGINE_FINANCIERO!S182,_ENGINE_FINANCIERO!S39,_ENGINE_FINANCIERO!S86,_ENGINE_FINANCIERO!S133,_ENGINE_FINANCIERO!S182),"")
A67: EE.UU. | B67: USD | G67: =_ENGINE_FINANCIERO!G39 -> 11900000000 | H67: =_ENGINE_FINANCIERO!H39 -> 11900000000 | I67: =IF(01_INPUTS!I17,_ENGINE_FINANCIERO!I39,"") -> 11900000000 | J67: =IF(01_INPUTS!J17,_ENGINE_FINANCIERO!J39,"") | K67: =IF(01_INPUTS!K17,_ENGINE_FINANCIERO!K39,"") | L67: =IF(01_INPUTS!L17,_ENGINE_FINANCIERO!L39,"") | M67: =IF(01_INPUTS!M17,_ENGINE_FINANCIERO!M39,"") | N67: =IF(01_INPUTS!N17,_ENGINE_FINANCIERO!N39,"") | O67: =IF(01_INPUTS!O17,_ENGINE_FINANCIERO!O39,"") | P67: =IF(01_INPUTS!P17,_ENGINE_FINANCIERO!P39,"") | ... S67: =IF(01_INPUTS!S17,_ENGINE_FINANCIERO!S39,"")
A68: China | B68: USD | G68: =_ENGINE_FINANCIERO!G86 -> 0 | H68: =_ENGINE_FINANCIERO!H86 -> 0 | I68: =IF(01_INPUTS!I17,_ENGINE_FINANCIERO!I86,"") -> 0 | J68: =IF(01_INPUTS!J17,_ENGINE_FINANCIERO!J86,"") | K68: =IF(01_INPUTS!K17,_ENGINE_FINANCIERO!K86,"") | L68: =IF(01_INPUTS!L17,_ENGINE_FINANCIERO!L86,"") | M68: =IF(01_INPUTS!M17,_ENGINE_FINANCIERO!M86,"") | N68: =IF(01_INPUTS!N17,_ENGINE_FINANCIERO!N86,"") | O68: =IF(01_INPUTS!O17,_ENGINE_FINANCIERO!O86,"") | P68: =IF(01_INPUTS!P17,_ENGINE_FINANCIERO!P86,"") | ... S68: =IF(01_INPUTS!S17,_ENGINE_FINANCIERO!S86,"")
A69: Europa | B69: USD | G69: =_ENGINE_FINANCIERO!G133 -> 0 | H69: =_ENGINE_FINANCIERO!H133 -> 0 | I69: =IF(01_INPUTS!I17,_ENGINE_FINANCIERO!I133,"") -> 0 | J69: =IF(01_INPUTS!J17,_ENGINE_FINANCIERO!J133,"") | K69: =IF(01_INPUTS!K17,_ENGINE_FINANCIERO!K133,"") | L69: =IF(01_INPUTS!L17,_ENGINE_FINANCIERO!L133,"") | M69: =IF(01_INPUTS!M17,_ENGINE_FINANCIERO!M133,"") | N69: =IF(01_INPUTS!N17,_ENGINE_FINANCIERO!N133,"") | O69: =IF(01_INPUTS!O17,_ENGINE_FINANCIERO!O133,"") | P69: =IF(01_INPUTS!P17,_ENGINE_FINANCIERO!P133,"") | ... S69: =IF(01_INPUTS!S17,_ENGINE_FINANCIERO!S133,"")
A70: Deudas a corto plazo (automática) | B70: USD | G70: =CHOOSE(MATCH($B$2,$U$1:$U$5,0),_ENGINE_FINANCIERO!G183,_ENGINE_FINANCIERO!G40,_ENGINE_FINANCIERO!G87,_ENGINE_FINANCIERO!G134,_ENGINE_FINANCIERO!G183) -> 0 | H70: =CHOOSE(MATCH($B$2,$U$1:$U$5,0),_ENGINE_FINANCIERO!H183,_ENGINE_FINANCIERO!H40,_ENGINE_FINANCIERO!H87,_ENGINE_FINANCIERO!H134,_ENGINE_FINANCIERO!H183) -> 0 | I70: =IF(01_INPUTS!I17,CHOOSE(MATCH($B$2,$U$1:$U$5,0),_ENGINE_FINANCIERO!I183,_ENGINE_FINANCIERO!I40,_ENGINE_FINANCIERO!I87,_ENGINE_FINANCIERO!I134,_ENGINE_FINANCIERO!I183),"") -> 0 | J70: =IF(01_INPUTS!J17,CHOOSE(MATCH($B$2,$U$1:$U$5,0),_ENGINE_FINANCIERO!J183,_ENGINE_FINANCIERO!J40,_ENGINE_FINANCIERO!J87,_ENGINE_FINANCIERO!J134,_ENGINE_FINANCIERO!J183),"") | K70: =IF(01_INPUTS!K17,CHOOSE(MATCH($B$2,$U$1:$U$5,0),_ENGINE_FINANCIERO!K183,_ENGINE_FINANCIERO!K40,_ENGINE_FINANCIERO!K87,_ENGINE_FINANCIERO!K134,_ENGINE_FINANCIERO!K183),"") | L70: =IF(01_INPUTS!L17,CHOOSE(MATCH($B$2,$U$1:$U$5,0),_ENGINE_FINANCIERO!L183,_ENGINE_FINANCIERO!L40,_ENGINE_FINANCIERO!L87,_ENGINE_FINANCIERO!L134,_ENGINE_FINANCIERO!L183),"") | M70: =IF(01_INPUTS!M17,CHOOSE(MATCH($B$2,$U$1:$U$5,0),_ENGINE_FINANCIERO!M183,_ENGINE_FINANCIERO!M40,_ENGINE_FINANCIERO!M87,_ENGINE_FINANCIERO!M134,_ENGINE_FINANCIERO!M183),"") | N70: =IF(01_INPUTS!N17,CHOOSE(MATCH($B$2,$U$1:$U$5,0),_ENGINE_FINANCIERO!N183,_ENGINE_FINANCIERO!N40,_ENGINE_FINANCIERO!N87,_ENGINE_FINANCIERO!N134,_ENGINE_FINANCIERO!N183),"") | O70: =IF(01_INPUTS!O17,CHOOSE(MATCH($B$2,$U$1:$U$5,0),_ENGINE_FINANCIERO!O183,_ENGINE_FINANCIERO!O40,_ENGINE_FINANCIERO!O87,_ENGINE_FINANCIERO!O134,_ENGINE_FINANCIERO!O183),"") | P70: =IF(01_INPUTS!P17,CHOOSE(MATCH($B$2,$U$1:$U$5,0),_ENGINE_FINANCIERO!P183,_ENGINE_FINANCIERO!P40,_ENGINE_FINANCIERO!P87,_ENGINE_FINANCIERO!P134,_ENGINE_FINANCIERO!P183),"") | ... S70: =IF(01_INPUTS!S17,CHOOSE(MATCH($B$2,$U$1:$U$5,0),_ENGINE_FINANCIERO!S183,_ENGINE_FINANCIERO!S40,_ENGINE_FINANCIERO!S87,_ENGINE_FINANCIERO!S134,_ENGINE_FINANCIERO!S183),"")
A71: EE.UU. | B71: USD | G71: =_ENGINE_FINANCIERO!G40 -> 0 | H71: =_ENGINE_FINANCIERO!H40 -> 0 | I71: =IF(01_INPUTS!I17,_ENGINE_FINANCIERO!I40,"") -> 0 | J71: =IF(01_INPUTS!J17,_ENGINE_FINANCIERO!J40,"") | K71: =IF(01_INPUTS!K17,_ENGINE_FINANCIERO!K40,"") | L71: =IF(01_INPUTS!L17,_ENGINE_FINANCIERO!L40,"") | M71: =IF(01_INPUTS!M17,_ENGINE_FINANCIERO!M40,"") | N71: =IF(01_INPUTS!N17,_ENGINE_FINANCIERO!N40,"") | O71: =IF(01_INPUTS!O17,_ENGINE_FINANCIERO!O40,"") | P71: =IF(01_INPUTS!P17,_ENGINE_FINANCIERO!P40,"") | ... S71: =IF(01_INPUTS!S17,_ENGINE_FINANCIERO!S40,"")
A72: China | B72: USD | G72: =_ENGINE_FINANCIERO!G87 -> 0 | H72: =_ENGINE_FINANCIERO!H87 -> 0 | I72: =IF(01_INPUTS!I17,_ENGINE_FINANCIERO!I87,"") -> 0 | J72: =IF(01_INPUTS!J17,_ENGINE_FINANCIERO!J87,"") | K72: =IF(01_INPUTS!K17,_ENGINE_FINANCIERO!K87,"") | L72: =IF(01_INPUTS!L17,_ENGINE_FINANCIERO!L87,"") | M72: =IF(01_INPUTS!M17,_ENGINE_FINANCIERO!M87,"") | N72: =IF(01_INPUTS!N17,_ENGINE_FINANCIERO!N87,"") | O72: =IF(01_INPUTS!O17,_ENGINE_FINANCIERO!O87,"") | P72: =IF(01_INPUTS!P17,_ENGINE_FINANCIERO!P87,"") | ... S72: =IF(01_INPUTS!S17,_ENGINE_FINANCIERO!S87,"")
A73: Europa | B73: USD | G73: =_ENGINE_FINANCIERO!G134 -> 0 | H73: =_ENGINE_FINANCIERO!H134 -> 0 | I73: =IF(01_INPUTS!I17,_ENGINE_FINANCIERO!I134,"") -> 0 | J73: =IF(01_INPUTS!J17,_ENGINE_FINANCIERO!J134,"") | K73: =IF(01_INPUTS!K17,_ENGINE_FINANCIERO!K134,"") | L73: =IF(01_INPUTS!L17,_ENGINE_FINANCIERO!L134,"") | M73: =IF(01_INPUTS!M17,_ENGINE_FINANCIERO!M134,"") | N73: =IF(01_INPUTS!N17,_ENGINE_FINANCIERO!N134,"") | O73: =IF(01_INPUTS!O17,_ENGINE_FINANCIERO!O134,"") | P73: =IF(01_INPUTS!P17,_ENGINE_FINANCIERO!P134,"") | ... S73: =IF(01_INPUTS!S17,_ENGINE_FINANCIERO!S134,"")
A74: Cuentas por Pagar | B74: USD | G74: =CHOOSE(MATCH($B$2,$U$1:$U$5,0),_ENGINE_FINANCIERO!G184,_ENGINE_FINANCIERO!G42,_ENGINE_FINANCIERO!G89,_ENGINE_FINANCIERO!G136,_ENGINE_FINANCIERO!G184) -> 1.2622878e+09 | H74: =CHOOSE(MATCH($B$2,$U$1:$U$5,0),_ENGINE_FINANCIERO!H184,_ENGINE_FINANCIERO!H42,_ENGINE_FINANCIERO!H89,_ENGINE_FINANCIERO!H136,_ENGINE_FINANCIERO!H184) -> 1.4317909e+09 | I74: =IF(01_INPUTS!I17,CHOOSE(MATCH($B$2,$U$1:$U$5,0),_ENGINE_FINANCIERO!I184,_ENGINE_FINANCIERO!I42,_ENGINE_FINANCIERO!I89,_ENGINE_FINANCIERO!I136,_ENGINE_FINANCIERO!I184),"") -> 2.1407319e+09 | J74: =IF(01_INPUTS!J17,CHOOSE(MATCH($B$2,$U$1:$U$5,0),_ENGINE_FINANCIERO!J184,_ENGINE_FINANCIERO!J42,_ENGINE_FINANCIERO!J89,_ENGINE_FINANCIERO!J136,_ENGINE_FINANCIERO!J184),"") | K74: =IF(01_INPUTS!K17,CHOOSE(MATCH($B$2,$U$1:$U$5,0),_ENGINE_FINANCIERO!K184,_ENGINE_FINANCIERO!K42,_ENGINE_FINANCIERO!K89,_ENGINE_FINANCIERO!K136,_ENGINE_FINANCIERO!K184),"") | L74: =IF(01_INPUTS!L17,CHOOSE(MATCH($B$2,$U$1:$U$5,0),_ENGINE_FINANCIERO!L184,_ENGINE_FINANCIERO!L42,_ENGINE_FINANCIERO!L89,_ENGINE_FINANCIERO!L136,_ENGINE_FINANCIERO!L184),"") | M74: =IF(01_INPUTS!M17,CHOOSE(MATCH($B$2,$U$1:$U$5,0),_ENGINE_FINANCIERO!M184,_ENGINE_FINANCIERO!M42,_ENGINE_FINANCIERO!M89,_ENGINE_FINANCIERO!M136,_ENGINE_FINANCIERO!M184),"") | N74: =IF(01_INPUTS!N17,CHOOSE(MATCH($B$2,$U$1:$U$5,0),_ENGINE_FINANCIERO!N184,_ENGINE_FINANCIERO!N42,_ENGINE_FINANCIERO!N89,_ENGINE_FINANCIERO!N136,_ENGINE_FINANCIERO!N184),"") | O74: =IF(01_INPUTS!O17,CHOOSE(MATCH($B$2,$U$1:$U$5,0),_ENGINE_FINANCIERO!O184,_ENGINE_FINANCIERO!O42,_ENGINE_FINANCIERO!O89,_ENGINE_FINANCIERO!O136,_ENGINE_FINANCIERO!O184),"") | P74: =IF(01_INPUTS!P17,CHOOSE(MATCH($B$2,$U$1:$U$5,0),_ENGINE_FINANCIERO!P184,_ENGINE_FINANCIERO!P42,_ENGINE_FINANCIERO!P89,_ENGINE_FINANCIERO!P136,_ENGINE_FINANCIERO!P184),"") | ... S74: =IF(01_INPUTS!S17,CHOOSE(MATCH($B$2,$U$1:$U$5,0),_ENGINE_FINANCIERO!S184,_ENGINE_FINANCIERO!S42,_ENGINE_FINANCIERO!S89,_ENGINE_FINANCIERO!S136,_ENGINE_FINANCIERO!S184),"")
A75: EE.UU. | B75: USD | G75: =_ENGINE_FINANCIERO!G42 -> 7.302669e+08 | H75: =_ENGINE_FINANCIERO!H42 -> 9.0122822e+08 | I75: =IF(01_INPUTS!I17,_ENGINE_FINANCIERO!I42,"") -> 1.0649823e+09 | J75: =IF(01_INPUTS!J17,_ENGINE_FINANCIERO!J42,"") | K75: =IF(01_INPUTS!K17,_ENGINE_FINANCIERO!K42,"") | L75: =IF(01_INPUTS!L17,_ENGINE_FINANCIERO!L42,"") | M75: =IF(01_INPUTS!M17,_ENGINE_FINANCIERO!M42,"") | N75: =IF(01_INPUTS!N17,_ENGINE_FINANCIERO!N42,"") | O75: =IF(01_INPUTS!O17,_ENGINE_FINANCIERO!O42,"") | P75: =IF(01_INPUTS!P17,_ENGINE_FINANCIERO!P42,"") | ... S75: =IF(01_INPUTS!S17,_ENGINE_FINANCIERO!S42,"")
A76: China | B76: USD | G76: =_ENGINE_FINANCIERO!G89 -> 4.2601554e+08 | H76: =_ENGINE_FINANCIERO!H89 -> 4.3742687e+08 | I76: =IF(01_INPUTS!I17,_ENGINE_FINANCIERO!I89,"") -> 9.2188413e+08 | J76: =IF(01_INPUTS!J17,_ENGINE_FINANCIERO!J89,"") | K76: =IF(01_INPUTS!K17,_ENGINE_FINANCIERO!K89,"") | L76: =IF(01_INPUTS!L17,_ENGINE_FINANCIERO!L89,"") | M76: =IF(01_INPUTS!M17,_ENGINE_FINANCIERO!M89,"") | N76: =IF(01_INPUTS!N17,_ENGINE_FINANCIERO!N89,"") | O76: =IF(01_INPUTS!O17,_ENGINE_FINANCIERO!O89,"") | P76: =IF(01_INPUTS!P17,_ENGINE_FINANCIERO!P89,"") | ... S76: =IF(01_INPUTS!S17,_ENGINE_FINANCIERO!S89,"")
A77: Europa | B77: USD | G77: =_ENGINE_FINANCIERO!G136 -> 1.0600533e+08 | H77: =_ENGINE_FINANCIERO!H136 -> 93135815 | I77: =IF(01_INPUTS!I17,_ENGINE_FINANCIERO!I136,"") -> 1.538655e+08 | J77: =IF(01_INPUTS!J17,_ENGINE_FINANCIERO!J136,"") | K77: =IF(01_INPUTS!K17,_ENGINE_FINANCIERO!K136,"") | L77: =IF(01_INPUTS!L17,_ENGINE_FINANCIERO!L136,"") | M77: =IF(01_INPUTS!M17,_ENGINE_FINANCIERO!M136,"") | N77: =IF(01_INPUTS!N17,_ENGINE_FINANCIERO!N136,"") | O77: =IF(01_INPUTS!O17,_ENGINE_FINANCIERO!O136,"") | P77: =IF(01_INPUTS!P17,_ENGINE_FINANCIERO!P136,"") | ... S77: =IF(01_INPUTS!S17,_ENGINE_FINANCIERO!S136,"")
A78: Pasivos Totales | B78: USD | G78: =CHOOSE(MATCH($B$2,$U$1:$U$5,0),_ENGINE_FINANCIERO!G185,_ENGINE_FINANCIERO!G43,_ENGINE_FINANCIERO!G90,_ENGINE_FINANCIERO!G137,_ENGINE_FINANCIERO!G185) -> 1.3162288e+10 | H78: =CHOOSE(MATCH($B$2,$U$1:$U$5,0),_ENGINE_FINANCIERO!H185,_ENGINE_FINANCIERO!H43,_ENGINE_FINANCIERO!H90,_ENGINE_FINANCIERO!H137,_ENGINE_FINANCIERO!H185) -> 1.3331791e+10 | I78: =IF(01_INPUTS!I17,CHOOSE(MATCH($B$2,$U$1:$U$5,0),_ENGINE_FINANCIERO!I185,_ENGINE_FINANCIERO!I43,_ENGINE_FINANCIERO!I90,_ENGINE_FINANCIERO!I137,_ENGINE_FINANCIERO!I185),"") -> 1.4040732e+10 | J78: =IF(01_INPUTS!J17,CHOOSE(MATCH($B$2,$U$1:$U$5,0),_ENGINE_FINANCIERO!J185,_ENGINE_FINANCIERO!J43,_ENGINE_FINANCIERO!J90,_ENGINE_FINANCIERO!J137,_ENGINE_FINANCIERO!J185),"") | K78: =IF(01_INPUTS!K17,CHOOSE(MATCH($B$2,$U$1:$U$5,0),_ENGINE_FINANCIERO!K185,_ENGINE_FINANCIERO!K43,_ENGINE_FINANCIERO!K90,_ENGINE_FINANCIERO!K137,_ENGINE_FINANCIERO!K185),"") | L78: =IF(01_INPUTS!L17,CHOOSE(MATCH($B$2,$U$1:$U$5,0),_ENGINE_FINANCIERO!L185,_ENGINE_FINANCIERO!L43,_ENGINE_FINANCIERO!L90,_ENGINE_FINANCIERO!L137,_ENGINE_FINANCIERO!L185),"") | M78: =IF(01_INPUTS!M17,CHOOSE(MATCH($B$2,$U$1:$U$5,0),_ENGINE_FINANCIERO!M185,_ENGINE_FINANCIERO!M43,_ENGINE_FINANCIERO!M90,_ENGINE_FINANCIERO!M137,_ENGINE_FINANCIERO!M185),"") | N78: =IF(01_INPUTS!N17,CHOOSE(MATCH($B$2,$U$1:$U$5,0),_ENGINE_FINANCIERO!N185,_ENGINE_FINANCIERO!N43,_ENGINE_FINANCIERO!N90,_ENGINE_FINANCIERO!N137,_ENGINE_FINANCIERO!N185),"") | O78: =IF(01_INPUTS!O17,CHOOSE(MATCH($B$2,$U$1:$U$5,0),_ENGINE_FINANCIERO!O185,_ENGINE_FINANCIERO!O43,_ENGINE_FINANCIERO!O90,_ENGINE_FINANCIERO!O137,_ENGINE_FINANCIERO!O185),"") | P78: =IF(01_INPUTS!P17,CHOOSE(MATCH($B$2,$U$1:$U$5,0),_ENGINE_FINANCIERO!P185,_ENGINE_FINANCIERO!P43,_ENGINE_FINANCIERO!P90,_ENGINE_FINANCIERO!P137,_ENGINE_FINANCIERO!P185),"") | ... S78: =IF(01_INPUTS!S17,CHOOSE(MATCH($B$2,$U$1:$U$5,0),_ENGINE_FINANCIERO!S185,_ENGINE_FINANCIERO!S43,_ENGINE_FINANCIERO!S90,_ENGINE_FINANCIERO!S137,_ENGINE_FINANCIERO!S185),"")
A79: EE.UU. | B79: USD | G79: =_ENGINE_FINANCIERO!G43 -> 1.3330267e+10 | H79: =_ENGINE_FINANCIERO!H43 -> 1.0501228e+10 | I79: =IF(01_INPUTS!I17,_ENGINE_FINANCIERO!I43,"") -> 1.0664982e+10 | J79: =IF(01_INPUTS!J17,_ENGINE_FINANCIERO!J43,"") | K79: =IF(01_INPUTS!K17,_ENGINE_FINANCIERO!K43,"") | L79: =IF(01_INPUTS!L17,_ENGINE_FINANCIERO!L43,"") | M79: =IF(01_INPUTS!M17,_ENGINE_FINANCIERO!M43,"") | N79: =IF(01_INPUTS!N17,_ENGINE_FINANCIERO!N43,"") | O79: =IF(01_INPUTS!O17,_ENGINE_FINANCIERO!O43,"") | P79: =IF(01_INPUTS!P17,_ENGINE_FINANCIERO!P43,"") | ... S79: =IF(01_INPUTS!S17,_ENGINE_FINANCIERO!S43,"")
A80: China | B80: USD | G80: =_ENGINE_FINANCIERO!G90 -> -1.7398446e+08 | H80: =_ENGINE_FINANCIERO!H90 -> 2.8374269e+09 | I80: =IF(01_INPUTS!I17,_ENGINE_FINANCIERO!I90,"") -> 3.3218841e+09 | J80: =IF(01_INPUTS!J17,_ENGINE_FINANCIERO!J90,"") | K80: =IF(01_INPUTS!K17,_ENGINE_FINANCIERO!K90,"") | L80: =IF(01_INPUTS!L17,_ENGINE_FINANCIERO!L90,"") | M80: =IF(01_INPUTS!M17,_ENGINE_FINANCIERO!M90,"") | N80: =IF(01_INPUTS!N17,_ENGINE_FINANCIERO!N90,"") | O80: =IF(01_INPUTS!O17,_ENGINE_FINANCIERO!O90,"") | P80: =IF(01_INPUTS!P17,_ENGINE_FINANCIERO!P90,"") | ... S80: =IF(01_INPUTS!S17,_ENGINE_FINANCIERO!S90,"")
A81: Europa | B81: USD | G81: =_ENGINE_FINANCIERO!G137 -> 6005327.1 | H81: =_ENGINE_FINANCIERO!H137 -> -6864184.7 | I81: =IF(01_INPUTS!I17,_ENGINE_FINANCIERO!I137,"") -> 53865499 | J81: =IF(01_INPUTS!J17,_ENGINE_FINANCIERO!J137,"") | K81: =IF(01_INPUTS!K17,_ENGINE_FINANCIERO!K137,"") | L81: =IF(01_INPUTS!L17,_ENGINE_FINANCIERO!L137,"") | M81: =IF(01_INPUTS!M17,_ENGINE_FINANCIERO!M137,"") | N81: =IF(01_INPUTS!N17,_ENGINE_FINANCIERO!N137,"") | O81: =IF(01_INPUTS!O17,_ENGINE_FINANCIERO!O137,"") | P81: =IF(01_INPUTS!P17,_ENGINE_FINANCIERO!P137,"") | ... S81: =IF(01_INPUTS!S17,_ENGINE_FINANCIERO!S137,"")
A82: Capital social | B82: USD | G82: =CHOOSE(MATCH($B$2,$U$1:$U$5,0),_ENGINE_FINANCIERO!G177,_ENGINE_FINANCIERO!G35,_ENGINE_FINANCIERO!G82,_ENGINE_FINANCIERO!G129,_ENGINE_FINANCIERO!G177) -> 5500000000 | H82: =CHOOSE(MATCH($B$2,$U$1:$U$5,0),_ENGINE_FINANCIERO!H177,_ENGINE_FINANCIERO!H35,_ENGINE_FINANCIERO!H82,_ENGINE_FINANCIERO!H129,_ENGINE_FINANCIERO!H177) -> 5500000000 | I82: =IF(01_INPUTS!I17,CHOOSE(MATCH($B$2,$U$1:$U$5,0),_ENGINE_FINANCIERO!I177,_ENGINE_FINANCIERO!I35,_ENGINE_FINANCIERO!I82,_ENGINE_FINANCIERO!I129,_ENGINE_FINANCIERO!I177),"") -> 5500000000 | J82: =IF(01_INPUTS!J17,CHOOSE(MATCH($B$2,$U$1:$U$5,0),_ENGINE_FINANCIERO!J177,_ENGINE_FINANCIERO!J35,_ENGINE_FINANCIERO!J82,_ENGINE_FINANCIERO!J129,_ENGINE_FINANCIERO!J177),"") | K82: =IF(01_INPUTS!K17,CHOOSE(MATCH($B$2,$U$1:$U$5,0),_ENGINE_FINANCIERO!K177,_ENGINE_FINANCIERO!K35,_ENGINE_FINANCIERO!K82,_ENGINE_FINANCIERO!K129,_ENGINE_FINANCIERO!K177),"") | L82: =IF(01_INPUTS!L17,CHOOSE(MATCH($B$2,$U$1:$U$5,0),_ENGINE_FINANCIERO!L177,_ENGINE_FINANCIERO!L35,_ENGINE_FINANCIERO!L82,_ENGINE_FINANCIERO!L129,_ENGINE_FINANCIERO!L177),"") | M82: =IF(01_INPUTS!M17,CHOOSE(MATCH($B$2,$U$1:$U$5,0),_ENGINE_FINANCIERO!M177,_ENGINE_FINANCIERO!M35,_ENGINE_FINANCIERO!M82,_ENGINE_FINANCIERO!M129,_ENGINE_FINANCIERO!M177),"") | N82: =IF(01_INPUTS!N17,CHOOSE(MATCH($B$2,$U$1:$U$5,0),_ENGINE_FINANCIERO!N177,_ENGINE_FINANCIERO!N35,_ENGINE_FINANCIERO!N82,_ENGINE_FINANCIERO!N129,_ENGINE_FINANCIERO!N177),"") | O82: =IF(01_INPUTS!O17,CHOOSE(MATCH($B$2,$U$1:$U$5,0),_ENGINE_FINANCIERO!O177,_ENGINE_FINANCIERO!O35,_ENGINE_FINANCIERO!O82,_ENGINE_FINANCIERO!O129,_ENGINE_FINANCIERO!O177),"") | P82: =IF(01_INPUTS!P17,CHOOSE(MATCH($B$2,$U$1:$U$5,0),_ENGINE_FINANCIERO!P177,_ENGINE_FINANCIERO!P35,_ENGINE_FINANCIERO!P82,_ENGINE_FINANCIERO!P129,_ENGINE_FINANCIERO!P177),"") | ... S82: =IF(01_INPUTS!S17,CHOOSE(MATCH($B$2,$U$1:$U$5,0),_ENGINE_FINANCIERO!S177,_ENGINE_FINANCIERO!S35,_ENGINE_FINANCIERO!S82,_ENGINE_FINANCIERO!S129,_ENGINE_FINANCIERO!S177),"")
A83: EE.UU. | B83: USD | G83: =_ENGINE_FINANCIERO!G35 -> 3250000000 | H83: =_ENGINE_FINANCIERO!H35 -> 3250000000 | I83: =IF(01_INPUTS!I17,_ENGINE_FINANCIERO!I35,"") -> 3250000000 | J83: =IF(01_INPUTS!J17,_ENGINE_FINANCIERO!J35,"") | K83: =IF(01_INPUTS!K17,_ENGINE_FINANCIERO!K35,"") | L83: =IF(01_INPUTS!L17,_ENGINE_FINANCIERO!L35,"") | M83: =IF(01_INPUTS!M17,_ENGINE_FINANCIERO!M35,"") | N83: =IF(01_INPUTS!N17,_ENGINE_FINANCIERO!N35,"") | O83: =IF(01_INPUTS!O17,_ENGINE_FINANCIERO!O35,"") | P83: =IF(01_INPUTS!P17,_ENGINE_FINANCIERO!P35,"") | ... S83: =IF(01_INPUTS!S17,_ENGINE_FINANCIERO!S35,"")
A84: China | B84: USD | G84: =_ENGINE_FINANCIERO!G82 -> 1500000000 | H84: =_ENGINE_FINANCIERO!H82 -> 1500000000 | I84: =IF(01_INPUTS!I17,_ENGINE_FINANCIERO!I82,"") -> 1500000000 | J84: =IF(01_INPUTS!J17,_ENGINE_FINANCIERO!J82,"") | K84: =IF(01_INPUTS!K17,_ENGINE_FINANCIERO!K82,"") | L84: =IF(01_INPUTS!L17,_ENGINE_FINANCIERO!L82,"") | M84: =IF(01_INPUTS!M17,_ENGINE_FINANCIERO!M82,"") | N84: =IF(01_INPUTS!N17,_ENGINE_FINANCIERO!N82,"") | O84: =IF(01_INPUTS!O17,_ENGINE_FINANCIERO!O82,"") | P84: =IF(01_INPUTS!P17,_ENGINE_FINANCIERO!P82,"") | ... S84: =IF(01_INPUTS!S17,_ENGINE_FINANCIERO!S82,"")
A85: Europa | B85: USD | G85: =_ENGINE_FINANCIERO!G129 -> 750000000 | H85: =_ENGINE_FINANCIERO!H129 -> 750000000 | I85: =IF(01_INPUTS!I17,_ENGINE_FINANCIERO!I129,"") -> 750000000 | J85: =IF(01_INPUTS!J17,_ENGINE_FINANCIERO!J129,"") | K85: =IF(01_INPUTS!K17,_ENGINE_FINANCIERO!K129,"") | L85: =IF(01_INPUTS!L17,_ENGINE_FINANCIERO!L129,"") | M85: =IF(01_INPUTS!M17,_ENGINE_FINANCIERO!M129,"") | N85: =IF(01_INPUTS!N17,_ENGINE_FINANCIERO!N129,"") | O85: =IF(01_INPUTS!O17,_ENGINE_FINANCIERO!O129,"") | P85: =IF(01_INPUTS!P17,_ENGINE_FINANCIERO!P129,"") | ... S85: =IF(01_INPUTS!S17,_ENGINE_FINANCIERO!S129,"")
A86: Capital adicional desembolsado | B86: USD | G86: =CHOOSE(MATCH($B$2,$U$1:$U$5,0),_ENGINE_FINANCIERO!G179,_ENGINE_FINANCIERO!G36,_ENGINE_FINANCIERO!G83,_ENGINE_FINANCIERO!G130,_ENGINE_FINANCIERO!G179) -> 0 | H86: =CHOOSE(MATCH($B$2,$U$1:$U$5,0),_ENGINE_FINANCIERO!H179,_ENGINE_FINANCIERO!H36,_ENGINE_FINANCIERO!H83,_ENGINE_FINANCIERO!H130,_ENGINE_FINANCIERO!H179) -> 0 | I86: =IF(01_INPUTS!I17,CHOOSE(MATCH($B$2,$U$1:$U$5,0),_ENGINE_FINANCIERO!I179,_ENGINE_FINANCIERO!I36,_ENGINE_FINANCIERO!I83,_ENGINE_FINANCIERO!I130,_ENGINE_FINANCIERO!I179),"") -> 0 | J86: =IF(01_INPUTS!J17,CHOOSE(MATCH($B$2,$U$1:$U$5,0),_ENGINE_FINANCIERO!J179,_ENGINE_FINANCIERO!J36,_ENGINE_FINANCIERO!J83,_ENGINE_FINANCIERO!J130,_ENGINE_FINANCIERO!J179),"") | K86: =IF(01_INPUTS!K17,CHOOSE(MATCH($B$2,$U$1:$U$5,0),_ENGINE_FINANCIERO!K179,_ENGINE_FINANCIERO!K36,_ENGINE_FINANCIERO!K83,_ENGINE_FINANCIERO!K130,_ENGINE_FINANCIERO!K179),"") | L86: =IF(01_INPUTS!L17,CHOOSE(MATCH($B$2,$U$1:$U$5,0),_ENGINE_FINANCIERO!L179,_ENGINE_FINANCIERO!L36,_ENGINE_FINANCIERO!L83,_ENGINE_FINANCIERO!L130,_ENGINE_FINANCIERO!L179),"") | M86: =IF(01_INPUTS!M17,CHOOSE(MATCH($B$2,$U$1:$U$5,0),_ENGINE_FINANCIERO!M179,_ENGINE_FINANCIERO!M36,_ENGINE_FINANCIERO!M83,_ENGINE_FINANCIERO!M130,_ENGINE_FINANCIERO!M179),"") | N86: =IF(01_INPUTS!N17,CHOOSE(MATCH($B$2,$U$1:$U$5,0),_ENGINE_FINANCIERO!N179,_ENGINE_FINANCIERO!N36,_ENGINE_FINANCIERO!N83,_ENGINE_FINANCIERO!N130,_ENGINE_FINANCIERO!N179),"") | O86: =IF(01_INPUTS!O17,CHOOSE(MATCH($B$2,$U$1:$U$5,0),_ENGINE_FINANCIERO!O179,_ENGINE_FINANCIERO!O36,_ENGINE_FINANCIERO!O83,_ENGINE_FINANCIERO!O130,_ENGINE_FINANCIERO!O179),"") | P86: =IF(01_INPUTS!P17,CHOOSE(MATCH($B$2,$U$1:$U$5,0),_ENGINE_FINANCIERO!P179,_ENGINE_FINANCIERO!P36,_ENGINE_FINANCIERO!P83,_ENGINE_FINANCIERO!P130,_ENGINE_FINANCIERO!P179),"") | ... S86: =IF(01_INPUTS!S17,CHOOSE(MATCH($B$2,$U$1:$U$5,0),_ENGINE_FINANCIERO!S179,_ENGINE_FINANCIERO!S36,_ENGINE_FINANCIERO!S83,_ENGINE_FINANCIERO!S130,_ENGINE_FINANCIERO!S179),"")
A87: EE.UU. | B87: USD | G87: =_ENGINE_FINANCIERO!G36 -> 0 | H87: =_ENGINE_FINANCIERO!H36 -> 0 | I87: =IF(01_INPUTS!I17,_ENGINE_FINANCIERO!I36,"") -> 0 | J87: =IF(01_INPUTS!J17,_ENGINE_FINANCIERO!J36,"") | K87: =IF(01_INPUTS!K17,_ENGINE_FINANCIERO!K36,"") | L87: =IF(01_INPUTS!L17,_ENGINE_FINANCIERO!L36,"") | M87: =IF(01_INPUTS!M17,_ENGINE_FINANCIERO!M36,"") | N87: =IF(01_INPUTS!N17,_ENGINE_FINANCIERO!N36,"") | O87: =IF(01_INPUTS!O17,_ENGINE_FINANCIERO!O36,"") | P87: =IF(01_INPUTS!P17,_ENGINE_FINANCIERO!P36,"") | ... S87: =IF(01_INPUTS!S17,_ENGINE_FINANCIERO!S36,"")
A88: China | B88: USD | G88: =_ENGINE_FINANCIERO!G83 -> 0 | H88: =_ENGINE_FINANCIERO!H83 -> 0 | I88: =IF(01_INPUTS!I17,_ENGINE_FINANCIERO!I83,"") -> 0 | J88: =IF(01_INPUTS!J17,_ENGINE_FINANCIERO!J83,"") | K88: =IF(01_INPUTS!K17,_ENGINE_FINANCIERO!K83,"") | L88: =IF(01_INPUTS!L17,_ENGINE_FINANCIERO!L83,"") | M88: =IF(01_INPUTS!M17,_ENGINE_FINANCIERO!M83,"") | N88: =IF(01_INPUTS!N17,_ENGINE_FINANCIERO!N83,"") | O88: =IF(01_INPUTS!O17,_ENGINE_FINANCIERO!O83,"") | P88: =IF(01_INPUTS!P17,_ENGINE_FINANCIERO!P83,"") | ... S88: =IF(01_INPUTS!S17,_ENGINE_FINANCIERO!S83,"")
A89: Europa | B89: USD | G89: =_ENGINE_FINANCIERO!G130 -> 0 | H89: =_ENGINE_FINANCIERO!H130 -> 0 | I89: =IF(01_INPUTS!I17,_ENGINE_FINANCIERO!I130,"") -> 0 | J89: =IF(01_INPUTS!J17,_ENGINE_FINANCIERO!J130,"") | K89: =IF(01_INPUTS!K17,_ENGINE_FINANCIERO!K130,"") | L89: =IF(01_INPUTS!L17,_ENGINE_FINANCIERO!L130,"") | M89: =IF(01_INPUTS!M17,_ENGINE_FINANCIERO!M130,"") | N89: =IF(01_INPUTS!N17,_ENGINE_FINANCIERO!N130,"") | O89: =IF(01_INPUTS!O17,_ENGINE_FINANCIERO!O130,"") | P89: =IF(01_INPUTS!P17,_ENGINE_FINANCIERO!P130,"") | ... S89: =IF(01_INPUTS!S17,_ENGINE_FINANCIERO!S130,"")
A90: Ganancias acumuladas | B90: USD | G90: =CHOOSE(MATCH($B$2,$U$1:$U$5,0),_ENGINE_FINANCIERO!G180,_ENGINE_FINANCIERO!G37,_ENGINE_FINANCIERO!G84,_ENGINE_FINANCIERO!G131,_ENGINE_FINANCIERO!G180) -> 4.503562e+09 | H90: =CHOOSE(MATCH($B$2,$U$1:$U$5,0),_ENGINE_FINANCIERO!H180,_ENGINE_FINANCIERO!H37,_ENGINE_FINANCIERO!H84,_ENGINE_FINANCIERO!H131,_ENGINE_FINANCIERO!H180) -> 6.1128985e+09 | I90: =IF(01_INPUTS!I17,CHOOSE(MATCH($B$2,$U$1:$U$5,0),_ENGINE_FINANCIERO!I180,_ENGINE_FINANCIERO!I37,_ENGINE_FINANCIERO!I84,_ENGINE_FINANCIERO!I131,_ENGINE_FINANCIERO!I180),"") -> 1.6727965e+10 | J90: =IF(01_INPUTS!J17,CHOOSE(MATCH($B$2,$U$1:$U$5,0),_ENGINE_FINANCIERO!J180,_ENGINE_FINANCIERO!J37,_ENGINE_FINANCIERO!J84,_ENGINE_FINANCIERO!J131,_ENGINE_FINANCIERO!J180),"") | K90: =IF(01_INPUTS!K17,CHOOSE(MATCH($B$2,$U$1:$U$5,0),_ENGINE_FINANCIERO!K180,_ENGINE_FINANCIERO!K37,_ENGINE_FINANCIERO!K84,_ENGINE_FINANCIERO!K131,_ENGINE_FINANCIERO!K180),"") | L90: =IF(01_INPUTS!L17,CHOOSE(MATCH($B$2,$U$1:$U$5,0),_ENGINE_FINANCIERO!L180,_ENGINE_FINANCIERO!L37,_ENGINE_FINANCIERO!L84,_ENGINE_FINANCIERO!L131,_ENGINE_FINANCIERO!L180),"") | M90: =IF(01_INPUTS!M17,CHOOSE(MATCH($B$2,$U$1:$U$5,0),_ENGINE_FINANCIERO!M180,_ENGINE_FINANCIERO!M37,_ENGINE_FINANCIERO!M84,_ENGINE_FINANCIERO!M131,_ENGINE_FINANCIERO!M180),"") | N90: =IF(01_INPUTS!N17,CHOOSE(MATCH($B$2,$U$1:$U$5,0),_ENGINE_FINANCIERO!N180,_ENGINE_FINANCIERO!N37,_ENGINE_FINANCIERO!N84,_ENGINE_FINANCIERO!N131,_ENGINE_FINANCIERO!N180),"") | O90: =IF(01_INPUTS!O17,CHOOSE(MATCH($B$2,$U$1:$U$5,0),_ENGINE_FINANCIERO!O180,_ENGINE_FINANCIERO!O37,_ENGINE_FINANCIERO!O84,_ENGINE_FINANCIERO!O131,_ENGINE_FINANCIERO!O180),"") | P90: =IF(01_INPUTS!P17,CHOOSE(MATCH($B$2,$U$1:$U$5,0),_ENGINE_FINANCIERO!P180,_ENGINE_FINANCIERO!P37,_ENGINE_FINANCIERO!P84,_ENGINE_FINANCIERO!P131,_ENGINE_FINANCIERO!P180),"") | ... S90: =IF(01_INPUTS!S17,CHOOSE(MATCH($B$2,$U$1:$U$5,0),_ENGINE_FINANCIERO!S180,_ENGINE_FINANCIERO!S37,_ENGINE_FINANCIERO!S84,_ENGINE_FINANCIERO!S131,_ENGINE_FINANCIERO!S180),"")
A91: EE.UU. | B91: USD | G91: =_ENGINE_FINANCIERO!G37 -> 2.2558127e+09 | H91: =_ENGINE_FINANCIERO!H37 -> 2.425432e+09 | I91: =IF(01_INPUTS!I17,_ENGINE_FINANCIERO!I37,"") -> 1.5448425e+09 | J91: =IF(01_INPUTS!J17,_ENGINE_FINANCIERO!J37,"") | K91: =IF(01_INPUTS!K17,_ENGINE_FINANCIERO!K37,"") | L91: =IF(01_INPUTS!L17,_ENGINE_FINANCIERO!L37,"") | M91: =IF(01_INPUTS!M17,_ENGINE_FINANCIERO!M37,"") | N91: =IF(01_INPUTS!N17,_ENGINE_FINANCIERO!N37,"") | O91: =IF(01_INPUTS!O17,_ENGINE_FINANCIERO!O37,"") | P91: =IF(01_INPUTS!P17,_ENGINE_FINANCIERO!P37,"") | ... S91: =IF(01_INPUTS!S17,_ENGINE_FINANCIERO!S37,"")
A92: China | B92: USD | G92: =_ENGINE_FINANCIERO!G84 -> 1.1685867e+09 | H92: =_ENGINE_FINANCIERO!H84 -> 2.1985251e+09 | I92: =IF(01_INPUTS!I17,_ENGINE_FINANCIERO!I84,"") -> 4.8453022e+09 | J92: =IF(01_INPUTS!J17,_ENGINE_FINANCIERO!J84,"") | K92: =IF(01_INPUTS!K17,_ENGINE_FINANCIERO!K84,"") | L92: =IF(01_INPUTS!L17,_ENGINE_FINANCIERO!L84,"") | M92: =IF(01_INPUTS!M17,_ENGINE_FINANCIERO!M84,"") | N92: =IF(01_INPUTS!N17,_ENGINE_FINANCIERO!N84,"") | O92: =IF(01_INPUTS!O17,_ENGINE_FINANCIERO!O84,"") | P92: =IF(01_INPUTS!P17,_ENGINE_FINANCIERO!P84,"") | ... S92: =IF(01_INPUTS!S17,_ENGINE_FINANCIERO!S84,"")
A93: Europa | B93: USD | G93: =_ENGINE_FINANCIERO!G131 -> 1.0791625e+09 | H93: =_ENGINE_FINANCIERO!H131 -> 1.4889414e+09 | I93: =IF(01_INPUTS!I17,_ENGINE_FINANCIERO!I131,"") -> 1.033782e+10 | J93: =IF(01_INPUTS!J17,_ENGINE_FINANCIERO!J131,"") | K93: =IF(01_INPUTS!K17,_ENGINE_FINANCIERO!K131,"") | L93: =IF(01_INPUTS!L17,_ENGINE_FINANCIERO!L131,"") | M93: =IF(01_INPUTS!M17,_ENGINE_FINANCIERO!M131,"") | N93: =IF(01_INPUTS!N17,_ENGINE_FINANCIERO!N131,"") | O93: =IF(01_INPUTS!O17,_ENGINE_FINANCIERO!O131,"") | P93: =IF(01_INPUTS!P17,_ENGINE_FINANCIERO!P131,"") | ... S93: =IF(01_INPUTS!S17,_ENGINE_FINANCIERO!S131,"")
A94: Patrimonio neto | B94: USD | G94: =CHOOSE(MATCH($B$2,$U$1:$U$5,0),_ENGINE_FINANCIERO!G181,_ENGINE_FINANCIERO!G38,_ENGINE_FINANCIERO!G85,_ENGINE_FINANCIERO!G132,_ENGINE_FINANCIERO!G181) -> 1.0003562e+10 | H94: =CHOOSE(MATCH($B$2,$U$1:$U$5,0),_ENGINE_FINANCIERO!H181,_ENGINE_FINANCIERO!H38,_ENGINE_FINANCIERO!H85,_ENGINE_FINANCIERO!H132,_ENGINE_FINANCIERO!H181) -> 1.1612898e+10 | I94: =IF(01_INPUTS!I17,CHOOSE(MATCH($B$2,$U$1:$U$5,0),_ENGINE_FINANCIERO!I181,_ENGINE_FINANCIERO!I38,_ENGINE_FINANCIERO!I85,_ENGINE_FINANCIERO!I132,_ENGINE_FINANCIERO!I181),"") -> 2.2227965e+10 | J94: =IF(01_INPUTS!J17,CHOOSE(MATCH($B$2,$U$1:$U$5,0),_ENGINE_FINANCIERO!J181,_ENGINE_FINANCIERO!J38,_ENGINE_FINANCIERO!J85,_ENGINE_FINANCIERO!J132,_ENGINE_FINANCIERO!J181),"") | K94: =IF(01_INPUTS!K17,CHOOSE(MATCH($B$2,$U$1:$U$5,0),_ENGINE_FINANCIERO!K181,_ENGINE_FINANCIERO!K38,_ENGINE_FINANCIERO!K85,_ENGINE_FINANCIERO!K132,_ENGINE_FINANCIERO!K181),"") | L94: =IF(01_INPUTS!L17,CHOOSE(MATCH($B$2,$U$1:$U$5,0),_ENGINE_FINANCIERO!L181,_ENGINE_FINANCIERO!L38,_ENGINE_FINANCIERO!L85,_ENGINE_FINANCIERO!L132,_ENGINE_FINANCIERO!L181),"") | M94: =IF(01_INPUTS!M17,CHOOSE(MATCH($B$2,$U$1:$U$5,0),_ENGINE_FINANCIERO!M181,_ENGINE_FINANCIERO!M38,_ENGINE_FINANCIERO!M85,_ENGINE_FINANCIERO!M132,_ENGINE_FINANCIERO!M181),"") | N94: =IF(01_INPUTS!N17,CHOOSE(MATCH($B$2,$U$1:$U$5,0),_ENGINE_FINANCIERO!N181,_ENGINE_FINANCIERO!N38,_ENGINE_FINANCIERO!N85,_ENGINE_FINANCIERO!N132,_ENGINE_FINANCIERO!N181),"") | O94: =IF(01_INPUTS!O17,CHOOSE(MATCH($B$2,$U$1:$U$5,0),_ENGINE_FINANCIERO!O181,_ENGINE_FINANCIERO!O38,_ENGINE_FINANCIERO!O85,_ENGINE_FINANCIERO!O132,_ENGINE_FINANCIERO!O181),"") | P94: =IF(01_INPUTS!P17,CHOOSE(MATCH($B$2,$U$1:$U$5,0),_ENGINE_FINANCIERO!P181,_ENGINE_FINANCIERO!P38,_ENGINE_FINANCIERO!P85,_ENGINE_FINANCIERO!P132,_ENGINE_FINANCIERO!P181),"") | ... S94: =IF(01_INPUTS!S17,CHOOSE(MATCH($B$2,$U$1:$U$5,0),_ENGINE_FINANCIERO!S181,_ENGINE_FINANCIERO!S38,_ENGINE_FINANCIERO!S85,_ENGINE_FINANCIERO!S132,_ENGINE_FINANCIERO!S181),"")
A95: EE.UU. | B95: USD | G95: =_ENGINE_FINANCIERO!G38 -> 5.5058127e+09 | H95: =_ENGINE_FINANCIERO!H38 -> 5.675432e+09 | I95: =IF(01_INPUTS!I17,_ENGINE_FINANCIERO!I38,"") -> 4.7948425e+09 | J95: =IF(01_INPUTS!J17,_ENGINE_FINANCIERO!J38,"") | K95: =IF(01_INPUTS!K17,_ENGINE_FINANCIERO!K38,"") | L95: =IF(01_INPUTS!L17,_ENGINE_FINANCIERO!L38,"") | M95: =IF(01_INPUTS!M17,_ENGINE_FINANCIERO!M38,"") | N95: =IF(01_INPUTS!N17,_ENGINE_FINANCIERO!N38,"") | O95: =IF(01_INPUTS!O17,_ENGINE_FINANCIERO!O38,"") | P95: =IF(01_INPUTS!P17,_ENGINE_FINANCIERO!P38,"") | ... S95: =IF(01_INPUTS!S17,_ENGINE_FINANCIERO!S38,"")
A96: China | B96: USD | G96: =_ENGINE_FINANCIERO!G85 -> 2.6685867e+09 | H96: =_ENGINE_FINANCIERO!H85 -> 3.6985251e+09 | I96: =IF(01_INPUTS!I17,_ENGINE_FINANCIERO!I85,"") -> 6.3453022e+09 | J96: =IF(01_INPUTS!J17,_ENGINE_FINANCIERO!J85,"") | K96: =IF(01_INPUTS!K17,_ENGINE_FINANCIERO!K85,"") | L96: =IF(01_INPUTS!L17,_ENGINE_FINANCIERO!L85,"") | M96: =IF(01_INPUTS!M17,_ENGINE_FINANCIERO!M85,"") | N96: =IF(01_INPUTS!N17,_ENGINE_FINANCIERO!N85,"") | O96: =IF(01_INPUTS!O17,_ENGINE_FINANCIERO!O85,"") | P96: =IF(01_INPUTS!P17,_ENGINE_FINANCIERO!P85,"") | ... S96: =IF(01_INPUTS!S17,_ENGINE_FINANCIERO!S85,"")
A97: Europa | B97: USD | G97: =_ENGINE_FINANCIERO!G132 -> 1.8291625e+09 | H97: =_ENGINE_FINANCIERO!H132 -> 2.2389414e+09 | I97: =IF(01_INPUTS!I17,_ENGINE_FINANCIERO!I132,"") -> 1.108782e+10 | J97: =IF(01_INPUTS!J17,_ENGINE_FINANCIERO!J132,"") | K97: =IF(01_INPUTS!K17,_ENGINE_FINANCIERO!K132,"") | L97: =IF(01_INPUTS!L17,_ENGINE_FINANCIERO!L132,"") | M97: =IF(01_INPUTS!M17,_ENGINE_FINANCIERO!M132,"") | N97: =IF(01_INPUTS!N17,_ENGINE_FINANCIERO!N132,"") | O97: =IF(01_INPUTS!O17,_ENGINE_FINANCIERO!O132,"") | P97: =IF(01_INPUTS!P17,_ENGINE_FINANCIERO!P132,"") | ... S97: =IF(01_INPUTS!S17,_ENGINE_FINANCIERO!S132,"")
A99: FLUJO DE FONDOS (método indirecto)
A100: Total actividades operativas | B100: USD | G100: =CHOOSE(MATCH($B$2,$U$1:$U$5,0),_ENGINE_FINANCIERO!G190,_ENGINE_FINANCIERO!G45,_ENGINE_FINANCIERO!G92,_ENGINE_FINANCIERO!G139,_ENGINE_FINANCIERO!G190) -> n/a (Ronda 0) | H100: =CHOOSE(MATCH($B$2,$U$1:$U$5,0),_ENGINE_FINANCIERO!H190,_ENGINE_FINANCIERO!H45,_ENGINE_FINANCIERO!H92,_ENGINE_FINANCIERO!H139,_ENGINE_FINANCIERO!H190) -> -3.7207303e+09 | I100: =IF(01_INPUTS!I17,CHOOSE(MATCH($B$2,$U$1:$U$5,0),_ENGINE_FINANCIERO!I190,_ENGINE_FINANCIERO!I45,_ENGINE_FINANCIERO!I92,_ENGINE_FINANCIERO!I139,_ENGINE_FINANCIERO!I190),"") -> 2.1562266e+10 | J100: =IF(01_INPUTS!J17,CHOOSE(MATCH($B$2,$U$1:$U$5,0),_ENGINE_FINANCIERO!J190,_ENGINE_FINANCIERO!J45,_ENGINE_FINANCIERO!J92,_ENGINE_FINANCIERO!J139,_ENGINE_FINANCIERO!J190),"") | K100: =IF(01_INPUTS!K17,CHOOSE(MATCH($B$2,$U$1:$U$5,0),_ENGINE_FINANCIERO!K190,_ENGINE_FINANCIERO!K45,_ENGINE_FINANCIERO!K92,_ENGINE_FINANCIERO!K139,_ENGINE_FINANCIERO!K190),"") | L100: =IF(01_INPUTS!L17,CHOOSE(MATCH($B$2,$U$1:$U$5,0),_ENGINE_FINANCIERO!L190,_ENGINE_FINANCIERO!L45,_ENGINE_FINANCIERO!L92,_ENGINE_FINANCIERO!L139,_ENGINE_FINANCIERO!L190),"") | M100: =IF(01_INPUTS!M17,CHOOSE(MATCH($B$2,$U$1:$U$5,0),_ENGINE_FINANCIERO!M190,_ENGINE_FINANCIERO!M45,_ENGINE_FINANCIERO!M92,_ENGINE_FINANCIERO!M139,_ENGINE_FINANCIERO!M190),"") | N100: =IF(01_INPUTS!N17,CHOOSE(MATCH($B$2,$U$1:$U$5,0),_ENGINE_FINANCIERO!N190,_ENGINE_FINANCIERO!N45,_ENGINE_FINANCIERO!N92,_ENGINE_FINANCIERO!N139,_ENGINE_FINANCIERO!N190),"") | O100: =IF(01_INPUTS!O17,CHOOSE(MATCH($B$2,$U$1:$U$5,0),_ENGINE_FINANCIERO!O190,_ENGINE_FINANCIERO!O45,_ENGINE_FINANCIERO!O92,_ENGINE_FINANCIERO!O139,_ENGINE_FINANCIERO!O190),"") | P100: =IF(01_INPUTS!P17,CHOOSE(MATCH($B$2,$U$1:$U$5,0),_ENGINE_FINANCIERO!P190,_ENGINE_FINANCIERO!P45,_ENGINE_FINANCIERO!P92,_ENGINE_FINANCIERO!P139,_ENGINE_FINANCIERO!P190),"") | ... S100: =IF(01_INPUTS!S17,CHOOSE(MATCH($B$2,$U$1:$U$5,0),_ENGINE_FINANCIERO!S190,_ENGINE_FINANCIERO!S45,_ENGINE_FINANCIERO!S92,_ENGINE_FINANCIERO!S139,_ENGINE_FINANCIERO!S190),"")
A101: EE.UU. | B101: USD | G101: =_ENGINE_FINANCIERO!G45 -> n/a (Ronda 0) | H101: =_ENGINE_FINANCIERO!H45 -> -4.1680063e+09 | I101: =IF(01_INPUTS!I17,_ENGINE_FINANCIERO!I45,"") -> 8.579509e+09 | J101: =IF(01_INPUTS!J17,_ENGINE_FINANCIERO!J45,"") | K101: =IF(01_INPUTS!K17,_ENGINE_FINANCIERO!K45,"") | L101: =IF(01_INPUTS!L17,_ENGINE_FINANCIERO!L45,"") | M101: =IF(01_INPUTS!M17,_ENGINE_FINANCIERO!M45,"") | N101: =IF(01_INPUTS!N17,_ENGINE_FINANCIERO!N45,"") | O101: =IF(01_INPUTS!O17,_ENGINE_FINANCIERO!O45,"") | P101: =IF(01_INPUTS!P17,_ENGINE_FINANCIERO!P45,"") | ... S101: =IF(01_INPUTS!S17,_ENGINE_FINANCIERO!S45,"")
A102: China | B102: USD | G102: =_ENGINE_FINANCIERO!G92 -> n/a (Ronda 0) | H102: =_ENGINE_FINANCIERO!H92 -> -5.6249841e+08 | I102: =IF(01_INPUTS!I17,_ENGINE_FINANCIERO!I92,"") -> 4.7689139e+09 | J102: =IF(01_INPUTS!J17,_ENGINE_FINANCIERO!J92,"") | K102: =IF(01_INPUTS!K17,_ENGINE_FINANCIERO!K92,"") | L102: =IF(01_INPUTS!L17,_ENGINE_FINANCIERO!L92,"") | M102: =IF(01_INPUTS!M17,_ENGINE_FINANCIERO!M92,"") | N102: =IF(01_INPUTS!N17,_ENGINE_FINANCIERO!N92,"") | O102: =IF(01_INPUTS!O17,_ENGINE_FINANCIERO!O92,"") | P102: =IF(01_INPUTS!P17,_ENGINE_FINANCIERO!P92,"") | ... S102: =IF(01_INPUTS!S17,_ENGINE_FINANCIERO!S92,"")
...

Sheet 03_RATIOS
A1: 03_RATIOS — Ratios de crecimiento, rentabilidad, financieros y operativos (GLOBAL, por ronda)
A3: Concepto | B3: Unidad | G3: R0 | H3: R1 | I3: R2 | J3: R3 | K3: R4 | L3: R5 | M3: R6 | N3: R7 | O3: R8 | P3: R9 | Q3: R10 | R3: R11 | S3: R12
A4: CRECIMIENTO
A5: Crecimiento de Ingresos vs. ronda anterior | B5: % | G5: n/a (ver 02_ESTADOS_PROYECTADOS) | H5: n/a (ver 02_ESTADOS_PROYECTADOS) | I5: =IF(01_INPUTS!I17,IFERROR((_ENGINE_FINANCIERO!I160-_ENGINE_FINANCIERO!H160)/_ENGINE_FINANCIERO!H160,""),"") | J5: =IF(01_INPUTS!J17,IFERROR((_ENGINE_FINANCIERO!J160-_ENGINE_FINANCIERO!I160)/_ENGINE_FINANCIERO!I160,""),"") | K5: =IF(01_INPUTS!K17,IFERROR((_ENGINE_FINANCIERO!K160-_ENGINE_FINANCIERO!J160)/_ENGINE_FINANCIERO!J160,""),"") | L5: =IF(01_INPUTS!L17,IFERROR((_ENGINE_FINANCIERO!L160-_ENGINE_FINANCIERO!K160)/_ENGINE_FINANCIERO!K160,""),"") | M5: =IF(01_INPUTS!M17,IFERROR((_ENGINE_FINANCIERO!M160-_ENGINE_FINANCIERO!L160)/_ENGINE_FINANCIERO!L160,""),"") | N5: =IF(01_INPUTS!N17,IFERROR((_ENGINE_FINANCIERO!N160-_ENGINE_FINANCIERO!M160)/_ENGINE_FINANCIERO!M160,""),"") | O5: =IF(01_INPUTS!O17,IFERROR((_ENGINE_FINANCIERO!O160-_ENGINE_FINANCIERO!N160)/_ENGINE_FINANCIERO!N160,""),"") | P5: =IF(01_INPUTS!P17,IFERROR((_ENGINE_FINANCIERO!P160-_ENGINE_FINANCIERO!O160)/_ENGINE_FINANCIERO!O160,""),"") | ... S5: =IF(01_INPUTS!S17,IFERROR((_ENGINE_FINANCIERO!S160-_ENGINE_FINANCIERO!R160)/_ENGINE_FINANCIERO!R160,""),"")
A6: RENTABILIDAD
A7: Margen EBITDA | B7: % | G7: n/a (ver 02_ESTADOS_PROYECTADOS) | H7: n/a (ver 02_ESTADOS_PROYECTADOS) | I7: =IF(01_INPUTS!I17,IFERROR(_ENGINE_FINANCIERO!I162/_ENGINE_FINANCIERO!I160,""),"") -> 0.24432294 | J7: =IF(01_INPUTS!J17,IFERROR(_ENGINE_FINANCIERO!J162/_ENGINE_FINANCIERO!J160,""),"") | K7: =IF(01_INPUTS!K17,IFERROR(_ENGINE_FINANCIERO!K162/_ENGINE_FINANCIERO!K160,""),"") | L7: =IF(01_INPUTS!L17,IFERROR(_ENGINE_FINANCIERO!L162/_ENGINE_FINANCIERO!L160,""),"") | M7: =IF(01_INPUTS!M17,IFERROR(_ENGINE_FINANCIERO!M162/_ENGINE_FINANCIERO!M160,""),"") | N7: =IF(01_INPUTS!N17,IFERROR(_ENGINE_FINANCIERO!N162/_ENGINE_FINANCIERO!N160,""),"") | O7: =IF(01_INPUTS!O17,IFERROR(_ENGINE_FINANCIERO!O162/_ENGINE_FINANCIERO!O160,""),"") | P7: =IF(01_INPUTS!P17,IFERROR(_ENGINE_FINANCIERO!P162/_ENGINE_FINANCIERO!P160,""),"") | ... S7: =IF(01_INPUTS!S17,IFERROR(_ENGINE_FINANCIERO!S162/_ENGINE_FINANCIERO!S160,""),"")
A8: ROS — Beneficio neto / Ingresos | B8: % | G8: n/a (ver 02_ESTADOS_PROYECTADOS) | H8: n/a (ver 02_ESTADOS_PROYECTADOS) | I8: =IF(01_INPUTS!I17,IFERROR(_ENGINE_FINANCIERO!I168/_ENGINE_FINANCIERO!I160,""),"") -> 0.17695483 | J8: =IF(01_INPUTS!J17,IFERROR(_ENGINE_FINANCIERO!J168/_ENGINE_FINANCIERO!J160,""),"") | K8: =IF(01_INPUTS!K17,IFERROR(_ENGINE_FINANCIERO!K168/_ENGINE_FINANCIERO!K160,""),"") | L8: =IF(01_INPUTS!L17,IFERROR(_ENGINE_FINANCIERO!L168/_ENGINE_FINANCIERO!L160,""),"") | M8: =IF(01_INPUTS!M17,IFERROR(_ENGINE_FINANCIERO!M168/_ENGINE_FINANCIERO!M160,""),"") | N8: =IF(01_INPUTS!N17,IFERROR(_ENGINE_FINANCIERO!N168/_ENGINE_FINANCIERO!N160,""),"") | O8: =IF(01_INPUTS!O17,IFERROR(_ENGINE_FINANCIERO!O168/_ENGINE_FINANCIERO!O160,""),"") | P8: =IF(01_INPUTS!P17,IFERROR(_ENGINE_FINANCIERO!P168/_ENGINE_FINANCIERO!P160,""),"") | ... S8: =IF(01_INPUTS!S17,IFERROR(_ENGINE_FINANCIERO!S168/_ENGINE_FINANCIERO!S160,""),"")
A9: ROE — Beneficio neto / Patrimonio promedio (apertura,cierre) | B9: % | G9: n/a (ver 02_ESTADOS_PROYECTADOS) | H9: n/a (ver 02_ESTADOS_PROYECTADOS) | I9: =IF(01_INPUTS!I17,IFERROR(_ENGINE_FINANCIERO!I168/((_ENGINE_FINANCIERO!H181+_ENGINE_FINANCIERO!I181)/2),""),"") -> 0.80465242 | J9: =IF(01_INPUTS!J17,IFERROR(_ENGINE_FINANCIERO!J168/((_ENGINE_FINANCIERO!I181+_ENGINE_FINANCIERO!J181)/2),""),"") | K9: =IF(01_INPUTS!K17,IFERROR(_ENGINE_FINANCIERO!K168/((_ENGINE_FINANCIERO!J181+_ENGINE_FINANCIERO!K181)/2),""),"") | L9: =IF(01_INPUTS!L17,IFERROR(_ENGINE_FINANCIERO!L168/((_ENGINE_FINANCIERO!K181+_ENGINE_FINANCIERO!L181)/2),""),"") | M9: =IF(01_INPUTS!M17,IFERROR(_ENGINE_FINANCIERO!M168/((_ENGINE_FINANCIERO!L181+_ENGINE_FINANCIERO!M181)/2),""),"") | N9: =IF(01_INPUTS!N17,IFERROR(_ENGINE_FINANCIERO!N168/((_ENGINE_FINANCIERO!M181+_ENGINE_FINANCIERO!N181)/2),""),"") | O9: =IF(01_INPUTS!O17,IFERROR(_ENGINE_FINANCIERO!O168/((_ENGINE_FINANCIERO!N181+_ENGINE_FINANCIERO!O181)/2),""),"") | P9: =IF(01_INPUTS!P17,IFERROR(_ENGINE_FINANCIERO!P168/((_ENGINE_FINANCIERO!O181+_ENGINE_FINANCIERO!P181)/2),""),"") | ... S9: =IF(01_INPUTS!S17,IFERROR(_ENGINE_FINANCIERO!S168/((_ENGINE_FINANCIERO!R181+_ENGINE_FINANCIERO!S181)/2),""),"")
A10: ROCE — EBIT / Capital empleado promedio (apertura,cierre) | B10: % | G10: n/a (ver 02_ESTADOS_PROYECTADOS) | H10: n/a (ver 02_ESTADOS_PROYECTADOS) | I10: =IF(01_INPUTS!I17,IFERROR(_ENGINE_FINANCIERO!I164/(((_ENGINE_FINANCIERO!H182+_ENGINE_FINANCIERO!H183+_ENGINE_FINANCIERO!H181)+(_ENGINE_FINANCIERO!I182+_ENGINE_FINANCIERO!I183+_ENGINE_FINANCIERO!I181))/2),""),"") -> 0.61838392 | J10: =IF(01_INPUTS!J17,IFERROR(_ENGINE_FINANCIERO!J164/(((_ENGINE_FINANCIERO!I182+_ENGINE_FINANCIERO!I183+_ENGINE_FINANCIERO!I181)+(_ENGINE_FINANCIERO!J182+_ENGINE_FINANCIERO!J183+_ENGINE_FINANCIERO!J181))/2),""),"") | K10: =IF(01_INPUTS!K17,IFERROR(_ENGINE_FINANCIERO!K164/(((_ENGINE_FINANCIERO!J182+_ENGINE_FINANCIERO!J183+_ENGINE_FINANCIERO!J181)+(_ENGINE_FINANCIERO!K182+_ENGINE_FINANCIERO!K183+_ENGINE_FINANCIERO!K181))/2),""),"") | L10: =IF(01_INPUTS!L17,IFERROR(_ENGINE_FINANCIERO!L164/(((_ENGINE_FINANCIERO!K182+_ENGINE_FINANCIERO!K183+_ENGINE_FINANCIERO!K181)+(_ENGINE_FINANCIERO!L182+_ENGINE_FINANCIERO!L183+_ENGINE_FINANCIERO!L181))/2),""),"") | M10: =IF(01_INPUTS!M17,IFERROR(_ENGINE_FINANCIERO!M164/(((_ENGINE_FINANCIERO!L182+_ENGINE_FINANCIERO!L183+_ENGINE_FINANCIERO!L181)+(_ENGINE_FINANCIERO!M182+_ENGINE_FINANCIERO!M183+_ENGINE_FINANCIERO!M181))/2),""),"") | N10: =IF(01_INPUTS!N17,IFERROR(_ENGINE_FINANCIERO!N164/(((_ENGINE_FINANCIERO!M182+_ENGINE_FINANCIERO!M183+_ENGINE_FINANCIERO!M181)+(_ENGINE_FINANCIERO!N182+_ENGINE_FINANCIERO!N183+_ENGINE_FINANCIERO!N181))/2),""),"") | O10: =IF(01_INPUTS!O17,IFERROR(_ENGINE_FINANCIERO!O164/(((_ENGINE_FINANCIERO!N182+_ENGINE_FINANCIERO!N183+_ENGINE_FINANCIERO!N181)+(_ENGINE_FINANCIERO!O182+_ENGINE_FINANCIERO!O183+_ENGINE_FINANCIERO!O181))/2),""),"") | P10: =IF(01_INPUTS!P17,IFERROR(_ENGINE_FINANCIERO!P164/(((_ENGINE_FINANCIERO!O182+_ENGINE_FINANCIERO!O183+_ENGINE_FINANCIERO!O181)+(_ENGINE_FINANCIERO!P182+_ENGINE_FINANCIERO!P183+_ENGINE_FINANCIERO!P181))/2),""),"") | ... S10: =IF(01_INPUTS!S17,IFERROR(_ENGINE_FINANCIERO!S164/(((_ENGINE_FINANCIERO!R182+_ENGINE_FINANCIERO!R183+_ENGINE_FINANCIERO!R181)+(_ENGINE_FINANCIERO!S182+_ENGINE_FINANCIERO!S183+_ENGINE_FINANCIERO!S181))/2),""),"")
A11: WACC (proxy simplificado) | B11: % | G11: n/a (ver 02_ESTADOS_PROYECTADOS) | H11: n/a (ver 02_ESTADOS_PROYECTADOS) | I11: =IF(01_INPUTS!I17,IFERROR((_ENGINE_FINANCIERO!I181/(_ENGINE_FINANCIERO!I182+_ENGINE_FINANCIERO!I183+_ENGINE_FINANCIERO!I181))*0.12+((_ENGINE_FINANCIERO!I182+_ENGINE_FINANCIERO!I183)/(_ENGINE_FINANCIERO!I182+_ENGINE_FINANCIERO!I183+_ENGINE_FINANCIERO!I181))*01_INPUTS!I29*(1-01_INPUTS!I23),""),"") -> 0.0917563 | J11: =IF(01_INPUTS!J17,IFERROR((_ENGINE_FINANCIERO!J181/(_ENGINE_FINANCIERO!J182+_ENGINE_FINANCIERO!J183+_ENGINE_FINANCIERO!J181))*0.12+((_ENGINE_FINANCIERO!J182+_ENGINE_FINANCIERO!J183)/(_ENGINE_FINANCIERO!J182+_ENGINE_FINANCIERO!J183+_ENGINE_FINANCIERO!J181))*01_INPUTS!J29*(1-01_INPUTS!J23),""),"") | K11: =IF(01_INPUTS!K17,IFERROR((_ENGINE_FINANCIERO!K181/(_ENGINE_FINANCIERO!K182+_ENGINE_FINANCIERO!K183+_ENGINE_FINANCIERO!K181))*0.12+((_ENGINE_FINANCIERO!K182+_ENGINE_FINANCIERO!K183)/(_ENGINE_FINANCIERO!K182+_ENGINE_FINANCIERO!K183+_ENGINE_FINANCIERO!K181))*01_INPUTS!K29*(1-01_INPUTS!K23),""),"") | L11: =IF(01_INPUTS!L17,IFERROR((_ENGINE_FINANCIERO!L181/(_ENGINE_FINANCIERO!L182+_ENGINE_FINANCIERO!L183+_ENGINE_FINANCIERO!L181))*0.12+((_ENGINE_FINANCIERO!L182+_ENGINE_FINANCIERO!L183)/(_ENGINE_FINANCIERO!L182+_ENGINE_FINANCIERO!L183+_ENGINE_FINANCIERO!L181))*01_INPUTS!L29*(1-01_INPUTS!L23),""),"") | M11: =IF(01_INPUTS!M17,IFERROR((_ENGINE_FINANCIERO!M181/(_ENGINE_FINANCIERO!M182+_ENGINE_FINANCIERO!M183+_ENGINE_FINANCIERO!M181))*0.12+((_ENGINE_FINANCIERO!M182+_ENGINE_FINANCIERO!M183)/(_ENGINE_FINANCIERO!M182+_ENGINE_FINANCIERO!M183+_ENGINE_FINANCIERO!M181))*01_INPUTS!M29*(1-01_INPUTS!M23),""),"") | N11: =IF(01_INPUTS!N17,IFERROR((_ENGINE_FINANCIERO!N181/(_ENGINE_FINANCIERO!N182+_ENGINE_FINANCIERO!N183+_ENGINE_FINANCIERO!N181))*0.12+((_ENGINE_FINANCIERO!N182+_ENGINE_FINANCIERO!N183)/(_ENGINE_FINANCIERO!N182+_ENGINE_FINANCIERO!N183+_ENGINE_FINANCIERO!N181))*01_INPUTS!N29*(1-01_INPUTS!N23),""),"") | O11: =IF(01_INPUTS!O17,IFERROR((_ENGINE_FINANCIERO!O181/(_ENGINE_FINANCIERO!O182+_ENGINE_FINANCIERO!O183+_ENGINE_FINANCIERO!O181))*0.12+((_ENGINE_FINANCIERO!O182+_ENGINE_FINANCIERO!O183)/(_ENGINE_FINANCIERO!O182+_ENGINE_FINANCIERO!O183+_ENGINE_FINANCIERO!O181))*01_INPUTS!O29*(1-01_INPUTS!O23),""),"") | P11: =IF(01_INPUTS!P17,IFERROR((_ENGINE_FINANCIERO!P181/(_ENGINE_FINANCIERO!P182+_ENGINE_FINANCIERO!P183+_ENGINE_FINANCIERO!P181))*0.12+((_ENGINE_FINANCIERO!P182+_ENGINE_FINANCIERO!P183)/(_ENGINE_FINANCIERO!P182+_ENGINE_FINANCIERO!P183+_ENGINE_FINANCIERO!P181))*01_INPUTS!P29*(1-01_INPUTS!P23),""),"") | ... S11: =IF(01_INPUTS!S17,IFERROR((_ENGINE_FINANCIERO!S181/(_ENGINE_FINANCIERO!S182+_ENGINE_FINANCIERO!S183+_ENGINE_FINANCIERO!S181))*0.12+((_ENGINE_FINANCIERO!S182+_ENGINE_FINANCIERO!S183)/(_ENGINE_FINANCIERO!S182+_ENGINE_FINANCIERO!S183+_ENGINE_FINANCIERO!S181))*01_INPUTS!S29*(1-01_INPUTS!S23),""),"")
A12: ROCE − WACC (creación de valor) | B12: p.p. | G12: n/a (ver 02_ESTADOS_PROYECTADOS) | H12: n/a (ver 02_ESTADOS_PROYECTADOS) | I12: =IF(01_INPUTS!I17,IFERROR(I10-I11,""),"") -> 0.52662762 | J12: =IF(01_INPUTS!J17,IFERROR(J10-J11,""),"") | K12: =IF(01_INPUTS!K17,IFERROR(K10-K11,""),"") | L12: =IF(01_INPUTS!L17,IFERROR(L10-L11,""),"") | M12: =IF(01_INPUTS!M17,IFERROR(M10-M11,""),"") | N12: =IF(01_INPUTS!N17,IFERROR(N10-N11,""),"") | O12: =IF(01_INPUTS!O17,IFERROR(O10-O11,""),"") | P12: =IF(01_INPUTS!P17,IFERROR(P10-P11,""),"") | ... S12: =IF(01_INPUTS!S17,IFERROR(S10-S11,""),"")
A13: EPS — Beneficio neto / N° acciones | B13: USD/acción | G13: n/a (ver 02_ESTADOS_PROYECTADOS) | H13: n/a (ver 02_ESTADOS_PROYECTADOS) | I13: =IF(01_INPUTS!I17,IFERROR(_ENGINE_FINANCIERO!I168/(_ENGINE_FINANCIERO!I178),""),"") -> 8.3785023 | J13: =IF(01_INPUTS!J17,IFERROR(_ENGINE_FINANCIERO!J168/(_ENGINE_FINANCIERO!J178),""),"") | K13: =IF(01_INPUTS!K17,IFERROR(_ENGINE_FINANCIERO!K168/(_ENGINE_FINANCIERO!K178),""),"") | L13: =IF(01_INPUTS!L17,IFERROR(_ENGINE_FINANCIERO!L168/(_ENGINE_FINANCIERO!L178),""),"") | M13: =IF(01_INPUTS!M17,IFERROR(_ENGINE_FINANCIERO!M168/(_ENGINE_FINANCIERO!M178),""),"") | N13: =IF(01_INPUTS!N17,IFERROR(_ENGINE_FINANCIERO!N168/(_ENGINE_FINANCIERO!N178),""),"") | O13: =IF(01_INPUTS!O17,IFERROR(_ENGINE_FINANCIERO!O168/(_ENGINE_FINANCIERO!O178),""),"") | P13: =IF(01_INPUTS!P17,IFERROR(_ENGINE_FINANCIERO!P168/(_ENGINE_FINANCIERO!P178),""),"") | ... S13: =IF(01_INPUTS!S17,IFERROR(_ENGINE_FINANCIERO!S168/(_ENGINE_FINANCIERO!S178),""),"")
A14: CAJA Y DEUDA
A15: Flujo de caja libre (FCF) = CFO − CAPEX | B15: USD | G15: n/a (ver 02_ESTADOS_PROYECTADOS) | H15: n/a (ver 02_ESTADOS_PROYECTADOS) | I15: =IF(01_INPUTS!I17,_ENGINE_FINANCIERO!I190-(_ENGINE_PRODUCCION!I180+_ENGINE_PRODUCCION!I199),"") -> 2.1562266e+10 | J15: =IF(01_INPUTS!J17,_ENGINE_FINANCIERO!J190-(_ENGINE_PRODUCCION!J180+_ENGINE_PRODUCCION!J199),"") | K15: =IF(01_INPUTS!K17,_ENGINE_FINANCIERO!K190-(_ENGINE_PRODUCCION!K180+_ENGINE_PRODUCCION!K199),"") | L15: =IF(01_INPUTS!L17,_ENGINE_FINANCIERO!L190-(_ENGINE_PRODUCCION!L180+_ENGINE_PRODUCCION!L199),"") | M15: =IF(01_INPUTS!M17,_ENGINE_FINANCIERO!M190-(_ENGINE_PRODUCCION!M180+_ENGINE_PRODUCCION!M199),"") | N15: =IF(01_INPUTS!N17,_ENGINE_FINANCIERO!N190-(_ENGINE_PRODUCCION!N180+_ENGINE_PRODUCCION!N199),"") | O15: =IF(01_INPUTS!O17,_ENGINE_FINANCIERO!O190-(_ENGINE_PRODUCCION!O180+_ENGINE_PRODUCCION!O199),"") | P15: =IF(01_INPUTS!P17,_ENGINE_FINANCIERO!P190-(_ENGINE_PRODUCCION!P180+_ENGINE_PRODUCCION!P199),"") | ... S15: =IF(01_INPUTS!S17,_ENGINE_FINANCIERO!S190-(_ENGINE_PRODUCCION!S180+_ENGINE_PRODUCCION!S199),"")
A16: Deuda financiera total (LP+CP) | B16: USD | G16: =_ENGINE_FINANCIERO!G182+_ENGINE_FINANCIERO!G183 -> 11900000000 | H16: =_ENGINE_FINANCIERO!H182+_ENGINE_FINANCIERO!H183 -> 11900000000 | I16: =IF(01_INPUTS!I17,_ENGINE_FINANCIERO!I182+_ENGINE_FINANCIERO!I183,"") -> 11900000000 | J16: =IF(01_INPUTS!J17,_ENGINE_FINANCIERO!J182+_ENGINE_FINANCIERO!J183,"") | K16: =IF(01_INPUTS!K17,_ENGINE_FINANCIERO!K182+_ENGINE_FINANCIERO!K183,"") | L16: =IF(01_INPUTS!L17,_ENGINE_FINANCIERO!L182+_ENGINE_FINANCIERO!L183,"") | M16: =IF(01_INPUTS!M17,_ENGINE_FINANCIERO!M182+_ENGINE_FINANCIERO!M183,"") | N16: =IF(01_INPUTS!N17,_ENGINE_FINANCIERO!N182+_ENGINE_FINANCIERO!N183,"") | O16: =IF(01_INPUTS!O17,_ENGINE_FINANCIERO!O182+_ENGINE_FINANCIERO!O183,"") | P16: =IF(01_INPUTS!P17,_ENGINE_FINANCIERO!P182+_ENGINE_FINANCIERO!P183,"") | ... S16: =IF(01_INPUTS!S17,_ENGINE_FINANCIERO!S182+_ENGINE_FINANCIERO!S183,"")
A17: Deuda financiera / Patrimonio | B17: x | G17: =IFERROR((_ENGINE_FINANCIERO!G182+_ENGINE_FINANCIERO!G183)/_ENGINE_FINANCIERO!G181,"") -> 1.1895763 | H17: =IFERROR((_ENGINE_FINANCIERO!H182+_ENGINE_FINANCIERO!H183)/_ENGINE_FINANCIERO!H181,"") -> 1.0247226 | I17: =IF(01_INPUTS!I17,IFERROR((_ENGINE_FINANCIERO!I182+_ENGINE_FINANCIERO!I183)/_ENGINE_FINANCIERO!I181,""),"") -> 0.53536166 | J17: =IF(01_INPUTS!J17,IFERROR((_ENGINE_FINANCIERO!J182+_ENGINE_FINANCIERO!J183)/_ENGINE_FINANCIERO!J181,""),"") | K17: =IF(01_INPUTS!K17,IFERROR((_ENGINE_FINANCIERO!K182+_ENGINE_FINANCIERO!K183)/_ENGINE_FINANCIERO!K181,""),"") | L17: =IF(01_INPUTS!L17,IFERROR((_ENGINE_FINANCIERO!L182+_ENGINE_FINANCIERO!L183)/_ENGINE_FINANCIERO!L181,""),"") | M17: =IF(01_INPUTS!M17,IFERROR((_ENGINE_FINANCIERO!M182+_ENGINE_FINANCIERO!M183)/_ENGINE_FINANCIERO!M181,""),"") | N17: =IF(01_INPUTS!N17,IFERROR((_ENGINE_FINANCIERO!N182+_ENGINE_FINANCIERO!N183)/_ENGINE_FINANCIERO!N181,""),"") | O17: =IF(01_INPUTS!O17,IFERROR((_ENGINE_FINANCIERO!O182+_ENGINE_FINANCIERO!O183)/_ENGINE_FINANCIERO!O181,""),"") | P17: =IF(01_INPUTS!P17,IFERROR((_ENGINE_FINANCIERO!P182+_ENGINE_FINANCIERO!P183)/_ENGINE_FINANCIERO!P181,""),"") | ... S17: =IF(01_INPUTS!S17,IFERROR((_ENGINE_FINANCIERO!S182+_ENGINE_FINANCIERO!S183)/_ENGINE_FINANCIERO!S181,""),"")
A18: Payout ratio = Dividendos / Beneficio neto | B18: % | G18: n/a (ver 02_ESTADOS_PROYECTADOS) | H18: n/a (ver 02_ESTADOS_PROYECTADOS) | I18: =IF(01_INPUTS!I17,IFERROR(IF(ISNUMBER(01_INPUTS!I270),01_INPUTS!I270,0)/_ENGINE_FINANCIERO!I168,""),"") -> 0.22034414 | J18: =IF(01_INPUTS!J17,IFERROR(IF(ISNUMBER(01_INPUTS!J270),01_INPUTS!J270,0)/_ENGINE_FINANCIERO!J168,""),"") | K18: =IF(01_INPUTS!K17,IFERROR(IF(ISNUMBER(01_INPUTS!K270),01_INPUTS!K270,0)/_ENGINE_FINANCIERO!K168,""),"") | L18: =IF(01_INPUTS!L17,IFERROR(IF(ISNUMBER(01_INPUTS!L270),01_INPUTS!L270,0)/_ENGINE_FINANCIERO!L168,""),"") | M18: =IF(01_INPUTS!M17,IFERROR(IF(ISNUMBER(01_INPUTS!M270),01_INPUTS!M270,0)/_ENGINE_FINANCIERO!M168,""),"") | N18: =IF(01_INPUTS!N17,IFERROR(IF(ISNUMBER(01_INPUTS!N270),01_INPUTS!N270,0)/_ENGINE_FINANCIERO!N168,""),"") | O18: =IF(01_INPUTS!O17,IFERROR(IF(ISNUMBER(01_INPUTS!O270),01_INPUTS!O270,0)/_ENGINE_FINANCIERO!O168,""),"") | P18: =IF(01_INPUTS!P17,IFERROR(IF(ISNUMBER(01_INPUTS!P270),01_INPUTS!P270,0)/_ENGINE_FINANCIERO!P168,""),"") | ... S18: =IF(01_INPUTS!S17,IFERROR(IF(ISNUMBER(01_INPUTS!S270),01_INPUTS!S270,0)/_ENGINE_FINANCIERO!S168,""),"")
A19: VALUACIÓN (PROXY — no es una predicción del algoritmo real de CESIM)
A20: Precio de acción de referencia (Condición, PROXY) | B20: USD | G20: =01_INPUTS!G61 -> 33.59236 | H20: =01_INPUTS!H61 -> 38.651795 | I20: =IF(01_INPUTS!I17,01_INPUTS!I61,"") -> 38.651795 | J20: =IF(01_INPUTS!J17,01_INPUTS!J61,"") | K20: =IF(01_INPUTS!K17,01_INPUTS!K61,"") | L20: =IF(01_INPUTS!L17,01_INPUTS!L61,"") | M20: =IF(01_INPUTS!M17,01_INPUTS!M61,"") | N20: =IF(01_INPUTS!N17,01_INPUTS!N61,"") | O20: =IF(01_INPUTS!O17,01_INPUTS!O61,"") | P20: =IF(01_INPUTS!P17,01_INPUTS!P61,"") | ... S20: =IF(01_INPUTS!S17,01_INPUTS!S61,"")
A21: P/E proxy = Precio referencia / EPS [PROXY] | B21: x | G21: n/a (ver 02_ESTADOS_PROYECTADOS) | H21: n/a (ver 02_ESTADOS_PROYECTADOS) | I21: =IF(01_INPUTS!I17,IFERROR(01_INPUTS!I61/I13,""),"") -> 4.6132105 | J21: =IF(01_INPUTS!J17,IFERROR(01_INPUTS!J61/J13,""),"") | K21: =IF(01_INPUTS!K17,IFERROR(01_INPUTS!K61/K13,""),"") | L21: =IF(01_INPUTS!L17,IFERROR(01_INPUTS!L61/L13,""),"") | M21: =IF(01_INPUTS!M17,IFERROR(01_INPUTS!M61/M13,""),"") | N21: =IF(01_INPUTS!N17,IFERROR(01_INPUTS!N61/N13,""),"") | O21: =IF(01_INPUTS!O17,IFERROR(01_INPUTS!O61/O13,""),"") | P21: =IF(01_INPUTS!P17,IFERROR(01_INPUTS!P61/P13,""),"") | ... S21: =IF(01_INPUTS!S17,IFERROR(01_INPUTS!S61/S13,""),"")
A22: Dividend yield proxy = Dividendo por acción / Precio [PROXY] | B22: % | G22: n/a (ver 02_ESTADOS_PROYECTADOS) | H22: n/a (ver 02_ESTADOS_PROYECTADOS) | I22: =IF(01_INPUTS!I17,IFERROR((IF(ISNUMBER(01_INPUTS!I270),01_INPUTS!I270,0)/(_ENGINE_FINANCIERO!I178))/01_INPUTS!I61,""),"") -> 0.047763729 | J22: =IF(01_INPUTS!J17,IFERROR((IF(ISNUMBER(01_INPUTS!J270),01_INPUTS!J270,0)/(_ENGINE_FINANCIERO!J178))/01_INPUTS!J61,""),"") | K22: =IF(01_INPUTS!K17,IFERROR((IF(ISNUMBER(01_INPUTS!K270),01_INPUTS!K270,0)/(_ENGINE_FINANCIERO!K178))/01_INPUTS!K61,""),"") | L22: =IF(01_INPUTS!L17,IFERROR((IF(ISNUMBER(01_INPUTS!L270),01_INPUTS!L270,0)/(_ENGINE_FINANCIERO!L178))/01_INPUTS!L61,""),"") | M22: =IF(01_INPUTS!M17,IFERROR((IF(ISNUMBER(01_INPUTS!M270),01_INPUTS!M270,0)/(_ENGINE_FINANCIERO!M178))/01_INPUTS!M61,""),"") | N22: =IF(01_INPUTS!N17,IFERROR((IF(ISNUMBER(01_INPUTS!N270),01_INPUTS!N270,0)/(_ENGINE_FINANCIERO!N178))/01_INPUTS!N61,""),"") | O22: =IF(01_INPUTS!O17,IFERROR((IF(ISNUMBER(01_INPUTS!O270),01_INPUTS!O270,0)/(_ENGINE_FINANCIERO!O178))/01_INPUTS!O61,""),"") | P22: =IF(01_INPUTS!P17,IFERROR((IF(ISNUMBER(01_INPUTS!P270),01_INPUTS!P270,0)/(_ENGINE_FINANCIERO!P178))/01_INPUTS!P61,""),"") | ... S22: =IF(01_INPUTS!S17,IFERROR((IF(ISNUMBER(01_INPUTS!S270),01_INPUTS!S270,0)/(_ENGINE_FINANCIERO!S178))/01_INPUTS!S61,""),"")
A23: Retorno del accionista del período (PROXY) = ΔPrecio referencia × (1+Dividend yield) [PROXY] | B23: % | G23: n/a (Ronda 0, sin ronda anterior) | H23: 0.18725103 | I23: =IF(01_INPUTS!I17,IFERROR((01_INPUTS!I61/01_INPUTS!H61)*(1+I22)-1,""),"") -> 0.047763729 | J23: =IF(01_INPUTS!J17,IFERROR((01_INPUTS!J61/01_INPUTS!I61)*(1+J22)-1,""),"") | K23: =IF(01_INPUTS!K17,IFERROR((01_INPUTS!K61/01_INPUTS!J61)*(1+K22)-1,""),"") | L23: =IF(01_INPUTS!L17,IFERROR((01_INPUTS!L61/01_INPUTS!K61)*(1+L22)-1,""),"") | M23: =IF(01_INPUTS!M17,IFERROR((01_INPUTS!M61/01_INPUTS!L61)*(1+M22)-1,""),"") | N23: =IF(01_INPUTS!N17,IFERROR((01_INPUTS!N61/01_INPUTS!M61)*(1+N22)-1,""),"") | O23: =IF(01_INPUTS!O17,IFERROR((01_INPUTS!O61/01_INPUTS!N61)*(1+O22)-1,""),"") | P23: =IF(01_INPUTS!P17,IFERROR((01_INPUTS!P61/01_INPUTS!O61)*(1+P22)-1,""),"") | ... S23: =IF(01_INPUTS!S17,IFERROR((01_INPUTS!S61/01_INPUTS!R61)*(1+S22)-1,""),"")
A24: Índice acumulado del accionista (PROXY, base Ronda 0 = 1,00) [memo] | B24: x | G24: 1 | H24: =G24*(1+H23) -> 1.187251 | I24: =IF(01_INPUTS!I17,H24*(1+I23),"") -> 1.2439586 | J24: =IF(01_INPUTS!J17,I24*(1+J23),"") | K24: =IF(01_INPUTS!K17,J24*(1+K23),"") | L24: =IF(01_INPUTS!L17,K24*(1+L23),"") | M24: =IF(01_INPUTS!M17,L24*(1+M23),"") | N24: =IF(01_INPUTS!N17,M24*(1+N23),"") | O24: =IF(01_INPUTS!O17,N24*(1+O23),"") | P24: =IF(01_INPUTS!P17,O24*(1+P23),"") | ... S24: =IF(01_INPUTS!S17,R24*(1+S23),"")
A25: Retorno total acumulado del accionista (PROXY, anualizado desde R0) [PROXY] | B25: % | G25: n/a (Ronda 0, sin ronda anterior) | H25: =IFERROR(H24^(1/1)-1,"") -> 0.18725103 | I25: =IF(01_INPUTS!I17,IFERROR(I24^(1/2)-1,""),"") -> 0.1153289 | J25: =IF(01_INPUTS!J17,IFERROR(J24^(1/3)-1,""),"") | K25: =IF(01_INPUTS!K17,IFERROR(K24^(1/4)-1,""),"") | L25: =IF(01_INPUTS!L17,IFERROR(L24^(1/5)-1,""),"") | M25: =IF(01_INPUTS!M17,IFERROR(M24^(1/6)-1,""),"") | N25: =IF(01_INPUTS!N17,IFERROR(N24^(1/7)-1,""),"") | O25: =IF(01_INPUTS!O17,IFERROR(O24^(1/8)-1,""),"") | P25: =IF(01_INPUTS!P17,IFERROR(P24^(1/9)-1,""),"") | Q25: =IF(01_INPUTS!Q17,IFERROR(Q24^(1/10)-1,""),"") | R25: =IF(01_INPUTS!R17,IFERROR(R24^(1/11)-1,""),"") | S25: =IF(01_INPUTS!S17,IFERROR(S24^(1/12)-1,""),"")
A26: OPERATIVO — CAPACIDAD, INVENTARIO, DEMANDA
A27: Utilización de capacidad — EE.UU. | B27: % | G27: =_ENGINE_PRODUCCION!G18 -> 0.7 | H27: =_ENGINE_PRODUCCION!H18 -> 0.68 | I27: =IF(01_INPUTS!I17,_ENGINE_PRODUCCION!I18,"") -> 0.9 | J27: =IF(01_INPUTS!J17,_ENGINE_PRODUCCION!J18,"") | K27: =IF(01_INPUTS!K17,_ENGINE_PRODUCCION!K18,"") | L27: =IF(01_INPUTS!L17,_ENGINE_PRODUCCION!L18,"") | M27: =IF(01_INPUTS!M17,_ENGINE_PRODUCCION!M18,"") | N27: =IF(01_INPUTS!N17,_ENGINE_PRODUCCION!N18,"") | O27: =IF(01_INPUTS!O17,_ENGINE_PRODUCCION!O18,"") | P27: =IF(01_INPUTS!P17,_ENGINE_PRODUCCION!P18,"") | ... S27: =IF(01_INPUTS!S17,_ENGINE_PRODUCCION!S18,"")
A28: Utilización de capacidad — China | B28: % | G28: =_ENGINE_PRODUCCION!G27 -> 0.8 | H28: =_ENGINE_PRODUCCION!H27 -> 0.68 | I28: =IF(01_INPUTS!I17,_ENGINE_PRODUCCION!I27,"") -> 0.9 | J28: =IF(01_INPUTS!J17,_ENGINE_PRODUCCION!J27,"") | K28: =IF(01_INPUTS!K17,_ENGINE_PRODUCCION!K27,"") | L28: =IF(01_INPUTS!L17,_ENGINE_PRODUCCION!L27,"") | M28: =IF(01_INPUTS!M17,_ENGINE_PRODUCCION!M27,"") | N28: =IF(01_INPUTS!N17,_ENGINE_PRODUCCION!N27,"") | O28: =IF(01_INPUTS!O17,_ENGINE_PRODUCCION!O27,"") | P28: =IF(01_INPUTS!P17,_ENGINE_PRODUCCION!P27,"") | ... S28: =IF(01_INPUTS!S17,_ENGINE_PRODUCCION!S27,"")
A29: Demanda insatisfecha CADIZ (total, todas tech/mercados) | B29: u. | G29: =_ENGINE_MERCADO!G191+_ENGINE_MERCADO!G196+_ENGINE_MERCADO!G201+_ENGINE_MERCADO!G206+_ENGINE_MERCADO!G211+_ENGINE_MERCADO!G216+_ENGINE_MERCADO!G221+_ENGINE_MERCADO!G226+_ENGINE_MERCADO!G231+_ENGINE_MERCADO!G236+_ENGINE_MERCADO!G241+_ENGINE_MERCADO!G246 -> 2185000 | H29: =_ENGINE_MERCADO!H191+_ENGINE_MERCADO!H196+_ENGINE_MERCADO!H201+_ENGINE_MERCADO!H206+_ENGINE_MERCADO!H211+_ENGINE_MERCADO!H216+_ENGINE_MERCADO!H221+_ENGINE_MERCADO!H226+_ENGINE_MERCADO!H231+_ENGINE_MERCADO!H236+_ENGINE_MERCADO!H241+_ENGINE_MERCADO!H246 -> 2909858 | I29: =IF(01_INPUTS!I17,_ENGINE_MERCADO!I191+_ENGINE_MERCADO!I196+_ENGINE_MERCADO!I201+_ENGINE_MERCADO!I206+_ENGINE_MERCADO!I211+_ENGINE_MERCADO!I216+_ENGINE_MERCADO!I221+_ENGINE_MERCADO!I226+_ENGINE_MERCADO!I231+_ENGINE_MERCADO!I236+_ENGINE_MERCADO!I241+_ENGINE_MERCADO!I246,"") -> 0 | J29: =IF(01_INPUTS!J17,_ENGINE_MERCADO!J191+_ENGINE_MERCADO!J196+_ENGINE_MERCADO!J201+_ENGINE_MERCADO!J206+_ENGINE_MERCADO!J211+_ENGINE_MERCADO!J216+_ENGINE_MERCADO!J221+_ENGINE_MERCADO!J226+_ENGINE_MERCADO!J231+_ENGINE_MERCADO!J236+_ENGINE_MERCADO!J241+_ENGINE_MERCADO!J246,"") | K29: =IF(01_INPUTS!K17,_ENGINE_MERCADO!K191+_ENGINE_MERCADO!K196+_ENGINE_MERCADO!K201+_ENGINE_MERCADO!K206+_ENGINE_MERCADO!K211+_ENGINE_MERCADO!K216+_ENGINE_MERCADO!K221+_ENGINE_MERCADO!K226+_ENGINE_MERCADO!K231+_ENGINE_MERCADO!K236+_ENGINE_MERCADO!K241+_ENGINE_MERCADO!K246,"") | L29: =IF(01_INPUTS!L17,_ENGINE_MERCADO!L191+_ENGINE_MERCADO!L196+_ENGINE_MERCADO!L201+_ENGINE_MERCADO!L206+_ENGINE_MERCADO!L211+_ENGINE_MERCADO!L216+_ENGINE_MERCADO!L221+_ENGINE_MERCADO!L226+_ENGINE_MERCADO!L231+_ENGINE_MERCADO!L236+_ENGINE_MERCADO!L241+_ENGINE_MERCADO!L246,"") | M29: =IF(01_INPUTS!M17,_ENGINE_MERCADO!M191+_ENGINE_MERCADO!M196+_ENGINE_MERCADO!M201+_ENGINE_MERCADO!M206+_ENGINE_MERCADO!M211+_ENGINE_MERCADO!M216+_ENGINE_MERCADO!M221+_ENGINE_MERCADO!M226+_ENGINE_MERCADO!M231+_ENGINE_MERCADO!M236+_ENGINE_MERCADO!M241+_ENGINE_MERCADO!M246,"") | N29: =IF(01_INPUTS!N17,_ENGINE_MERCADO!N191+_ENGINE_MERCADO!N196+_ENGINE_MERCADO!N201+_ENGINE_MERCADO!N206+_ENGINE_MERCADO!N211+_ENGINE_MERCADO!N216+_ENGINE_MERCADO!N221+_ENGINE_MERCADO!N226+_ENGINE_MERCADO!N231+_ENGINE_MERCADO!N236+_ENGINE_MERCADO!N241+_ENGINE_MERCADO!N246,"") | O29: =IF(01_INPUTS!O17,_ENGINE_MERCADO!O191+_ENGINE_MERCADO!O196+_ENGINE_MERCADO!O201+_ENGINE_MERCADO!O206+_ENGINE_MERCADO!O211+_ENGINE_MERCADO!O216+_ENGINE_MERCADO!O221+_ENGINE_MERCADO!O226+_ENGINE_MERCADO!O231+_ENGINE_MERCADO!O236+_ENGINE_MERCADO!O241+_ENGINE_MERCADO!O246,"") | P29: =IF(01_INPUTS!P17,_ENGINE_MERCADO!P191+_ENGINE_MERCADO!P196+_ENGINE_MERCADO!P201+_ENGINE_MERCADO!P206+_ENGINE_MERCADO!P211+_ENGINE_MERCADO!P216+_ENGINE_MERCADO!P221+_ENGINE_MERCADO!P226+_ENGINE_MERCADO!P231+_ENGINE_MERCADO!P236+_ENGINE_MERCADO!P241+_ENGINE_MERCADO!P246,"") | ... S29: =IF(01_INPUTS!S17,_ENGINE_MERCADO!S191+_ENGINE_MERCADO!S196+_ENGINE_MERCADO!S201+_ENGINE_MERCADO!S206+_ENGINE_MERCADO!S211+_ENGINE_MERCADO!S216+_ENGINE_MERCADO!S221+_ENGINE_MERCADO!S226+_ENGINE_MERCADO!S231+_ENGINE_MERCADO!S236+_ENGINE_MERCADO!S241+_ENGINE_MERCADO!S246,"")
A30: Cuota de mercado CADIZ (ponderada por volumen, 3 mercados) | B30: % | G30: =IF((IF(ISNUMBER(01_INPUTS!G124),1,0)+IF(ISNUMBER(01_INPUTS!G125),1,0)+IF(ISNUMBER(01_INPUTS!G126),1,0)+IF(ISNUMBER(01_INPUTS!G127),1,0)+IF(ISNUMBER(01_INPUTS!G128),1,0)+IF(ISNUMBER(01_INPUTS!G129),1,0)+IF(ISNUMBER(01_INPUTS!G130),1,0)+IF(ISNUMBER(01_INPUTS!G131),1,0)+IF(ISNUMBER(01_INPUTS!G132),1,0)+IF(ISNUMBER(01_INPUTS!G133),1,0)+IF(ISNUMBER(01_INPUTS!G134),1,0)+IF(ISNUMBER(01_INPUTS!G135),1,0))=0,"",IFERROR(((IF(ISNUMBER(01_INPUTS!G124),01_INPUTS!G124,0)+IF(ISNUMBER(01_INPUTS!G125),01_INPUTS!G125,0)+IF(ISNUMBER(01_INPUTS!G126),01_INPUTS!G126,0)+IF(ISNUMBER(01_INPUTS!G127),01_INPUTS!G127,0))*_ENGINE_MERCADO!G6+(IF(ISNUMBER(01_INPUTS!G128),01_INPUTS!G128,0)+IF(ISNUMBER(01_INPUTS!G129),01_INPUTS!G129,0)+IF(ISNUMBER(01_INPUTS!G130),01_INPUTS!G130,0)+IF(ISNUMBER(01_INPUTS!G131),01_INPUTS!G131,0))*_ENGINE_MERCADO!G8+(IF(ISNUMBER(01_INPUTS!G132),01_INPUTS!G132,0)+IF(ISNUMBER(01_INPUTS!G133),01_INPUTS!G133,0)+IF(ISNUMBER(01_INPUTS!G134),01_INPUTS!G134,0)+IF(ISNUMBER(01_INPUTS!G135),01_INPUTS!G135,0))*_ENGINE_MERCADO!G10)/(_ENGINE_MERCADO!G6+_ENGINE_MERCADO!G8+_ENGINE_MERCADO!G10),"")) | H30: =IF((IF(ISNUMBER(01_INPUTS!H124),1,0)+IF(ISNUMBER(01_INPUTS!H125),1,0)+IF(ISNUMBER(01_INPUTS!H126),1,0)+IF(ISNUMBER(01_INPUTS!H127),1,0)+IF(ISNUMBER(01_INPUTS!H128),1,0)+IF(ISNUMBER(01_INPUTS!H129),1,0)+IF(ISNUMBER(01_INPUTS!H130),1,0)+IF(ISNUMBER(01_INPUTS!H131),1,0)+IF(ISNUMBER(01_INPUTS!H132),1,0)+IF(ISNUMBER(01_INPUTS!H133),1,0)+IF(ISNUMBER(01_INPUTS!H134),1,0)+IF(ISNUMBER(01_INPUTS!H135),1,0))=0,"",IFERROR(((IF(ISNUMBER(01_INPUTS!H124),01_INPUTS!H124,0)+IF(ISNUMBER(01_INPUTS!H125),01_INPUTS!H125,0)+IF(ISNUMBER(01_INPUTS!H126),01_INPUTS!H126,0)+IF(ISNUMBER(01_INPUTS!H127),01_INPUTS!H127,0))*_ENGINE_MERCADO!H6+(IF(ISNUMBER(01_INPUTS!H128),01_INPUTS!H128,0)+IF(ISNUMBER(01_INPUTS!H129),01_INPUTS!H129,0)+IF(ISNUMBER(01_INPUTS!H130),01_INPUTS!H130,0)+IF(ISNUMBER(01_INPUTS!H131),01_INPUTS!H131,0))*_ENGINE_MERCADO!H8+(IF(ISNUMBER(01_INPUTS!H132),01_INPUTS!H132,0)+IF(ISNUMBER(01_INPUTS!H133),01_INPUTS!H133,0)+IF(ISNUMBER(01_INPUTS!H134),01_INPUTS!H134,0)+IF(ISNUMBER(01_INPUTS!H135),01_INPUTS!H135,0))*_ENGINE_MERCADO!H10)/(_ENGINE_MERCADO!H6+_ENGINE_MERCADO!H8+_ENGINE_MERCADO!H10),"")) | I30: =IF(01_INPUTS!I17,IF((IF(ISNUMBER(01_INPUTS!I124),1,0)+IF(ISNUMBER(01_INPUTS!I125),1,0)+IF(ISNUMBER(01_INPUTS!I126),1,0)+IF(ISNUMBER(01_INPUTS!I127),1,0)+IF(ISNUMBER(01_INPUTS!I128),1,0)+IF(ISNUMBER(01_INPUTS!I129),1,0)+IF(ISNUMBER(01_INPUTS!I130),1,0)+IF(ISNUMBER(01_INPUTS!I131),1,0)+IF(ISNUMBER(01_INPUTS!I132),1,0)+IF(ISNUMBER(01_INPUTS!I133),1,0)+IF(ISNUMBER(01_INPUTS!I134),1,0)+IF(ISNUMBER(01_INPUTS!I135),1,0))=0,"",IFERROR(((IF(ISNUMBER(01_INPUTS!I124),01_INPUTS!I124,0)+IF(ISNUMBER(01_INPUTS!I125),01_INPUTS!I125,0)+IF(ISNUMBER(01_INPUTS!I126),01_INPUTS!I126,0)+IF(ISNUMBER(01_INPUTS!I127),01_INPUTS!I127,0))*_ENGINE_MERCADO!I6+(IF(ISNUMBER(01_INPUTS!I128),01_INPUTS!I128,0)+IF(ISNUMBER(01_INPUTS!I129),01_INPUTS!I129,0)+IF(ISNUMBER(01_INPUTS!I130),01_INPUTS!I130,0)+IF(ISNUMBER(01_INPUTS!I131),01_INPUTS!I131,0))*_ENGINE_MERCADO!I8+(IF(ISNUMBER(01_INPUTS!I132),01_INPUTS!I132,0)+IF(ISNUMBER(01_INPUTS!I133),01_INPUTS!I133,0)+IF(ISNUMBER(01_INPUTS!I134),01_INPUTS!I134,0)+IF(ISNUMBER(01_INPUTS!I135),01_INPUTS!I135,0))*_ENGINE_MERCADO!I10)/(_ENGINE_MERCADO!I6+_ENGINE_MERCADO!I8+_ENGINE_MERCADO!I10),"")),"") -> 0.17945545 | J30: =IF(01_INPUTS!J17,IF((IF(ISNUMBER(01_INPUTS!J124),1,0)+IF(ISNUMBER(01_INPUTS!J125),1,0)+IF(ISNUMBER(01_INPUTS!J126),1,0)+IF(ISNUMBER(01_INPUTS!J127),1,0)+IF(ISNUMBER(01_INPUTS!J128),1,0)+IF(ISNUMBER(01_INPUTS!J129),1,0)+IF(ISNUMBER(01_INPUTS!J130),1,0)+IF(ISNUMBER(01_INPUTS!J131),1,0)+IF(ISNUMBER(01_INPUTS!J132),1,0)+IF(ISNUMBER(01_INPUTS!J133),1,0)+IF(ISNUMBER(01_INPUTS!J134),1,0)+IF(ISNUMBER(01_INPUTS!J135),1,0))=0,"",IFERROR(((IF(ISNUMBER(01_INPUTS!J124),01_INPUTS!J124,0)+IF(ISNUMBER(01_INPUTS!J125),01_INPUTS!J125,0)+IF(ISNUMBER(01_INPUTS!J126),01_INPUTS!J126,0)+IF(ISNUMBER(01_INPUTS!J127),01_INPUTS!J127,0))*_ENGINE_MERCADO!J6+(IF(ISNUMBER(01_INPUTS!J128),01_INPUTS!J128,0)+IF(ISNUMBER(01_INPUTS!J129),01_INPUTS!J129,0)+IF(ISNUMBER(01_INPUTS!J130),01_INPUTS!J130,0)+IF(ISNUMBER(01_INPUTS!J131),01_INPUTS!J131,0))*_ENGINE_MERCADO!J8+(IF(ISNUMBER(01_INPUTS!J132),01_INPUTS!J132,0)+IF(ISNUMBER(01_INPUTS!J133),01_INPUTS!J133,0)+IF(ISNUMBER(01_INPUTS!J134),01_INPUTS!J134,0)+IF(ISNUMBER(01_INPUTS!J135),01_INPUTS!J135,0))*_ENGINE_MERCADO!J10)/(_ENGINE_MERCADO!J6+_ENGINE_MERCADO!J8+_ENGINE_MERCADO!J10),"")),"") | K30: =IF(01_INPUTS!K17,IF((IF(ISNUMBER(01_INPUTS!K124),1,0)+IF(ISNUMBER(01_INPUTS!K125),1,0)+IF(ISNUMBER(01_INPUTS!K126),1,0)+IF(ISNUMBER(01_INPUTS!K127),1,0)+IF(ISNUMBER(01_INPUTS!K128),1,0)+IF(ISNUMBER(01_INPUTS!K129),1,0)+IF(ISNUMBER(01_INPUTS!K130),1,0)+IF(ISNUMBER(01_INPUTS!K131),1,0)+IF(ISNUMBER(01_INPUTS!K132),1,0)+IF(ISNUMBER(01_INPUTS!K133),1,0)+IF(ISNUMBER(01_INPUTS!K134),1,0)+IF(ISNUMBER(01_INPUTS!K135),1,0))=0,"",IFERROR(((IF(ISNUMBER(01_INPUTS!K124),01_INPUTS!K124,0)+IF(ISNUMBER(01_INPUTS!K125),01_INPUTS!K125,0)+IF(ISNUMBER(01_INPUTS!K126),01_INPUTS!K126,0)+IF(ISNUMBER(01_INPUTS!K127),01_INPUTS!K127,0))*_ENGINE_MERCADO!K6+(IF(ISNUMBER(01_INPUTS!K128),01_INPUTS!K128,0)+IF(ISNUMBER(01_INPUTS!K129),01_INPUTS!K129,0)+IF(ISNUMBER(01_INPUTS!K130),01_INPUTS!K130,0)+IF(ISNUMBER(01_INPUTS!K131),01_INPUTS!K131,0))*_ENGINE_MERCADO!K8+(IF(ISNUMBER(01_INPUTS!K132),01_INPUTS!K132,0)+IF(ISNUMBER(01_INPUTS!K133),01_INPUTS!K133,0)+IF(ISNUMBER(01_INPUTS!K134),01_INPUTS!K134,0)+IF(ISNUMBER(01_INPUTS!K135),01_INPUTS!K135,0))*_ENGINE_MERCADO!K10)/(_ENGINE_MERCADO!K6+_ENGINE_MERCADO!K8+_ENGINE_MERCADO!K10),"")),"") | L30: =IF(01_INPUTS!L17,IF((IF(ISNUMBER(01_INPUTS!L124),1,0)+IF(ISNUMBER(01_INPUTS!L125),1,0)+IF(ISNUMBER(01_INPUTS!L126),1,0)+IF(ISNUMBER(01_INPUTS!L127),1,0)+IF(ISNUMBER(01_INPUTS!L128),1,0)+IF(ISNUMBER(01_INPUTS!L129),1,0)+IF(ISNUMBER(01_INPUTS!L130),1,0)+IF(ISNUMBER(01_INPUTS!L131),1,0)+IF(ISNUMBER(01_INPUTS!L132),1,0)+IF(ISNUMBER(01_INPUTS!L133),1,0)+IF(ISNUMBER(01_INPUTS!L134),1,0)+IF(ISNUMBER(01_INPUTS!L135),1,0))=0,"",IFERROR(((IF(ISNUMBER(01_INPUTS!L124),01_INPUTS!L124,0)+IF(ISNUMBER(01_INPUTS!L125),01_INPUTS!L125,0)+IF(ISNUMBER(01_INPUTS!L126),01_INPUTS!L126,0)+IF(ISNUMBER(01_INPUTS!L127),01_INPUTS!L127,0))*_ENGINE_MERCADO!L6+(IF(ISNUMBER(01_INPUTS!L128),01_INPUTS!L128,0)+IF(ISNUMBER(01_INPUTS!L129),01_INPUTS!L129,0)+IF(ISNUMBER(01_INPUTS!L130),01_INPUTS!L130,0)+IF(ISNUMBER(01_INPUTS!L131),01_INPUTS!L131,0))*_ENGINE_MERCADO!L8+(IF(ISNUMBER(01_INPUTS!L132),01_INPUTS!L132,0)+IF(ISNUMBER(01_INPUTS!L133),01_INPUTS!L133,0)+IF(ISNUMBER(01_INPUTS!L134),01_INPUTS!L134,0)+IF(ISNUMBER(01_INPUTS!L135),01_INPUTS!L135,0))*_ENGINE_MERCADO!L10)/(_ENGINE_MERCADO!L6+_ENGINE_MERCADO!L8+_ENGINE_MERCADO!L10),"")),"") | M30: =IF(01_INPUTS!M17,IF((IF(ISNUMBER(01_INPUTS!M124),1,0)+IF(ISNUMBER(01_INPUTS!M125),1,0)+IF(ISNUMBER(01_INPUTS!M126),1,0)+IF(ISNUMBER(01_INPUTS!M127),1,0)+IF(ISNUMBER(01_INPUTS!M128),1,0)+IF(ISNUMBER(01_INPUTS!M129),1,0)+IF(ISNUMBER(01_INPUTS!M130),1,0)+IF(ISNUMBER(01_INPUTS!M131),1,0)+IF(ISNUMBER(01_INPUTS!M132),1,0)+IF(ISNUMBER(01_INPUTS!M133),1,0)+IF(ISNUMBER(01_INPUTS!M134),1,0)+IF(ISNUMBER(01_INPUTS!M135),1,0))=0,"",IFERROR(((IF(ISNUMBER(01_INPUTS!M124),01_INPUTS!M124,0)+IF(ISNUMBER(01_INPUTS!M125),01_INPUTS!M125,0)+IF(ISNUMBER(01_INPUTS!M126),01_INPUTS!M126,0)+IF(ISNUMBER(01_INPUTS!M127),01_INPUTS!M127,0))*_ENGINE_MERCADO!M6+(IF(ISNUMBER(01_INPUTS!M128),01_INPUTS!M128,0)+IF(ISNUMBER(01_INPUTS!M129),01_INPUTS!M129,0)+IF(ISNUMBER(01_INPUTS!M130),01_INPUTS!M130,0)+IF(ISNUMBER(01_INPUTS!M131),01_INPUTS!M131,0))*_ENGINE_MERCADO!M8+(IF(ISNUMBER(01_INPUTS!M132),01_INPUTS!M132,0)+IF(ISNUMBER(01_INPUTS!M133),01_INPUTS!M133,0)+IF(ISNUMBER(01_INPUTS!M134),01_INPUTS!M134,0)+IF(ISNUMBER(01_INPUTS!M135),01_INPUTS!M135,0))*_ENGINE_MERCADO!M10)/(_ENGINE_MERCADO!M6+_ENGINE_MERCADO!M8+_ENGINE_MERCADO!M10),"")),"") | N30: =IF(01_INPUTS!N17,IF((IF(ISNUMBER(01_INPUTS!N124),1,0)+IF(ISNUMBER(01_INPUTS!N125),1,0)+IF(ISNUMBER(01_INPUTS!N126),1,0)+IF(ISNUMBER(01_INPUTS!N127),1,0)+IF(ISNUMBER(01_INPUTS!N128),1,0)+IF(ISNUMBER(01_INPUTS!N129),1,0)+IF(ISNUMBER(01_INPUTS!N130),1,0)+IF(ISNUMBER(01_INPUTS!N131),1,0)+IF(ISNUMBER(01_INPUTS!N132),1,0)+IF(ISNUMBER(01_INPUTS!N133),1,0)+IF(ISNUMBER(01_INPUTS!N134),1,0)+IF(ISNUMBER(01_INPUTS!N135),1,0))=0,"",IFERROR(((IF(ISNUMBER(01_INPUTS!N124),01_INPUTS!N124,0)+IF(ISNUMBER(01_INPUTS!N125),01_INPUTS!N125,0)+IF(ISNUMBER(01_INPUTS!N126),01_INPUTS!N126,0)+IF(ISNUMBER(01_INPUTS!N127),01_INPUTS!N127,0))*_ENGINE_MERCADO!N6+(IF(ISNUMBER(01_INPUTS!N128),01_INPUTS!N128,0)+IF(ISNUMBER(01_INPUTS!N129),01_INPUTS!N129,0)+IF(ISNUMBER(01_INPUTS!N130),01_INPUTS!N130,0)+IF(ISNUMBER(01_INPUTS!N131),01_INPUTS!N131,0))*_ENGINE_MERCADO!N8+(IF(ISNUMBER(01_INPUTS!N132),01_INPUTS!N132,0)+IF(ISNUMBER(01_INPUTS!N133),01_INPUTS!N133,0)+IF(ISNUMBER(01_INPUTS!N134),01_INPUTS!N134,0)+IF(ISNUMBER(01_INPUTS!N135),01_INPUTS!N135,0))*_ENGINE_MERCADO!N10)/(_ENGINE_MERCADO!N6+_ENGINE_MERCADO!N8+_ENGINE_MERCADO!N10),"")),"") | O30: =IF(01_INPUTS!O17,IF((IF(ISNUMBER(01_INPUTS!O124),1,0)+IF(ISNUMBER(01_INPUTS!O125),1,0)+IF(ISNUMBER(01_INPUTS!O126),1,0)+IF(ISNUMBER(01_INPUTS!O127),1,0)+IF(ISNUMBER(01_INPUTS!O128),1,0)+IF(ISNUMBER(01_INPUTS!O129),1,0)+IF(ISNUMBER(01_INPUTS!O130),1,0)+IF(ISNUMBER(01_INPUTS!O131),1,0)+IF(ISNUMBER(01_INPUTS!O132),1,0)+IF(ISNUMBER(01_INPUTS!O133),1,0)+IF(ISNUMBER(01_INPUTS!O134),1,0)+IF(ISNUMBER(01_INPUTS!O135),1,0))=0,"",IFERROR(((IF(ISNUMBER(01_INPUTS!O124),01_INPUTS!O124,0)+IF(ISNUMBER(01_INPUTS!O125),01_INPUTS!O125,0)+IF(ISNUMBER(01_INPUTS!O126),01_INPUTS!O126,0)+IF(ISNUMBER(01_INPUTS!O127),01_INPUTS!O127,0))*_ENGINE_MERCADO!O6+(IF(ISNUMBER(01_INPUTS!O128),01_INPUTS!O128,0)+IF(ISNUMBER(01_INPUTS!O129),01_INPUTS!O129,0)+IF(ISNUMBER(01_INPUTS!O130),01_INPUTS!O130,0)+IF(ISNUMBER(01_INPUTS!O131),01_INPUTS!O131,0))*_ENGINE_MERCADO!O8+(IF(ISNUMBER(01_INPUTS!O132),01_INPUTS!O132,0)+IF(ISNUMBER(01_INPUTS!O133),01_INPUTS!O133,0)+IF(ISNUMBER(01_INPUTS!O134),01_INPUTS!O134,0)+IF(ISNUMBER(01_INPUTS!O135),01_INPUTS!O135,0))*_ENGINE_MERCADO!O10)/(_ENGINE_MERCADO!O6+_ENGINE_MERCADO!O8+_ENGINE_MERCADO!O10),"")),"") | P30: =IF(01_INPUTS!P17,IF((IF(ISNUMBER(01_INPUTS!P124),1,0)+IF(ISNUMBER(01_INPUTS!P125),1,0)+IF(ISNUMBER(01_INPUTS!P126),1,0)+IF(ISNUMBER(01_INPUTS!P127),1,0)+IF(ISNUMBER(01_INPUTS!P128),1,0)+IF(ISNUMBER(01_INPUTS!P129),1,0)+IF(ISNUMBER(01_INPUTS!P130),1,0)+IF(ISNUMBER(01_INPUTS!P131),1,0)+IF(ISNUMBER(01_INPUTS!P132),1,0)+IF(ISNUMBER(01_INPUTS!P133),1,0)+IF(ISNUMBER(01_INPUTS!P134),1,0)+IF(ISNUMBER(01_INPUTS!P135),1,0))=0,"",IFERROR(((IF(ISNUMBER(01_INPUTS!P124),01_INPUTS!P124,0)+IF(ISNUMBER(01_INPUTS!P125),01_INPUTS!P125,0)+IF(ISNUMBER(01_INPUTS!P126),01_INPUTS!P126,0)+IF(ISNUMBER(01_INPUTS!P127),01_INPUTS!P127,0))*_ENGINE_MERCADO!P6+(IF(ISNUMBER(01_INPUTS!P128),01_INPUTS!P128,0)+IF(ISNUMBER(01_INPUTS!P129),01_INPUTS!P129,0)+IF(ISNUMBER(01_INPUTS!P130),01_INPUTS!P130,0)+IF(ISNUMBER(01_INPUTS!P131),01_INPUTS!P131,0))*_ENGINE_MERCADO!P8+(IF(ISNUMBER(01_INPUTS!P132),01_INPUTS!P132,0)+IF(ISNUMBER(01_INPUTS!P133),01_INPUTS!P133,0)+IF(ISNUMBER(01_INPUTS!P134),01_INPUTS!P134,0)+IF(ISNUMBER(01_INPUTS!P135),01_INPUTS!P135,0))*_ENGINE_MERCADO!P10)/(_ENGINE_MERCADO!P6+_ENGINE_MERCADO!P8+_ENGINE_MERCADO!P10),"")),"") | ... S30: =IF(01_INPUTS!S17,IF((IF(ISNUMBER(01_INPUTS!S124),1,0)+IF(ISNUMBER(01_INPUTS!S125),1,0)+IF(ISNUMBER(01_INPUTS!S126),1,0)+IF(ISNUMBER(01_INPUTS!S127),1,0)+IF(ISNUMBER(01_INPUTS!S128),1,0)+IF(ISNUMBER(01_INPUTS!S129),1,0)+IF(ISNUMBER(01_INPUTS!S130),1,0)+IF(ISNUMBER(01_INPUTS!S131),1,0)+IF(ISNUMBER(01_INPUTS!S132),1,0)+IF(ISNUMBER(01_INPUTS!S133),1,0)+IF(ISNUMBER(01_INPUTS!S134),1,0)+IF(ISNUMBER(01_INPUTS!S135),1,0))=0,"",IFERROR(((IF(ISNUMBER(01_INPUTS!S124),01_INPUTS!S124,0)+IF(ISNUMBER(01_INPUTS!S125),01_INPUTS!S125,0)+IF(ISNUMBER(01_INPUTS!S126),01_INPUTS!S126,0)+IF(ISNUMBER(01_INPUTS!S127),01_INPUTS!S127,0))*_ENGINE_MERCADO!S6+(IF(ISNUMBER(01_INPUTS!S128),01_INPUTS!S128,0)+IF(ISNUMBER(01_INPUTS!S129),01_INPUTS!S129,0)+IF(ISNUMBER(01_INPUTS!S130),01_INPUTS!S130,0)+IF(ISNUMBER(01_INPUTS!S131),01_INPUTS!S131,0))*_ENGINE_MERCADO!S8+(IF(ISNUMBER(01_INPUTS!S132),01_INPUTS!S132,0)+IF(ISNUMBER(01_INPUTS!S133),01_INPUTS!S133,0)+IF(ISNUMBER(01_INPUTS!S134),01_INPUTS!S134,0)+IF(ISNUMBER(01_INPUTS!S135),01_INPUTS!S135,0))*_ENGINE_MERCADO!S10)/(_ENGINE_MERCADO!S6+_ENGINE_MERCADO!S8+_ENGINE_MERCADO!S10),"")),"")
A31: POR VEHÍCULO
A32: Ingresos por vehículo vendido | B32: USD/u. | G32: n/a | H32: n/a | I32: =IF(01_INPUTS!I17,IFERROR(_ENGINE_FINANCIERO!I160/(_ENGINE_MERCADO!I190+_ENGINE_MERCADO!I195+_ENGINE_MERCADO!I200+_ENGINE_MERCADO!I205+_ENGINE_MERCADO!I210+_ENGINE_MERCADO!I215+_ENGINE_MERCADO!I220+_ENGINE_MERCADO!I225+_ENGINE_MERCADO!I230+_ENGINE_MERCADO!I235+_ENGINE_MERCADO!I240+_ENGINE_MERCADO!I245),""),"") -> 26094.174 | J32: =IF(01_INPUTS!J17,IFERROR(_ENGINE_FINANCIERO!J160/(_ENGINE_MERCADO!J190+_ENGINE_MERCADO!J195+_ENGINE_MERCADO!J200+_ENGINE_MERCADO!J205+_ENGINE_MERCADO!J210+_ENGINE_MERCADO!J215+_ENGINE_MERCADO!J220+_ENGINE_MERCADO!J225+_ENGINE_MERCADO!J230+_ENGINE_MERCADO!J235+_ENGINE_MERCADO!J240+_ENGINE_MERCADO!J245),""),"") | K32: =IF(01_INPUTS!K17,IFERROR(_ENGINE_FINANCIERO!K160/(_ENGINE_MERCADO!K190+_ENGINE_MERCADO!K195+_ENGINE_MERCADO!K200+_ENGINE_MERCADO!K205+_ENGINE_MERCADO!K210+_ENGINE_MERCADO!K215+_ENGINE_MERCADO!K220+_ENGINE_MERCADO!K225+_ENGINE_MERCADO!K230+_ENGINE_MERCADO!K235+_ENGINE_MERCADO!K240+_ENGINE_MERCADO!K245),""),"") | L32: =IF(01_INPUTS!L17,IFERROR(_ENGINE_FINANCIERO!L160/(_ENGINE_MERCADO!L190+_ENGINE_MERCADO!L195+_ENGINE_MERCADO!L200+_ENGINE_MERCADO!L205+_ENGINE_MERCADO!L210+_ENGINE_MERCADO!L215+_ENGINE_MERCADO!L220+_ENGINE_MERCADO!L225+_ENGINE_MERCADO!L230+_ENGINE_MERCADO!L235+_ENGINE_MERCADO!L240+_ENGINE_MERCADO!L245),""),"") | M32: =IF(01_INPUTS!M17,IFERROR(_ENGINE_FINANCIERO!M160/(_ENGINE_MERCADO!M190+_ENGINE_MERCADO!M195+_ENGINE_MERCADO!M200+_ENGINE_MERCADO!M205+_ENGINE_MERCADO!M210+_ENGINE_MERCADO!M215+_ENGINE_MERCADO!M220+_ENGINE_MERCADO!M225+_ENGINE_MERCADO!M230+_ENGINE_MERCADO!M235+_ENGINE_MERCADO!M240+_ENGINE_MERCADO!M245),""),"") | N32: =IF(01_INPUTS!N17,IFERROR(_ENGINE_FINANCIERO!N160/(_ENGINE_MERCADO!N190+_ENGINE_MERCADO!N195+_ENGINE_MERCADO!N200+_ENGINE_MERCADO!N205+_ENGINE_MERCADO!N210+_ENGINE_MERCADO!N215+_ENGINE_MERCADO!N220+_ENGINE_MERCADO!N225+_ENGINE_MERCADO!N230+_ENGINE_MERCADO!N235+_ENGINE_MERCADO!N240+_ENGINE_MERCADO!N245),""),"") | O32: =IF(01_INPUTS!O17,IFERROR(_ENGINE_FINANCIERO!O160/(_ENGINE_MERCADO!O190+_ENGINE_MERCADO!O195+_ENGINE_MERCADO!O200+_ENGINE_MERCADO!O205+_ENGINE_MERCADO!O210+_ENGINE_MERCADO!O215+_ENGINE_MERCADO!O220+_ENGINE_MERCADO!O225+_ENGINE_MERCADO!O230+_ENGINE_MERCADO!O235+_ENGINE_MERCADO!O240+_ENGINE_MERCADO!O245),""),"") | P32: =IF(01_INPUTS!P17,IFERROR(_ENGINE_FINANCIERO!P160/(_ENGINE_MERCADO!P190+_ENGINE_MERCADO!P195+_ENGINE_MERCADO!P200+_ENGINE_MERCADO!P205+_ENGINE_MERCADO!P210+_ENGINE_MERCADO!P215+_ENGINE_MERCADO!P220+_ENGINE_MERCADO!P225+_ENGINE_MERCADO!P230+_ENGINE_MERCADO!P235+_ENGINE_MERCADO!P240+_ENGINE_MERCADO!P245),""),"") | ... S32: =IF(01_INPUTS!S17,IFERROR(_ENGINE_FINANCIERO!S160/(_ENGINE_MERCADO!S190+_ENGINE_MERCADO!S195+_ENGINE_MERCADO!S200+_ENGINE_MERCADO!S205+_ENGINE_MERCADO!S210+_ENGINE_MERCADO!S215+_ENGINE_MERCADO!S220+_ENGINE_MERCADO!S225+_ENGINE_MERCADO!S230+_ENGINE_MERCADO!S235+_ENGINE_MERCADO!S240+_ENGINE_MERCADO!S245),""),"")
A33: EBITDA por vehículo vendido | B33: USD/u. | G33: n/a | H33: n/a | I33: =IF(01_INPUTS!I17,IFERROR(_ENGINE_FINANCIERO!I162/(_ENGINE_MERCADO!I190+_ENGINE_MERCADO!I195+_ENGINE_MERCADO!I200+_ENGINE_MERCADO!I205+_ENGINE_MERCADO!I210+_ENGINE_MERCADO!I215+_ENGINE_MERCADO!I220+_ENGINE_MERCADO!I225+_ENGINE_MERCADO!I230+_ENGINE_MERCADO!I235+_ENGINE_MERCADO!I240+_ENGINE_MERCADO!I245),""),"") -> 6375.4052 | J33: =IF(01_INPUTS!J17,IFERROR(_ENGINE_FINANCIERO!J162/(_ENGINE_MERCADO!J190+_ENGINE_MERCADO!J195+_ENGINE_MERCADO!J200+_ENGINE_MERCADO!J205+_ENGINE_MERCADO!J210+_ENGINE_MERCADO!J215+_ENGINE_MERCADO!J220+_ENGINE_MERCADO!J225+_ENGINE_MERCADO!J230+_ENGINE_MERCADO!J235+_ENGINE_MERCADO!J240+_ENGINE_MERCADO!J245),""),"") | K33: =IF(01_INPUTS!K17,IFERROR(_ENGINE_FINANCIERO!K162/(_ENGINE_MERCADO!K190+_ENGINE_MERCADO!K195+_ENGINE_MERCADO!K200+_ENGINE_MERCADO!K205+_ENGINE_MERCADO!K210+_ENGINE_MERCADO!K215+_ENGINE_MERCADO!K220+_ENGINE_MERCADO!K225+_ENGINE_MERCADO!K230+_ENGINE_MERCADO!K235+_ENGINE_MERCADO!K240+_ENGINE_MERCADO!K245),""),"") | L33: =IF(01_INPUTS!L17,IFERROR(_ENGINE_FINANCIERO!L162/(_ENGINE_MERCADO!L190+_ENGINE_MERCADO!L195+_ENGINE_MERCADO!L200+_ENGINE_MERCADO!L205+_ENGINE_MERCADO!L210+_ENGINE_MERCADO!L215+_ENGINE_MERCADO!L220+_ENGINE_MERCADO!L225+_ENGINE_MERCADO!L230+_ENGINE_MERCADO!L235+_ENGINE_MERCADO!L240+_ENGINE_MERCADO!L245),""),"") | M33: =IF(01_INPUTS!M17,IFERROR(_ENGINE_FINANCIERO!M162/(_ENGINE_MERCADO!M190+_ENGINE_MERCADO!M195+_ENGINE_MERCADO!M200+_ENGINE_MERCADO!M205+_ENGINE_MERCADO!M210+_ENGINE_MERCADO!M215+_ENGINE_MERCADO!M220+_ENGINE_MERCADO!M225+_ENGINE_MERCADO!M230+_ENGINE_MERCADO!M235+_ENGINE_MERCADO!M240+_ENGINE_MERCADO!M245),""),"") | N33: =IF(01_INPUTS!N17,IFERROR(_ENGINE_FINANCIERO!N162/(_ENGINE_MERCADO!N190+_ENGINE_MERCADO!N195+_ENGINE_MERCADO!N200+_ENGINE_MERCADO!N205+_ENGINE_MERCADO!N210+_ENGINE_MERCADO!N215+_ENGINE_MERCADO!N220+_ENGINE_MERCADO!N225+_ENGINE_MERCADO!N230+_ENGINE_MERCADO!N235+_ENGINE_MERCADO!N240+_ENGINE_MERCADO!N245),""),"") | O33: =IF(01_INPUTS!O17,IFERROR(_ENGINE_FINANCIERO!O162/(_ENGINE_MERCADO!O190+_ENGINE_MERCADO!O195+_ENGINE_MERCADO!O200+_ENGINE_MERCADO!O205+_ENGINE_MERCADO!O210+_ENGINE_MERCADO!O215+_ENGINE_MERCADO!O220+_ENGINE_MERCADO!O225+_ENGINE_MERCADO!O230+_ENGINE_MERCADO!O235+_ENGINE_MERCADO!O240+_ENGINE_MERCADO!O245),""),"") | P33: =IF(01_INPUTS!P17,IFERROR(_ENGINE_FINANCIERO!P162/(_ENGINE_MERCADO!P190+_ENGINE_MERCADO!P195+_ENGINE_MERCADO!P200+_ENGINE_MERCADO!P205+_ENGINE_MERCADO!P210+_ENGINE_MERCADO!P215+_ENGINE_MERCADO!P220+_ENGINE_MERCADO!P225+_ENGINE_MERCADO!P230+_ENGINE_MERCADO!P235+_ENGINE_MERCADO!P240+_ENGINE_MERCADO!P245),""),"") | ... S33: =IF(01_INPUTS!S17,IFERROR(_ENGINE_FINANCIERO!S162/(_ENGINE_MERCADO!S190+_ENGINE_MERCADO!S195+_ENGINE_MERCADO!S200+_ENGINE_MERCADO!S205+_ENGINE_MERCADO!S210+_ENGINE_MERCADO!S215+_ENGINE_MERCADO!S220+_ENGINE_MERCADO!S225+_ENGINE_MERCADO!S230+_ENGINE_MERCADO!S235+_ENGINE_MERCADO!S240+_ENGINE_MERCADO!S245),""),"")

Sheet 04_CONTROL_MODELO
A1: 04_CONTROL_MODELO — Controles técnicos de salud del modelo (NO es Control de Gestión frente a profesores/accionistas)
A2: Verifica consistencia interna e integridad de datos. OK = check pasa; ERROR = revisar antes de usar la proyección. No evalúa desempeño estratégico (eso es 03_RATIOS).
A4: Control | B4: Tipo | C4: Nota | G4: R0 | H4: R1 | I4: R2 | J4: R3 | K4: R4 | L4: R5 | M4: R6 | N4: R7 | O4: R8 | P4: R9 | Q4: R10 | R4: R11 | S4: R12
A5: A · IDENTIDADES CONTABLES Y DE CONSOLIDACIÓN (Fase 2: por país Y Global)
A6: Balance: Activo Total = Patrimonio + Pasivo — EE.UU. | B6: CONTROL | G6: =IF(ABS(_ENGINE_FINANCIERO!G44)<1000,"OK",IF(ABS(ABS(_ENGINE_FINANCIERO!G44)-1508776236.64)<1000000,"ADVERTENCIA — diferencia heredada R1 ≈ USD 1.508,8 M (v1.2)","ERROR")) -> OK | H6: =IF(ABS(_ENGINE_FINANCIERO!H44)<1000,"OK",IF(ABS(ABS(_ENGINE_FINANCIERO!H44)-1508776236.64)<1000000,"ADVERTENCIA — diferencia heredada R1 ≈ USD 1.508,8 M (v1.2)","ERROR")) -> OK | I6: =IF(01_INPUTS!I17,IF(ABS(_ENGINE_FINANCIERO!I44)<1000,"OK",IF(ABS(ABS(_ENGINE_FINANCIERO!I44)-1508776236.64)<1000000,"ADVERTENCIA — diferencia heredada R1 ≈ USD 1.508,8 M (v1.2)","ERROR")),"NO ACTIVA") -> OK | J6: =IF(01_INPUTS!J17,IF(ABS(_ENGINE_FINANCIERO!J44)<1000,"OK",IF(ABS(ABS(_ENGINE_FINANCIERO!J44)-1508776236.64)<1000000,"ADVERTENCIA — diferencia heredada R1 ≈ USD 1.508,8 M (v1.2)","ERROR")),"NO ACTIVA") -> NO ACTIVA | K6: =IF(01_INPUTS!K17,IF(ABS(_ENGINE_FINANCIERO!K44)<1000,"OK",IF(ABS(ABS(_ENGINE_FINANCIERO!K44)-1508776236.64)<1000000,"ADVERTENCIA — diferencia heredada R1 ≈ USD 1.508,8 M (v1.2)","ERROR")),"NO ACTIVA") -> NO ACTIVA | L6: =IF(01_INPUTS!L17,IF(ABS(_ENGINE_FINANCIERO!L44)<1000,"OK",IF(ABS(ABS(_ENGINE_FINANCIERO!L44)-1508776236.64)<1000000,"ADVERTENCIA — diferencia heredada R1 ≈ USD 1.508,8 M (v1.2)","ERROR")),"NO ACTIVA") -> NO ACTIVA | M6: =IF(01_INPUTS!M17,IF(ABS(_ENGINE_FINANCIERO!M44)<1000,"OK",IF(ABS(ABS(_ENGINE_FINANCIERO!M44)-1508776236.64)<1000000,"ADVERTENCIA — diferencia heredada R1 ≈ USD 1.508,8 M (v1.2)","ERROR")),"NO ACTIVA") -> NO ACTIVA | N6: =IF(01_INPUTS!N17,IF(ABS(_ENGINE_FINANCIERO!N44)<1000,"OK",IF(ABS(ABS(_ENGINE_FINANCIERO!N44)-1508776236.64)<1000000,"ADVERTENCIA — diferencia heredada R1 ≈ USD 1.508,8 M (v1.2)","ERROR")),"NO ACTIVA") -> NO ACTIVA | O6: =IF(01_INPUTS!O17,IF(ABS(_ENGINE_FINANCIERO!O44)<1000,"OK",IF(ABS(ABS(_ENGINE_FINANCIERO!O44)-1508776236.64)<1000000,"ADVERTENCIA — diferencia heredada R1 ≈ USD 1.508,8 M (v1.2)","ERROR")),"NO ACTIVA") -> NO ACTIVA | P6: =IF(01_INPUTS!P17,IF(ABS(_ENGINE_FINANCIERO!P44)<1000,"OK",IF(ABS(ABS(_ENGINE_FINANCIERO!P44)-1508776236.64)<1000000,"ADVERTENCIA — diferencia heredada R1 ≈ USD 1.508,8 M (v1.2)","ERROR")),"NO ACTIVA") -> NO ACTIVA | ... S6: =IF(01_INPUTS!S17,IF(ABS(_ENGINE_FINANCIERO!S44)<1000,"OK",IF(ABS(ABS(_ENGINE_FINANCIERO!S44)-1508776236.64)<1000000,"ADVERTENCIA — diferencia heredada R1 ≈ USD 1.508,8 M (v1.2)","ERROR")),"NO ACTIVA") -> NO ACTIVA
A7: Balance: Activo Total = Patrimonio + Pasivo — China | B7: CONTROL | G7: =IF(ABS(_ENGINE_FINANCIERO!G91)<1000,"OK",IF(ABS(ABS(_ENGINE_FINANCIERO!G91)-1508776236.64)<1000000,"ADVERTENCIA — diferencia heredada R1 ≈ USD 1.508,8 M (v1.2)","ERROR")) -> OK | H7: =IF(ABS(_ENGINE_FINANCIERO!H91)<1000,"OK",IF(ABS(ABS(_ENGINE_FINANCIERO!H91)-1508776236.64)<1000000,"ADVERTENCIA — diferencia heredada R1 ≈ USD 1.508,8 M (v1.2)","ERROR")) -> OK | I7: =IF(01_INPUTS!I17,IF(ABS(_ENGINE_FINANCIERO!I91)<1000,"OK",IF(ABS(ABS(_ENGINE_FINANCIERO!I91)-1508776236.64)<1000000,"ADVERTENCIA — diferencia heredada R1 ≈ USD 1.508,8 M (v1.2)","ERROR")),"NO ACTIVA") -> OK | J7: =IF(01_INPUTS!J17,IF(ABS(_ENGINE_FINANCIERO!J91)<1000,"OK",IF(ABS(ABS(_ENGINE_FINANCIERO!J91)-1508776236.64)<1000000,"ADVERTENCIA — diferencia heredada R1 ≈ USD 1.508,8 M (v1.2)","ERROR")),"NO ACTIVA") -> NO ACTIVA | K7: =IF(01_INPUTS!K17,IF(ABS(_ENGINE_FINANCIERO!K91)<1000,"OK",IF(ABS(ABS(_ENGINE_FINANCIERO!K91)-1508776236.64)<1000000,"ADVERTENCIA — diferencia heredada R1 ≈ USD 1.508,8 M (v1.2)","ERROR")),"NO ACTIVA") -> NO ACTIVA | L7: =IF(01_INPUTS!L17,IF(ABS(_ENGINE_FINANCIERO!L91)<1000,"OK",IF(ABS(ABS(_ENGINE_FINANCIERO!L91)-1508776236.64)<1000000,"ADVERTENCIA — diferencia heredada R1 ≈ USD 1.508,8 M (v1.2)","ERROR")),"NO ACTIVA") -> NO ACTIVA | M7: =IF(01_INPUTS!M17,IF(ABS(_ENGINE_FINANCIERO!M91)<1000,"OK",IF(ABS(ABS(_ENGINE_FINANCIERO!M91)-1508776236.64)<1000000,"ADVERTENCIA — diferencia heredada R1 ≈ USD 1.508,8 M (v1.2)","ERROR")),"NO ACTIVA") -> NO ACTIVA | N7: =IF(01_INPUTS!N17,IF(ABS(_ENGINE_FINANCIERO!N91)<1000,"OK",IF(ABS(ABS(_ENGINE_FINANCIERO!N91)-1508776236.64)<1000000,"ADVERTENCIA — diferencia heredada R1 ≈ USD 1.508,8 M (v1.2)","ERROR")),"NO ACTIVA") -> NO ACTIVA | O7: =IF(01_INPUTS!O17,IF(ABS(_ENGINE_FINANCIERO!O91)<1000,"OK",IF(ABS(ABS(_ENGINE_FINANCIERO!O91)-1508776236.64)<1000000,"ADVERTENCIA — diferencia heredada R1 ≈ USD 1.508,8 M (v1.2)","ERROR")),"NO ACTIVA") -> NO ACTIVA | P7: =IF(01_INPUTS!P17,IF(ABS(_ENGINE_FINANCIERO!P91)<1000,"OK",IF(ABS(ABS(_ENGINE_FINANCIERO!P91)-1508776236.64)<1000000,"ADVERTENCIA — diferencia heredada R1 ≈ USD 1.508,8 M (v1.2)","ERROR")),"NO ACTIVA") -> NO ACTIVA | ... S7: =IF(01_INPUTS!S17,IF(ABS(_ENGINE_FINANCIERO!S91)<1000,"OK",IF(ABS(ABS(_ENGINE_FINANCIERO!S91)-1508776236.64)<1000000,"ADVERTENCIA — diferencia heredada R1 ≈ USD 1.508,8 M (v1.2)","ERROR")),"NO ACTIVA") -> NO ACTIVA
A8: Balance: Activo Total = Patrimonio + Pasivo — Europa | B8: CONTROL | G8: =IF(ABS(_ENGINE_FINANCIERO!G138)<1000,"OK",IF(ABS(ABS(_ENGINE_FINANCIERO!G138)-1508776236.64)<1000000,"ADVERTENCIA — diferencia heredada R1 ≈ USD 1.508,8 M (v1.2)","ERROR")) -> OK | H8: =IF(ABS(_ENGINE_FINANCIERO!H138)<1000,"OK",IF(ABS(ABS(_ENGINE_FINANCIERO!H138)-1508776236.64)<1000000,"ADVERTENCIA — diferencia heredada R1 ≈ USD 1.508,8 M (v1.2)","ERROR")) -> OK | I8: =IF(01_INPUTS!I17,IF(ABS(_ENGINE_FINANCIERO!I138)<1000,"OK",IF(ABS(ABS(_ENGINE_FINANCIERO!I138)-1508776236.64)<1000000,"ADVERTENCIA — diferencia heredada R1 ≈ USD 1.508,8 M (v1.2)","ERROR")),"NO ACTIVA") -> OK | J8: =IF(01_INPUTS!J17,IF(ABS(_ENGINE_FINANCIERO!J138)<1000,"OK",IF(ABS(ABS(_ENGINE_FINANCIERO!J138)-1508776236.64)<1000000,"ADVERTENCIA — diferencia heredada R1 ≈ USD 1.508,8 M (v1.2)","ERROR")),"NO ACTIVA") -> NO ACTIVA | K8: =IF(01_INPUTS!K17,IF(ABS(_ENGINE_FINANCIERO!K138)<1000,"OK",IF(ABS(ABS(_ENGINE_FINANCIERO!K138)-1508776236.64)<1000000,"ADVERTENCIA — diferencia heredada R1 ≈ USD 1.508,8 M (v1.2)","ERROR")),"NO ACTIVA") -> NO ACTIVA | L8: =IF(01_INPUTS!L17,IF(ABS(_ENGINE_FINANCIERO!L138)<1000,"OK",IF(ABS(ABS(_ENGINE_FINANCIERO!L138)-1508776236.64)<1000000,"ADVERTENCIA — diferencia heredada R1 ≈ USD 1.508,8 M (v1.2)","ERROR")),"NO ACTIVA") -> NO ACTIVA | M8: =IF(01_INPUTS!M17,IF(ABS(_ENGINE_FINANCIERO!M138)<1000,"OK",IF(ABS(ABS(_ENGINE_FINANCIERO!M138)-1508776236.64)<1000000,"ADVERTENCIA — diferencia heredada R1 ≈ USD 1.508,8 M (v1.2)","ERROR")),"NO ACTIVA") -> NO ACTIVA | N8: =IF(01_INPUTS!N17,IF(ABS(_ENGINE_FINANCIERO!N138)<1000,"OK",IF(ABS(ABS(_ENGINE_FINANCIERO!N138)-1508776236.64)<1000000,"ADVERTENCIA — diferencia heredada R1 ≈ USD 1.508,8 M (v1.2)","ERROR")),"NO ACTIVA") -> NO ACTIVA | O8: =IF(01_INPUTS!O17,IF(ABS(_ENGINE_FINANCIERO!O138)<1000,"OK",IF(ABS(ABS(_ENGINE_FINANCIERO!O138)-1508776236.64)<1000000,"ADVERTENCIA — diferencia heredada R1 ≈ USD 1.508,8 M (v1.2)","ERROR")),"NO ACTIVA") -> NO ACTIVA | P8: =IF(01_INPUTS!P17,IF(ABS(_ENGINE_FINANCIERO!P138)<1000,"OK",IF(ABS(ABS(_ENGINE_FINANCIERO!P138)-1508776236.64)<1000000,"ADVERTENCIA — diferencia heredada R1 ≈ USD 1.508,8 M (v1.2)","ERROR")),"NO ACTIVA") -> NO ACTIVA | ... S8: =IF(01_INPUTS!S17,IF(ABS(_ENGINE_FINANCIERO!S138)<1000,"OK",IF(ABS(ABS(_ENGINE_FINANCIERO!S138)-1508776236.64)<1000000,"ADVERTENCIA — diferencia heredada R1 ≈ USD 1.508,8 M (v1.2)","ERROR")),"NO ACTIVA") -> NO ACTIVA
A9: Balance: Activo Total = Patrimonio + Pasivo (Global = Σ países) | B9: CONTROL | C9: Fase 2: el Global ahora es la SUMA de los 3 Balances por país (arriba), 100% consistentes con RDOS en R0/R1 -- esto corrige la inconsistencia heredada de v1.2 (~1.508,8 MM USD en R1). Ver Informe_V2.md. | G9: =IF(ABS(_ENGINE_FINANCIERO!G186)<1000,"OK",IF(ABS(ABS(_ENGINE_FINANCIERO!G186)-1508776236.64)<1000000,"ADVERTENCIA — diferencia heredada R1 ≈ USD 1.508,8 M (v1.2)","ERROR")) -> OK | H9: =IF(ABS(_ENGINE_FINANCIERO!H186)<1000,"OK",IF(ABS(ABS(_ENGINE_FINANCIERO!H186)-1508776236.64)<1000000,"ADVERTENCIA — diferencia heredada R1 ≈ USD 1.508,8 M (v1.2)","ERROR")) -> OK | I9: =IF(01_INPUTS!I17,IF(ABS(_ENGINE_FINANCIERO!I186)<1000,"OK",IF(ABS(ABS(_ENGINE_FINANCIERO!I186)-1508776236.64)<1000000,"ADVERTENCIA — diferencia heredada R1 ≈ USD 1.508,8 M (v1.2)","ERROR")),"NO ACTIVA") -> OK | J9: =IF(01_INPUTS!J17,IF(ABS(_ENGINE_FINANCIERO!J186)<1000,"OK",IF(ABS(ABS(_ENGINE_FINANCIERO!J186)-1508776236.64)<1000000,"ADVERTENCIA — diferencia heredada R1 ≈ USD 1.508,8 M (v1.2)","ERROR")),"NO ACTIVA") -> NO ACTIVA | K9: =IF(01_INPUTS!K17,IF(ABS(_ENGINE_FINANCIERO!K186)<1000,"OK",IF(ABS(ABS(_ENGINE_FINANCIERO!K186)-1508776236.64)<1000000,"ADVERTENCIA — diferencia heredada R1 ≈ USD 1.508,8 M (v1.2)","ERROR")),"NO ACTIVA") -> NO ACTIVA | L9: =IF(01_INPUTS!L17,IF(ABS(_ENGINE_FINANCIERO!L186)<1000,"OK",IF(ABS(ABS(_ENGINE_FINANCIERO!L186)-1508776236.64)<1000000,"ADVERTENCIA — diferencia heredada R1 ≈ USD 1.508,8 M (v1.2)","ERROR")),"NO ACTIVA") -> NO ACTIVA | M9: =IF(01_INPUTS!M17,IF(ABS(_ENGINE_FINANCIERO!M186)<1000,"OK",IF(ABS(ABS(_ENGINE_FINANCIERO!M186)-1508776236.64)<1000000,"ADVERTENCIA — diferencia heredada R1 ≈ USD 1.508,8 M (v1.2)","ERROR")),"NO ACTIVA") -> NO ACTIVA | N9: =IF(01_INPUTS!N17,IF(ABS(_ENGINE_FINANCIERO!N186)<1000,"OK",IF(ABS(ABS(_ENGINE_FINANCIERO!N186)-1508776236.64)<1000000,"ADVERTENCIA — diferencia heredada R1 ≈ USD 1.508,8 M (v1.2)","ERROR")),"NO ACTIVA") -> NO ACTIVA | O9: =IF(01_INPUTS!O17,IF(ABS(_ENGINE_FINANCIERO!O186)<1000,"OK",IF(ABS(ABS(_ENGINE_FINANCIERO!O186)-1508776236.64)<1000000,"ADVERTENCIA — diferencia heredada R1 ≈ USD 1.508,8 M (v1.2)","ERROR")),"NO ACTIVA") -> NO ACTIVA | P9: =IF(01_INPUTS!P17,IF(ABS(_ENGINE_FINANCIERO!P186)<1000,"OK",IF(ABS(ABS(_ENGINE_FINANCIERO!P186)-1508776236.64)<1000000,"ADVERTENCIA — diferencia heredada R1 ≈ USD 1.508,8 M (v1.2)","ERROR")),"NO ACTIVA") -> NO ACTIVA | ... S9: =IF(01_INPUTS!S17,IF(ABS(_ENGINE_FINANCIERO!S186)<1000,"OK",IF(ABS(ABS(_ENGINE_FINANCIERO!S186)-1508776236.64)<1000000,"ADVERTENCIA — diferencia heredada R1 ≈ USD 1.508,8 M (v1.2)","ERROR")),"NO ACTIVA") -> NO ACTIVA
A10: Préstamos internos: Σ EE.UU.+China+Europa = 0 | B10: CONTROL | C10: REGLA VERIFICADA: los préstamos internos entre países (D8) deben netear a 0 exactamente cada ronda (Fase 2: ahora trackeados explícitamente por país, no solo colapsados a nivel Global). | G10: =IF(ABS(_ENGINE_FINANCIERO!G187)<1,"OK","ERROR") -> OK | H10: =IF(ABS(_ENGINE_FINANCIERO!H187)<1,"OK","ERROR") -> OK | I10: =IF(01_INPUTS!I17,IF(ABS(_ENGINE_FINANCIERO!I187)<1,"OK","ERROR"),"NO ACTIVA") -> OK | J10: =IF(01_INPUTS!J17,IF(ABS(_ENGINE_FINANCIERO!J187)<1,"OK","ERROR"),"NO ACTIVA") -> NO ACTIVA | K10: =IF(01_INPUTS!K17,IF(ABS(_ENGINE_FINANCIERO!K187)<1,"OK","ERROR"),"NO ACTIVA") -> NO ACTIVA | L10: =IF(01_INPUTS!L17,IF(ABS(_ENGINE_FINANCIERO!L187)<1,"OK","ERROR"),"NO ACTIVA") -> NO ACTIVA | M10: =IF(01_INPUTS!M17,IF(ABS(_ENGINE_FINANCIERO!M187)<1,"OK","ERROR"),"NO ACTIVA") -> NO ACTIVA | N10: =IF(01_INPUTS!N17,IF(ABS(_ENGINE_FINANCIERO!N187)<1,"OK","ERROR"),"NO ACTIVA") -> NO ACTIVA | O10: =IF(01_INPUTS!O17,IF(ABS(_ENGINE_FINANCIERO!O187)<1,"OK","ERROR"),"NO ACTIVA") -> NO ACTIVA | P10: =IF(01_INPUTS!P17,IF(ABS(_ENGINE_FINANCIERO!P187)<1,"OK","ERROR"),"NO ACTIVA") -> NO ACTIVA | ... S10: =IF(01_INPUTS!S17,IF(ABS(_ENGINE_FINANCIERO!S187)<1,"OK","ERROR"),"NO ACTIVA") -> NO ACTIVA
A11: Cash Flow: Efectivo cierre (CF) = Efectivo (Balance) | B11: CONTROL | G11: =IF(ISTEXT(_ENGINE_FINANCIERO!G197),"OK",IF(ABS(_ENGINE_FINANCIERO!G197)<1,"OK","ERROR")) -> OK | H11: =IF(ISTEXT(_ENGINE_FINANCIERO!H197),"OK",IF(ABS(_ENGINE_FINANCIERO!H197)<1,"OK","ERROR")) -> OK | I11: =IF(01_INPUTS!I17,IF(ISTEXT(_ENGINE_FINANCIERO!I197),"OK",IF(ABS(_ENGINE_FINANCIERO!I197)<1,"OK","ERROR")),"NO ACTIVA") -> OK | J11: =IF(01_INPUTS!J17,IF(ISTEXT(_ENGINE_FINANCIERO!J197),"OK",IF(ABS(_ENGINE_FINANCIERO!J197)<1,"OK","ERROR")),"NO ACTIVA") -> NO ACTIVA | K11: =IF(01_INPUTS!K17,IF(ISTEXT(_ENGINE_FINANCIERO!K197),"OK",IF(ABS(_ENGINE_FINANCIERO!K197)<1,"OK","ERROR")),"NO ACTIVA") -> NO ACTIVA | L11: =IF(01_INPUTS!L17,IF(ISTEXT(_ENGINE_FINANCIERO!L197),"OK",IF(ABS(_ENGINE_FINANCIERO!L197)<1,"OK","ERROR")),"NO ACTIVA") -> NO ACTIVA | M11: =IF(01_INPUTS!M17,IF(ISTEXT(_ENGINE_FINANCIERO!M197),"OK",IF(ABS(_ENGINE_FINANCIERO!M197)<1,"OK","ERROR")),"NO ACTIVA") -> NO ACTIVA | N11: =IF(01_INPUTS!N17,IF(ISTEXT(_ENGINE_FINANCIERO!N197),"OK",IF(ABS(_ENGINE_FINANCIERO!N197)<1,"OK","ERROR")),"NO ACTIVA") -> NO ACTIVA | O11: =IF(01_INPUTS!O17,IF(ISTEXT(_ENGINE_FINANCIERO!O197),"OK",IF(ABS(_ENGINE_FINANCIERO!O197)<1,"OK","ERROR")),"NO ACTIVA") -> NO ACTIVA | P11: =IF(01_INPUTS!P17,IF(ISTEXT(_ENGINE_FINANCIERO!P197),"OK",IF(ABS(_ENGINE_FINANCIERO!P197)<1,"OK","ERROR")),"NO ACTIVA") -> NO ACTIVA | ... S11: =IF(01_INPUTS!S17,IF(ISTEXT(_ENGINE_FINANCIERO!S197),"OK",IF(ABS(_ENGINE_FINANCIERO!S197)<1,"OK","ERROR")),"NO ACTIVA") -> NO ACTIVA
A12: Consolidación: Beneficio Global = Σ Beneficio países | B12: CONTROL | G12: =IF(ISTEXT(_ENGINE_FINANCIERO!G169),"OK",IF(ABS(_ENGINE_FINANCIERO!G169)<1,"OK","ERROR")) -> OK | H12: =IF(ISTEXT(_ENGINE_FINANCIERO!H169),"OK",IF(ABS(_ENGINE_FINANCIERO!H169)<1,"OK","ERROR")) -> OK | I12: =IF(01_INPUTS!I17,IF(ISTEXT(_ENGINE_FINANCIERO!I169),"OK",IF(ABS(_ENGINE_FINANCIERO!I169)<1,"OK","ERROR")),"NO ACTIVA") -> OK | J12: =IF(01_INPUTS!J17,IF(ISTEXT(_ENGINE_FINANCIERO!J169),"OK",IF(ABS(_ENGINE_FINANCIERO!J169)<1,"OK","ERROR")),"NO ACTIVA") -> NO ACTIVA | K12: =IF(01_INPUTS!K17,IF(ISTEXT(_ENGINE_FINANCIERO!K169),"OK",IF(ABS(_ENGINE_FINANCIERO!K169)<1,"OK","ERROR")),"NO ACTIVA") -> NO ACTIVA | L12: =IF(01_INPUTS!L17,IF(ISTEXT(_ENGINE_FINANCIERO!L169),"OK",IF(ABS(_ENGINE_FINANCIERO!L169)<1,"OK","ERROR")),"NO ACTIVA") -> NO ACTIVA | M12: =IF(01_INPUTS!M17,IF(ISTEXT(_ENGINE_FINANCIERO!M169),"OK",IF(ABS(_ENGINE_FINANCIERO!M169)<1,"OK","ERROR")),"NO ACTIVA") -> NO ACTIVA | N12: =IF(01_INPUTS!N17,IF(ISTEXT(_ENGINE_FINANCIERO!N169),"OK",IF(ABS(_ENGINE_FINANCIERO!N169)<1,"OK","ERROR")),"NO ACTIVA") -> NO ACTIVA | O12: =IF(01_INPUTS!O17,IF(ISTEXT(_ENGINE_FINANCIERO!O169),"OK",IF(ABS(_ENGINE_FINANCIERO!O169)<1,"OK","ERROR")),"NO ACTIVA") -> NO ACTIVA | P12: =IF(01_INPUTS!P17,IF(ISTEXT(_ENGINE_FINANCIERO!P169),"OK",IF(ABS(_ENGINE_FINANCIERO!P169)<1,"OK","ERROR")),"NO ACTIVA") -> NO ACTIVA | ... S12: =IF(01_INPUTS!S17,IF(ISTEXT(_ENGINE_FINANCIERO!S169),"OK",IF(ABS(_ENGINE_FINANCIERO!S169)<1,"OK","ERROR")),"NO ACTIVA") -> NO ACTIVA
A14: B · MERCADO, VENTAS E INVENTARIO
A15: Ventas ≤ Disponibilidad (por área/tecnología) | B15: CONTROL | G15: =IF(AND((_ENGINE_PRODUCCION!G83<=_ENGINE_PRODUCCION!G80+0.5),(_ENGINE_PRODUCCION!G95<=_ENGINE_PRODUCCION!G92+0.5),(_ENGINE_PRODUCCION!G107<=_ENGINE_PRODUCCION!G104+0.5),(_ENGINE_PRODUCCION!G119<=_ENGINE_PRODUCCION!G116+0.5),(_ENGINE_PRODUCCION!G132<=_ENGINE_PRODUCCION!G129+0.5),(_ENGINE_PRODUCCION!G144<=_ENGINE_PRODUCCION!G141+0.5),(_ENGINE_PRODUCCION!G156<=_ENGINE_PRODUCCION!G153+0.5),(_ENGINE_PRODUCCION!G168<=_ENGINE_PRODUCCION!G165+0.5)),"OK","ERROR") -> OK | H15: =IF(AND((_ENGINE_PRODUCCION!H83<=_ENGINE_PRODUCCION!H80+0.5),(_ENGINE_PRODUCCION!H95<=_ENGINE_PRODUCCION!H92+0.5),(_ENGINE_PRODUCCION!H107<=_ENGINE_PRODUCCION!H104+0.5),(_ENGINE_PRODUCCION!H119<=_ENGINE_PRODUCCION!H116+0.5),(_ENGINE_PRODUCCION!H132<=_ENGINE_PRODUCCION!H129+0.5),(_ENGINE_PRODUCCION!H144<=_ENGINE_PRODUCCION!H141+0.5),(_ENGINE_PRODUCCION!H156<=_ENGINE_PRODUCCION!H153+0.5),(_ENGINE_PRODUCCION!H168<=_ENGINE_PRODUCCION!H165+0.5)),"OK","ERROR") -> OK | I15: =IF(01_INPUTS!I17,IF(AND((_ENGINE_PRODUCCION!I83<=_ENGINE_PRODUCCION!I80+0.5),(_ENGINE_PRODUCCION!I95<=_ENGINE_PRODUCCION!I92+0.5),(_ENGINE_PRODUCCION!I107<=_ENGINE_PRODUCCION!I104+0.5),(_ENGINE_PRODUCCION!I119<=_ENGINE_PRODUCCION!I116+0.5),(_ENGINE_PRODUCCION!I132<=_ENGINE_PRODUCCION!I129+0.5),(_ENGINE_PRODUCCION!I144<=_ENGINE_PRODUCCION!I141+0.5),(_ENGINE_PRODUCCION!I156<=_ENGINE_PRODUCCION!I153+0.5),(_ENGINE_PRODUCCION!I168<=_ENGINE_PRODUCCION!I165+0.5)),"OK","ERROR"),"NO ACTIVA") -> OK | J15: =IF(01_INPUTS!J17,IF(AND((_ENGINE_PRODUCCION!J83<=_ENGINE_PRODUCCION!J80+0.5),(_ENGINE_PRODUCCION!J95<=_ENGINE_PRODUCCION!J92+0.5),(_ENGINE_PRODUCCION!J107<=_ENGINE_PRODUCCION!J104+0.5),(_ENGINE_PRODUCCION!J119<=_ENGINE_PRODUCCION!J116+0.5),(_ENGINE_PRODUCCION!J132<=_ENGINE_PRODUCCION!J129+0.5),(_ENGINE_PRODUCCION!J144<=_ENGINE_PRODUCCION!J141+0.5),(_ENGINE_PRODUCCION!J156<=_ENGINE_PRODUCCION!J153+0.5),(_ENGINE_PRODUCCION!J168<=_ENGINE_PRODUCCION!J165+0.5)),"OK","ERROR"),"NO ACTIVA") -> NO ACTIVA | K15: =IF(01_INPUTS!K17,IF(AND((_ENGINE_PRODUCCION!K83<=_ENGINE_PRODUCCION!K80+0.5),(_ENGINE_PRODUCCION!K95<=_ENGINE_PRODUCCION!K92+0.5),(_ENGINE_PRODUCCION!K107<=_ENGINE_PRODUCCION!K104+0.5),(_ENGINE_PRODUCCION!K119<=_ENGINE_PRODUCCION!K116+0.5),(_ENGINE_PRODUCCION!K132<=_ENGINE_PRODUCCION!K129+0.5),(_ENGINE_PRODUCCION!K144<=_ENGINE_PRODUCCION!K141+0.5),(_ENGINE_PRODUCCION!K156<=_ENGINE_PRODUCCION!K153+0.5),(_ENGINE_PRODUCCION!K168<=_ENGINE_PRODUCCION!K165+0.5)),"OK","ERROR"),"NO ACTIVA") -> NO ACTIVA | L15: =IF(01_INPUTS!L17,IF(AND((_ENGINE_PRODUCCION!L83<=_ENGINE_PRODUCCION!L80+0.5),(_ENGINE_PRODUCCION!L95<=_ENGINE_PRODUCCION!L92+0.5),(_ENGINE_PRODUCCION!L107<=_ENGINE_PRODUCCION!L104+0.5),(_ENGINE_PRODUCCION!L119<=_ENGINE_PRODUCCION!L116+0.5),(_ENGINE_PRODUCCION!L132<=_ENGINE_PRODUCCION!L129+0.5),(_ENGINE_PRODUCCION!L144<=_ENGINE_PRODUCCION!L141+0.5),(_ENGINE_PRODUCCION!L156<=_ENGINE_PRODUCCION!L153+0.5),(_ENGINE_PRODUCCION!L168<=_ENGINE_PRODUCCION!L165+0.5)),"OK","ERROR"),"NO ACTIVA") -> NO ACTIVA | M15: =IF(01_INPUTS!M17,IF(AND((_ENGINE_PRODUCCION!M83<=_ENGINE_PRODUCCION!M80+0.5),(_ENGINE_PRODUCCION!M95<=_ENGINE_PRODUCCION!M92+0.5),(_ENGINE_PRODUCCION!M107<=_ENGINE_PRODUCCION!M104+0.5),(_ENGINE_PRODUCCION!M119<=_ENGINE_PRODUCCION!M116+0.5),(_ENGINE_PRODUCCION!M132<=_ENGINE_PRODUCCION!M129+0.5),(_ENGINE_PRODUCCION!M144<=_ENGINE_PRODUCCION!M141+0.5),(_ENGINE_PRODUCCION!M156<=_ENGINE_PRODUCCION!M153+0.5),(_ENGINE_PRODUCCION!M168<=_ENGINE_PRODUCCION!M165+0.5)),"OK","ERROR"),"NO ACTIVA") -> NO ACTIVA | N15: =IF(01_INPUTS!N17,IF(AND((_ENGINE_PRODUCCION!N83<=_ENGINE_PRODUCCION!N80+0.5),(_ENGINE_PRODUCCION!N95<=_ENGINE_PRODUCCION!N92+0.5),(_ENGINE_PRODUCCION!N107<=_ENGINE_PRODUCCION!N104+0.5),(_ENGINE_PRODUCCION!N119<=_ENGINE_PRODUCCION!N116+0.5),(_ENGINE_PRODUCCION!N132<=_ENGINE_PRODUCCION!N129+0.5),(_ENGINE_PRODUCCION!N144<=_ENGINE_PRODUCCION!N141+0.5),(_ENGINE_PRODUCCION!N156<=_ENGINE_PRODUCCION!N153+0.5),(_ENGINE_PRODUCCION!N168<=_ENGINE_PRODUCCION!N165+0.5)),"OK","ERROR"),"NO ACTIVA") -> NO ACTIVA | O15: =IF(01_INPUTS!O17,IF(AND((_ENGINE_PRODUCCION!O83<=_ENGINE_PRODUCCION!O80+0.5),(_ENGINE_PRODUCCION!O95<=_ENGINE_PRODUCCION!O92+0.5),(_ENGINE_PRODUCCION!O107<=_ENGINE_PRODUCCION!O104+0.5),(_ENGINE_PRODUCCION!O119<=_ENGINE_PRODUCCION!O116+0.5),(_ENGINE_PRODUCCION!O132<=_ENGINE_PRODUCCION!O129+0.5),(_ENGINE_PRODUCCION!O144<=_ENGINE_PRODUCCION!O141+0.5),(_ENGINE_PRODUCCION!O156<=_ENGINE_PRODUCCION!O153+0.5),(_ENGINE_PRODUCCION!O168<=_ENGINE_PRODUCCION!O165+0.5)),"OK","ERROR"),"NO ACTIVA") -> NO ACTIVA | P15: =IF(01_INPUTS!P17,IF(AND((_ENGINE_PRODUCCION!P83<=_ENGINE_PRODUCCION!P80+0.5),(_ENGINE_PRODUCCION!P95<=_ENGINE_PRODUCCION!P92+0.5),(_ENGINE_PRODUCCION!P107<=_ENGINE_PRODUCCION!P104+0.5),(_ENGINE_PRODUCCION!P119<=_ENGINE_PRODUCCION!P116+0.5),(_ENGINE_PRODUCCION!P132<=_ENGINE_PRODUCCION!P129+0.5),(_ENGINE_PRODUCCION!P144<=_ENGINE_PRODUCCION!P141+0.5),(_ENGINE_PRODUCCION!P156<=_ENGINE_PRODUCCION!P153+0.5),(_ENGINE_PRODUCCION!P168<=_ENGINE_PRODUCCION!P165+0.5)),"OK","ERROR"),"NO ACTIVA") -> NO ACTIVA | ... S15: =IF(01_INPUTS!S17,IF(AND((_ENGINE_PRODUCCION!S83<=_ENGINE_PRODUCCION!S80+0.5),(_ENGINE_PRODUCCION!S95<=_ENGINE_PRODUCCION!S92+0.5),(_ENGINE_PRODUCCION!S107<=_ENGINE_PRODUCCION!S104+0.5),(_ENGINE_PRODUCCION!S119<=_ENGINE_PRODUCCION!S116+0.5),(_ENGINE_PRODUCCION!S132<=_ENGINE_PRODUCCION!S129+0.5),(_ENGINE_PRODUCCION!S144<=_ENGINE_PRODUCCION!S141+0.5),(_ENGINE_PRODUCCION!S156<=_ENGINE_PRODUCCION!S153+0.5),(_ENGINE_PRODUCCION!S168<=_ENGINE_PRODUCCION!S165+0.5)),"OK","ERROR"),"NO ACTIVA") -> NO ACTIVA
A16: Inventario final ≥ 0 (todas las áreas/tecnología) | B16: CONTROL | G16: =IF(AND((_ENGINE_PRODUCCION!G85>=-0.5),(_ENGINE_PRODUCCION!G97>=-0.5),(_ENGINE_PRODUCCION!G109>=-0.5),(_ENGINE_PRODUCCION!G121>=-0.5),(_ENGINE_PRODUCCION!G134>=-0.5),(_ENGINE_PRODUCCION!G146>=-0.5),(_ENGINE_PRODUCCION!G158>=-0.5),(_ENGINE_PRODUCCION!G170>=-0.5)),"OK","ERROR") -> OK | H16: =IF(AND((_ENGINE_PRODUCCION!H85>=-0.5),(_ENGINE_PRODUCCION!H97>=-0.5),(_ENGINE_PRODUCCION!H109>=-0.5),(_ENGINE_PRODUCCION!H121>=-0.5),(_ENGINE_PRODUCCION!H134>=-0.5),(_ENGINE_PRODUCCION!H146>=-0.5),(_ENGINE_PRODUCCION!H158>=-0.5),(_ENGINE_PRODUCCION!H170>=-0.5)),"OK","ERROR") -> OK | I16: =IF(01_INPUTS!I17,IF(AND((_ENGINE_PRODUCCION!I85>=-0.5),(_ENGINE_PRODUCCION!I97>=-0.5),(_ENGINE_PRODUCCION!I109>=-0.5),(_ENGINE_PRODUCCION!I121>=-0.5),(_ENGINE_PRODUCCION!I134>=-0.5),(_ENGINE_PRODUCCION!I146>=-0.5),(_ENGINE_PRODUCCION!I158>=-0.5),(_ENGINE_PRODUCCION!I170>=-0.5)),"OK","ERROR"),"NO ACTIVA") -> OK | J16: =IF(01_INPUTS!J17,IF(AND((_ENGINE_PRODUCCION!J85>=-0.5),(_ENGINE_PRODUCCION!J97>=-0.5),(_ENGINE_PRODUCCION!J109>=-0.5),(_ENGINE_PRODUCCION!J121>=-0.5),(_ENGINE_PRODUCCION!J134>=-0.5),(_ENGINE_PRODUCCION!J146>=-0.5),(_ENGINE_PRODUCCION!J158>=-0.5),(_ENGINE_PRODUCCION!J170>=-0.5)),"OK","ERROR"),"NO ACTIVA") -> NO ACTIVA | K16: =IF(01_INPUTS!K17,IF(AND((_ENGINE_PRODUCCION!K85>=-0.5),(_ENGINE_PRODUCCION!K97>=-0.5),(_ENGINE_PRODUCCION!K109>=-0.5),(_ENGINE_PRODUCCION!K121>=-0.5),(_ENGINE_PRODUCCION!K134>=-0.5),(_ENGINE_PRODUCCION!K146>=-0.5),(_ENGINE_PRODUCCION!K158>=-0.5),(_ENGINE_PRODUCCION!K170>=-0.5)),"OK","ERROR"),"NO ACTIVA") -> NO ACTIVA | L16: =IF(01_INPUTS!L17,IF(AND((_ENGINE_PRODUCCION!L85>=-0.5),(_ENGINE_PRODUCCION!L97>=-0.5),(_ENGINE_PRODUCCION!L109>=-0.5),(_ENGINE_PRODUCCION!L121>=-0.5),(_ENGINE_PRODUCCION!L134>=-0.5),(_ENGINE_PRODUCCION!L146>=-0.5),(_ENGINE_PRODUCCION!L158>=-0.5),(_ENGINE_PRODUCCION!L170>=-0.5)),"OK","ERROR"),"NO ACTIVA") -> NO ACTIVA | M16: =IF(01_INPUTS!M17,IF(AND((_ENGINE_PRODUCCION!M85>=-0.5),(_ENGINE_PRODUCCION!M97>=-0.5),(_ENGINE_PRODUCCION!M109>=-0.5),(_ENGINE_PRODUCCION!M121>=-0.5),(_ENGINE_PRODUCCION!M134>=-0.5),(_ENGINE_PRODUCCION!M146>=-0.5),(_ENGINE_PRODUCCION!M158>=-0.5),(_ENGINE_PRODUCCION!M170>=-0.5)),"OK","ERROR"),"NO ACTIVA") -> NO ACTIVA | N16: =IF(01_INPUTS!N17,IF(AND((_ENGINE_PRODUCCION!N85>=-0.5),(_ENGINE_PRODUCCION!N97>=-0.5),(_ENGINE_PRODUCCION!N109>=-0.5),(_ENGINE_PRODUCCION!N121>=-0.5),(_ENGINE_PRODUCCION!N134>=-0.5),(_ENGINE_PRODUCCION!N146>=-0.5),(_ENGINE_PRODUCCION!N158>=-0.5),(_ENGINE_PRODUCCION!N170>=-0.5)),"OK","ERROR"),"NO ACTIVA") -> NO ACTIVA | O16: =IF(01_INPUTS!O17,IF(AND((_ENGINE_PRODUCCION!O85>=-0.5),(_ENGINE_PRODUCCION!O97>=-0.5),(_ENGINE_PRODUCCION!O109>=-0.5),(_ENGINE_PRODUCCION!O121>=-0.5),(_ENGINE_PRODUCCION!O134>=-0.5),(_ENGINE_PRODUCCION!O146>=-0.5),(_ENGINE_PRODUCCION!O158>=-0.5),(_ENGINE_PRODUCCION!O170>=-0.5)),"OK","ERROR"),"NO ACTIVA") -> NO ACTIVA | P16: =IF(01_INPUTS!P17,IF(AND((_ENGINE_PRODUCCION!P85>=-0.5),(_ENGINE_PRODUCCION!P97>=-0.5),(_ENGINE_PRODUCCION!P109>=-0.5),(_ENGINE_PRODUCCION!P121>=-0.5),(_ENGINE_PRODUCCION!P134>=-0.5),(_ENGINE_PRODUCCION!P146>=-0.5),(_ENGINE_PRODUCCION!P158>=-0.5),(_ENGINE_PRODUCCION!P170>=-0.5)),"OK","ERROR"),"NO ACTIVA") -> NO ACTIVA | ... S16: =IF(01_INPUTS!S17,IF(AND((_ENGINE_PRODUCCION!S85>=-0.5),(_ENGINE_PRODUCCION!S97>=-0.5),(_ENGINE_PRODUCCION!S109>=-0.5),(_ENGINE_PRODUCCION!S121>=-0.5),(_ENGINE_PRODUCCION!S134>=-0.5),(_ENGINE_PRODUCCION!S146>=-0.5),(_ENGINE_PRODUCCION!S158>=-0.5),(_ENGINE_PRODUCCION!S170>=-0.5)),"OK","ERROR"),"NO ACTIVA") -> NO ACTIVA
A17: Demanda insatisfecha ≥ 0 (todos los mercados/tecnología) | B17: CONTROL | G17: =IF(AND((_ENGINE_MERCADO!G191>=-0.5),(_ENGINE_MERCADO!G196>=-0.5),(_ENGINE_MERCADO!G201>=-0.5),(_ENGINE_MERCADO!G206>=-0.5),(_ENGINE_MERCADO!G211>=-0.5),(_ENGINE_MERCADO!G216>=-0.5),(_ENGINE_MERCADO!G221>=-0.5),(_ENGINE_MERCADO!G226>=-0.5),(_ENGINE_MERCADO!G231>=-0.5),(_ENGINE_MERCADO!G236>=-0.5),(_ENGINE_MERCADO!G241>=-0.5),(_ENGINE_MERCADO!G246>=-0.5)),"OK","ERROR") -> OK | H17: =IF(AND((_ENGINE_MERCADO!H191>=-0.5),(_ENGINE_MERCADO!H196>=-0.5),(_ENGINE_MERCADO!H201>=-0.5),(_ENGINE_MERCADO!H206>=-0.5),(_ENGINE_MERCADO!H211>=-0.5),(_ENGINE_MERCADO!H216>=-0.5),(_ENGINE_MERCADO!H221>=-0.5),(_ENGINE_MERCADO!H226>=-0.5),(_ENGINE_MERCADO!H231>=-0.5),(_ENGINE_MERCADO!H236>=-0.5),(_ENGINE_MERCADO!H241>=-0.5),(_ENGINE_MERCADO!H246>=-0.5)),"OK","ERROR") -> OK | I17: =IF(01_INPUTS!I17,IF(AND((_ENGINE_MERCADO!I191>=-0.5),(_ENGINE_MERCADO!I196>=-0.5),(_ENGINE_MERCADO!I201>=-0.5),(_ENGINE_MERCADO!I206>=-0.5),(_ENGINE_MERCADO!I211>=-0.5),(_ENGINE_MERCADO!I216>=-0.5),(_ENGINE_MERCADO!I221>=-0.5),(_ENGINE_MERCADO!I226>=-0.5),(_ENGINE_MERCADO!I231>=-0.5),(_ENGINE_MERCADO!I236>=-0.5),(_ENGINE_MERCADO!I241>=-0.5),(_ENGINE_MERCADO!I246>=-0.5)),"OK","ERROR"),"NO ACTIVA") -> OK | J17: =IF(01_INPUTS!J17,IF(AND((_ENGINE_MERCADO!J191>=-0.5),(_ENGINE_MERCADO!J196>=-0.5),(_ENGINE_MERCADO!J201>=-0.5),(_ENGINE_MERCADO!J206>=-0.5),(_ENGINE_MERCADO!J211>=-0.5),(_ENGINE_MERCADO!J216>=-0.5),(_ENGINE_MERCADO!J221>=-0.5),(_ENGINE_MERCADO!J226>=-0.5),(_ENGINE_MERCADO!J231>=-0.5),(_ENGINE_MERCADO!J236>=-0.5),(_ENGINE_MERCADO!J241>=-0.5),(_ENGINE_MERCADO!J246>=-0.5)),"OK","ERROR"),"NO ACTIVA") -> NO ACTIVA | K17: =IF(01_INPUTS!K17,IF(AND((_ENGINE_MERCADO!K191>=-0.5),(_ENGINE_MERCADO!K196>=-0.5),(_ENGINE_MERCADO!K201>=-0.5),(_ENGINE_MERCADO!K206>=-0.5),(_ENGINE_MERCADO!K211>=-0.5),(_ENGINE_MERCADO!K216>=-0.5),(_ENGINE_MERCADO!K221>=-0.5),(_ENGINE_MERCADO!K226>=-0.5),(_ENGINE_MERCADO!K231>=-0.5),(_ENGINE_MERCADO!K236>=-0.5),(_ENGINE_MERCADO!K241>=-0.5),(_ENGINE_MERCADO!K246>=-0.5)),"OK","ERROR"),"NO ACTIVA") -> NO ACTIVA | L17: =IF(01_INPUTS!L17,IF(AND((_ENGINE_MERCADO!L191>=-0.5),(_ENGINE_MERCADO!L196>=-0.5),(_ENGINE_MERCADO!L201>=-0.5),(_ENGINE_MERCADO!L206>=-0.5),(_ENGINE_MERCADO!L211>=-0.5),(_ENGINE_MERCADO!L216>=-0.5),(_ENGINE_MERCADO!L221>=-0.5),(_ENGINE_MERCADO!L226>=-0.5),(_ENGINE_MERCADO!L231>=-0.5),(_ENGINE_MERCADO!L236>=-0.5),(_ENGINE_MERCADO!L241>=-0.5),(_ENGINE_MERCADO!L246>=-0.5)),"OK","ERROR"),"NO ACTIVA") -> NO ACTIVA | M17: =IF(01_INPUTS!M17,IF(AND((_ENGINE_MERCADO!M191>=-0.5),(_ENGINE_MERCADO!M196>=-0.5),(_ENGINE_MERCADO!M201>=-0.5),(_ENGINE_MERCADO!M206>=-0.5),(_ENGINE_MERCADO!M211>=-0.5),(_ENGINE_MERCADO!M216>=-0.5),(_ENGINE_MERCADO!M221>=-0.5),(_ENGINE_MERCADO!M226>=-0.5),(_ENGINE_MERCADO!M231>=-0.5),(_ENGINE_MERCADO!M236>=-0.5),(_ENGINE_MERCADO!M241>=-0.5),(_ENGINE_MERCADO!M246>=-0.5)),"OK","ERROR"),"NO ACTIVA") -> NO ACTIVA | N17: =IF(01_INPUTS!N17,IF(AND((_ENGINE_MERCADO!N191>=-0.5),(_ENGINE_MERCADO!N196>=-0.5),(_ENGINE_MERCADO!N201>=-0.5),(_ENGINE_MERCADO!N206>=-0.5),(_ENGINE_MERCADO!N211>=-0.5),(_ENGINE_MERCADO!N216>=-0.5),(_ENGINE_MERCADO!N221>=-0.5),(_ENGINE_MERCADO!N226>=-0.5),(_ENGINE_MERCADO!N231>=-0.5),(_ENGINE_MERCADO!N236>=-0.5),(_ENGINE_MERCADO!N241>=-0.5),(_ENGINE_MERCADO!N246>=-0.5)),"OK","ERROR"),"NO ACTIVA") -> NO ACTIVA | O17: =IF(01_INPUTS!O17,IF(AND((_ENGINE_MERCADO!O191>=-0.5),(_ENGINE_MERCADO!O196>=-0.5),(_ENGINE_MERCADO!O201>=-0.5),(_ENGINE_MERCADO!O206>=-0.5),(_ENGINE_MERCADO!O211>=-0.5),(_ENGINE_MERCADO!O216>=-0.5),(_ENGINE_MERCADO!O221>=-0.5),(_ENGINE_MERCADO!O226>=-0.5),(_ENGINE_MERCADO!O231>=-0.5),(_ENGINE_MERCADO!O236>=-0.5),(_ENGINE_MERCADO!O241>=-0.5),(_ENGINE_MERCADO!O246>=-0.5)),"OK","ERROR"),"NO ACTIVA") -> NO ACTIVA | P17: =IF(01_INPUTS!P17,IF(AND((_ENGINE_MERCADO!P191>=-0.5),(_ENGINE_MERCADO!P196>=-0.5),(_ENGINE_MERCADO!P201>=-0.5),(_ENGINE_MERCADO!P206>=-0.5),(_ENGINE_MERCADO!P211>=-0.5),(_ENGINE_MERCADO!P216>=-0.5),(_ENGINE_MERCADO!P221>=-0.5),(_ENGINE_MERCADO!P226>=-0.5),(_ENGINE_MERCADO!P231>=-0.5),(_ENGINE_MERCADO!P236>=-0.5),(_ENGINE_MERCADO!P241>=-0.5),(_ENGINE_MERCADO!P246>=-0.5)),"OK","ERROR"),"NO ACTIVA") -> NO ACTIVA | ... S17: =IF(01_INPUTS!S17,IF(AND((_ENGINE_MERCADO!S191>=-0.5),(_ENGINE_MERCADO!S196>=-0.5),(_ENGINE_MERCADO!S201>=-0.5),(_ENGINE_MERCADO!S206>=-0.5),(_ENGINE_MERCADO!S211>=-0.5),(_ENGINE_MERCADO!S216>=-0.5),(_ENGINE_MERCADO!S221>=-0.5),(_ENGINE_MERCADO!S226>=-0.5),(_ENGINE_MERCADO!S231>=-0.5),(_ENGINE_MERCADO!S236>=-0.5),(_ENGINE_MERCADO!S241>=-0.5),(_ENGINE_MERCADO!S246>=-0.5)),"OK","ERROR"),"NO ACTIVA") -> NO ACTIVA
A18: Producción propia ≤ Capacidad operativa (por área) | B18: CONTROL | G18: =IF(AND((_ENGINE_PRODUCCION!G17<=_ENGINE_PRODUCCION!G16+0.5),(_ENGINE_PRODUCCION!G26<=_ENGINE_PRODUCCION!G25+0.5)),"OK","ERROR") -> OK | H18: =IF(AND((_ENGINE_PRODUCCION!H17<=_ENGINE_PRODUCCION!H16+0.5),(_ENGINE_PRODUCCION!H26<=_ENGINE_PRODUCCION!H25+0.5)),"OK","ERROR") -> OK | I18: =IF(01_INPUTS!I17,IF(AND((_ENGINE_PRODUCCION!I17<=_ENGINE_PRODUCCION!I16+0.5),(_ENGINE_PRODUCCION!I26<=_ENGINE_PRODUCCION!I25+0.5)),"OK","ERROR"),"NO ACTIVA") -> OK | J18: =IF(01_INPUTS!J17,IF(AND((_ENGINE_PRODUCCION!J17<=_ENGINE_PRODUCCION!J16+0.5),(_ENGINE_PRODUCCION!J26<=_ENGINE_PRODUCCION!J25+0.5)),"OK","ERROR"),"NO ACTIVA") -> NO ACTIVA | K18: =IF(01_INPUTS!K17,IF(AND((_ENGINE_PRODUCCION!K17<=_ENGINE_PRODUCCION!K16+0.5),(_ENGINE_PRODUCCION!K26<=_ENGINE_PRODUCCION!K25+0.5)),"OK","ERROR"),"NO ACTIVA") -> NO ACTIVA | L18: =IF(01_INPUTS!L17,IF(AND((_ENGINE_PRODUCCION!L17<=_ENGINE_PRODUCCION!L16+0.5),(_ENGINE_PRODUCCION!L26<=_ENGINE_PRODUCCION!L25+0.5)),"OK","ERROR"),"NO ACTIVA") -> NO ACTIVA | M18: =IF(01_INPUTS!M17,IF(AND((_ENGINE_PRODUCCION!M17<=_ENGINE_PRODUCCION!M16+0.5),(_ENGINE_PRODUCCION!M26<=_ENGINE_PRODUCCION!M25+0.5)),"OK","ERROR"),"NO ACTIVA") -> NO ACTIVA | N18: =IF(01_INPUTS!N17,IF(AND((_ENGINE_PRODUCCION!N17<=_ENGINE_PRODUCCION!N16+0.5),(_ENGINE_PRODUCCION!N26<=_ENGINE_PRODUCCION!N25+0.5)),"OK","ERROR"),"NO ACTIVA") -> NO ACTIVA | O18: =IF(01_INPUTS!O17,IF(AND((_ENGINE_PRODUCCION!O17<=_ENGINE_PRODUCCION!O16+0.5),(_ENGINE_PRODUCCION!O26<=_ENGINE_PRODUCCION!O25+0.5)),"OK","ERROR"),"NO ACTIVA") -> NO ACTIVA | P18: =IF(01_INPUTS!P17,IF(AND((_ENGINE_PRODUCCION!P17<=_ENGINE_PRODUCCION!P16+0.5),(_ENGINE_PRODUCCION!P26<=_ENGINE_PRODUCCION!P25+0.5)),"OK","ERROR"),"NO ACTIVA") -> NO ACTIVA | ... S18: =IF(01_INPUTS!S17,IF(AND((_ENGINE_PRODUCCION!S17<=_ENGINE_PRODUCCION!S16+0.5),(_ENGINE_PRODUCCION!S26<=_ENGINE_PRODUCCION!S25+0.5)),"OK","ERROR"),"NO ACTIVA") -> NO ACTIVA
A19: Asignación multi-origen: estado OK en Sección D de _ENGINE_MERCADO | B19: CONTROL | G19: =IF(AND((_ENGINE_MERCADO!G189="OK"),(_ENGINE_MERCADO!G194="OK"),(_ENGINE_MERCADO!G199="OK"),(_ENGINE_MERCADO!G204="OK"),(_ENGINE_MERCADO!G209="OK"),(_ENGINE_MERCADO!G214="OK"),(_ENGINE_MERCADO!G219="OK"),(_ENGINE_MERCADO!G224="OK"),(_ENGINE_MERCADO!G229="OK"),(_ENGINE_MERCADO!G234="OK"),(_ENGINE_MERCADO!G239="OK"),(_ENGINE_MERCADO!G244="OK")),"OK","ERROR") -> OK | H19: =IF(AND((_ENGINE_MERCADO!H189="OK"),(_ENGINE_MERCADO!H194="OK"),(_ENGINE_MERCADO!H199="OK"),(_ENGINE_MERCADO!H204="OK"),(_ENGINE_MERCADO!H209="OK"),(_ENGINE_MERCADO!H214="OK"),(_ENGINE_MERCADO!H219="OK"),(_ENGINE_MERCADO!H224="OK"),(_ENGINE_MERCADO!H229="OK"),(_ENGINE_MERCADO!H234="OK"),(_ENGINE_MERCADO!H239="OK"),(_ENGINE_MERCADO!H244="OK")),"OK","ERROR") -> OK | I19: =IF(01_INPUTS!I17,IF(AND((_ENGINE_MERCADO!I189="OK"),(_ENGINE_MERCADO!I194="OK"),(_ENGINE_MERCADO!I199="OK"),(_ENGINE_MERCADO!I204="OK"),(_ENGINE_MERCADO!I209="OK"),(_ENGINE_MERCADO!I214="OK"),(_ENGINE_MERCADO!I219="OK"),(_ENGINE_MERCADO!I224="OK"),(_ENGINE_MERCADO!I229="OK"),(_ENGINE_MERCADO!I234="OK"),(_ENGINE_MERCADO!I239="OK"),(_ENGINE_MERCADO!I244="OK")),"OK","ERROR"),"NO ACTIVA") -> OK | J19: =IF(01_INPUTS!J17,IF(AND((_ENGINE_MERCADO!J189="OK"),(_ENGINE_MERCADO!J194="OK"),(_ENGINE_MERCADO!J199="OK"),(_ENGINE_MERCADO!J204="OK"),(_ENGINE_MERCADO!J209="OK"),(_ENGINE_MERCADO!J214="OK"),(_ENGINE_MERCADO!J219="OK"),(_ENGINE_MERCADO!J224="OK"),(_ENGINE_MERCADO!J229="OK"),(_ENGINE_MERCADO!J234="OK"),(_ENGINE_MERCADO!J239="OK"),(_ENGINE_MERCADO!J244="OK")),"OK","ERROR"),"NO ACTIVA") -> NO ACTIVA | K19: =IF(01_INPUTS!K17,IF(AND((_ENGINE_MERCADO!K189="OK"),(_ENGINE_MERCADO!K194="OK"),(_ENGINE_MERCADO!K199="OK"),(_ENGINE_MERCADO!K204="OK"),(_ENGINE_MERCADO!K209="OK"),(_ENGINE_MERCADO!K214="OK"),(_ENGINE_MERCADO!K219="OK"),(_ENGINE_MERCADO!K224="OK"),(_ENGINE_MERCADO!K229="OK"),(_ENGINE_MERCADO!K234="OK"),(_ENGINE_MERCADO!K239="OK"),(_ENGINE_MERCADO!K244="OK")),"OK","ERROR"),"NO ACTIVA") -> NO ACTIVA | L19: =IF(01_INPUTS!L17,IF(AND((_ENGINE_MERCADO!L189="OK"),(_ENGINE_MERCADO!L194="OK"),(_ENGINE_MERCADO!L199="OK"),(_ENGINE_MERCADO!L204="OK"),(_ENGINE_MERCADO!L209="OK"),(_ENGINE_MERCADO!L214="OK"),(_ENGINE_MERCADO!L219="OK"),(_ENGINE_MERCADO!L224="OK"),(_ENGINE_MERCADO!L229="OK"),(_ENGINE_MERCADO!L234="OK"),(_ENGINE_MERCADO!L239="OK"),(_ENGINE_MERCADO!L244="OK")),"OK","ERROR"),"NO ACTIVA") -> NO ACTIVA | M19: =IF(01_INPUTS!M17,IF(AND((_ENGINE_MERCADO!M189="OK"),(_ENGINE_MERCADO!M194="OK"),(_ENGINE_MERCADO!M199="OK"),(_ENGINE_MERCADO!M204="OK"),(_ENGINE_MERCADO!M209="OK"),(_ENGINE_MERCADO!M214="OK"),(_ENGINE_MERCADO!M219="OK"),(_ENGINE_MERCADO!M224="OK"),(_ENGINE_MERCADO!M229="OK"),(_ENGINE_MERCADO!M234="OK"),(_ENGINE_MERCADO!M239="OK"),(_ENGINE_MERCADO!M244="OK")),"OK","ERROR"),"NO ACTIVA") -> NO ACTIVA | N19: =IF(01_INPUTS!N17,IF(AND((_ENGINE_MERCADO!N189="OK"),(_ENGINE_MERCADO!N194="OK"),(_ENGINE_MERCADO!N199="OK"),(_ENGINE_MERCADO!N204="OK"),(_ENGINE_MERCADO!N209="OK"),(_ENGINE_MERCADO!N214="OK"),(_ENGINE_MERCADO!N219="OK"),(_ENGINE_MERCADO!N224="OK"),(_ENGINE_MERCADO!N229="OK"),(_ENGINE_MERCADO!N234="OK"),(_ENGINE_MERCADO!N239="OK"),(_ENGINE_MERCADO!N244="OK")),"OK","ERROR"),"NO ACTIVA") -> NO ACTIVA | O19: =IF(01_INPUTS!O17,IF(AND((_ENGINE_MERCADO!O189="OK"),(_ENGINE_MERCADO!O194="OK"),(_ENGINE_MERCADO!O199="OK"),(_ENGINE_MERCADO!O204="OK"),(_ENGINE_MERCADO!O209="OK"),(_ENGINE_MERCADO!O214="OK"),(_ENGINE_MERCADO!O219="OK"),(_ENGINE_MERCADO!O224="OK"),(_ENGINE_MERCADO!O229="OK"),(_ENGINE_MERCADO!O234="OK"),(_ENGINE_MERCADO!O239="OK"),(_ENGINE_MERCADO!O244="OK")),"OK","ERROR"),"NO ACTIVA") -> NO ACTIVA | P19: =IF(01_INPUTS!P17,IF(AND((_ENGINE_MERCADO!P189="OK"),(_ENGINE_MERCADO!P194="OK"),(_ENGINE_MERCADO!P199="OK"),(_ENGINE_MERCADO!P204="OK"),(_ENGINE_MERCADO!P209="OK"),(_ENGINE_MERCADO!P214="OK"),(_ENGINE_MERCADO!P219="OK"),(_ENGINE_MERCADO!P224="OK"),(_ENGINE_MERCADO!P229="OK"),(_ENGINE_MERCADO!P234="OK"),(_ENGINE_MERCADO!P239="OK"),(_ENGINE_MERCADO!P244="OK")),"OK","ERROR"),"NO ACTIVA") -> NO ACTIVA | ... S19: =IF(01_INPUTS!S17,IF(AND((_ENGINE_MERCADO!S189="OK"),(_ENGINE_MERCADO!S194="OK"),(_ENGINE_MERCADO!S199="OK"),(_ENGINE_MERCADO!S204="OK"),(_ENGINE_MERCADO!S209="OK"),(_ENGINE_MERCADO!S214="OK"),(_ENGINE_MERCADO!S219="OK"),(_ENGINE_MERCADO!S224="OK"),(_ENGINE_MERCADO!S229="OK"),(_ENGINE_MERCADO!S234="OK"),(_ENGINE_MERCADO!S239="OK"),(_ENGINE_MERCADO!S244="OK")),"OK","ERROR"),"NO ACTIVA") -> NO ACTIVA
A21: C · TERCERIZACIÓN, DECISIONES Y CONDICIONES (D2/D8/D9)
